Workbook

Sheet Contract Log
A1: Project Name | C1: Address | D1: Estimated Start Date | E1: Estimated Completion Date | F1: Vendor | G1: PO# | H1: Contract Status | I1: Vendor | J1: PO# | K1: Contract Status | L1: Vendor | M1: PO# | N1: Contract Status | O1: Vendor | P1: PO# | Q1: Contract Status | R1: Vendor | S1: PO# | T1: Contract Status
A2: HRP Holbrook | C2: Asheville, NC | D2: 45566 | F2: Zavala | G2: 2411 $243,965 | H2: Fully Executed | I2: Pristine | K2: Fully Executed
A3: Pines at Peach | C3: Raleigh, NC | D3: 45474 | F3: Pristine | G3: 2216 $337,788 | H3: Fully Executed | I3: Zavala-NO PO | L3: Bruzz-NO PO | N3: Fully Executed
A4: Gatebay (Inv 2080/2081/2103) | C4: Henderson, NC | D4: 45566 | E4: 45597 | F4: Pristine | G4: 2378 $38,896 | H4: Fully Executed
A5: Mountain Glen | C5: Brevard, NC | D5: 45536 | F5: Zavala | G5: 2366 $56,964.02 | H5: Fully Executed | I5: Pristine | J5: 2496 $88,825.00 | K5: Fully Executed | L5: Martinez-NO PO | O5: Towa-NO PO | R5: JGBR - Has PO's but not sure how to get this to them now? | V5: Missing info to draft contract
A6: Aaron Mills | C6: Martinsville, VA | D6: 45802 | I6: Pristine-Per OC PO not ready 8/12/25 | J6: Chris 4/28
A7: DHIC: Sedgebrook | C7: Cary, NC | D7: 45658 | F7: Zavala | G7: 2526 | H7: Fully Executed | I7: JSH Windows/Siding | J7: 2862/2863 | K7: Fully Executed | L7: Anzola Trim-NO PO
A8: DHIC: Jeffries Ridge (Alli) | C8: Raleigh, NC | D8: 45627 | F8: Zavala | G8: 2523 | H8: Fully Executed | I8: Pristine | J8: 2842 $201,646.00 | K8: Fully Executed | L8: CIE (interior) | M8: 2557 $26,226.00 *PO had note 'need to be edited' - emailed OC 6/25 | O8: Towa | P8: no PO in QB | V8: Created - Awaiting Signatures
A9: DHIC: Ripley Station (Starting interior & siding July 2025) | C9: Raleigh, NC | F9: Zavala | G9: 2525 | H9: Fully Executed | I9: Rubio & Pristine | J9: 3170, 3243, 3246-Rubio; 3244, 3245 Pristine | K9: Rubio 3170 Fully Executed; Pristine 3244 Fully Executed; Rubio 3243 Fully Executed; Pristine 3403 Fully Executed; Rubio 3246 Fully Executed; Pristine 3245 created by SA and awaiting signatures | L9: Anzola Trim (Joe) wait for PO | O9: Towa-NO PO | R9: Amber | S9: NO PO# | T9: Created - Awaiting Signatures | V9: Sub Executed - Need Wesco Signatures
A10: DHIC: Madison Glen | C10: Raleigh, NC | F10: Zavala | G10: 2524 & 3883 | H10: Fully Executed | I10: Pristine (Siding & WIndows) | J10: 3884 | K10: Created - Awaiting Signatures | L10: Anzola Trim (Joe) wait for PO | O10: Towa-NO PO | V10: Fully Executed
A11: DHIC: Avonlea Apartments | C11: Raleigh, NC | D11: 45658 | F11: Zavala | G11: 2521 | H11: Fully Executed | I11: Rubio Siding/Windows | J11: 2960 $286,564.00 3062 $24,045.00 | K11: Fully Executed | L11: Anzola Trim (Joe) wait for PO | O11: Towa-NO PO | R11: JSH - NO PO | V11: To Be Completed
A12: DHIC: Tryon Grove | C12: Raleigh, NC | F12: Zavala-8/12 OC checking PO - 9/24/25 Updated to Rooster Roofing RK | G12: Rooster Roofing 3322 | H12: Fully Executed | I12: JSH Windows/Siding Gave to Joe 8/7/25 & 9/3/25 | J12: 3164, 3188, 3167, 3190 | K12: Created - Awaiting Signatures | L12: Pristine | M12: 3163-Bldg 2500 only | N12: Fully Executed | O12: Towa-NO PO | R12: JSH chase
A13: DHIC: Highland Village | C13: Cary, NC | F13: Zavala | G13: 2522 | H13: Fully Executed | I13: TBD Siding | L13: CIE (interior) or Anzola | O13: Towa-NO PO
A14: Bond Deal 3: Ridgeway (not started - Aug/Sept 2025 start) | C14: Taylorsville, NC | F14: Zavala | G14: 2443 (Oscar to follow up 6/18) | H14: Created - Awaiting Signatures | L14: Bruzz? | O14: Towa-NO PO
A15: Bond Deal 3: Brookside | C15: Maxton, NC | F15: Pristine | G15: 2720? Note: SA need OC help | I15: Anzola/Martinez | L15: Guillermo Shutters
A16: Bond Deal 3: Berry Park | C16: Chadbourn, NC | I16: Bruzz Interior | L16: Guillermo Shutters | O16: Towa-NO PO
A17: Bond Deal 3: Chadwick Place | C17: Chadbourn, NC | I17: Bruzz Interior | L17: Guillermo Shutters - not set up
A18: Bond Deal 3: Piney Pointe | C18: Hamlet, NC | I18: Martinez | O18: Towa-NO PO
A19: Bond Deal 3: Brittany Place | C19: Washington, NC | I19: Martinez | L19: Bruzz
A20: Bond Deal 3: British Woods ************ This is where we start again 6/26**** | C20: Roanoke Rapids, NC
A21: Bond Deal 3: Burnside Village | C21: Hookertown, NC | I21: Martinez | L21: Bruzz? | O21: Towa-NO PO
A22: Bond Deal 3: Gooden Village | C22: Elizabethcity, NC | L22: Anzola Trim (Joe) | O22: Towa-NO PO
A23: Bond Deal 3: Pine Ridge | C23: Avery, NC
A24: Bond Deal 3: Ridgeview | C24: Sparta, NC
A25: Bond Deal 3: Ridgeway | C25: Taylorsville, NC | F25: Amber Construction | G25: 3948 (OLD) | H25: Created - Awaiting Signatures | I25: Bruzz-gave to CO 5/15 | J25: 4044 | K25: Created - Awaiting Signatures | L25: Amber emailed 5/15 | M25: 4045 | N25: Fully Executed
A26: Bond Deal 3: River Park | C26: Sylva, NC
A27: Bond Deal 3: Scotland Arms | C27: Scotland Neck, NC
A28: Bond Deal 3: Woodfield | C28: Fairmont, NC
A29: Partnership: Park Place Apartments | C29: Snow Hill, NC
A30: Partnership: Crest Knolls | C30: Taylorsville, NC
A31: Partnership: Gatebay Apartments | C31: Conway, NC
A32: Partnership: Regal Oaks | C32: Hendersonville, NC
A33: Partnership: Greenfield Manor | C33: Mullins, SC | F33: Amber Construction | G33: 3903 | H33: Fully Executed
A34: Brian Dloniak | C34: GSO, NC | F34: Zavala | G34: NO PO# | H34: Fully Executed
A35: Partnership: British Woods | C35: Roanoke Rapids, NC | F35: Zavala-emailed 5/15 | G35: 4051 | H35: Fully Executed
A36: Partnership: Colony Woods | C36: Roanoke Rapids, NC | F36: Zavala-emailed 5/15 | G36: 4050 | H36: Fully Executed
A37: Partnership: Long Branch | C37: Dillon, SC | F37: Bruzz | G37: PO# 4033 | H37: Fully Executed | I37: Amber emailed 5/15 | J37: 4048 | K37: Fully Executed
A38: Partnership: Mill Pond | C38: Dillon, SC | F38: Bruzz | G38: 4025 | H38: Fully Executed | I38: Amber | J38: 4024 | K38: Fully Executed
A39: Partnership: Silver Trace | C39: Marion, SC | F39: Amber Construction | G39: NO PO# | H39: Fully Executed
A40: Partnership: River Bend | C40: Fair Bluff, NC | F40: Amber Construction | G40: PO# 4086-6/4 emailed to Amber | H40: Fully Executed
A41: Partnership: Berry Court | C41: Chadbourn, NC | F41: Amber Construction 6/5 | G41: PO# 4091 6/5 emailed to Amber | H41: Fully Executed | I41: Bruzz 6/5 Printed gave to CO | J41: 4090 | K41: Created - Awaiting Signatures | L41: Pristine 6/5 Printed gave to CO | M41: 4092 | N41: Created - Awaiting Signatures
A42: Partnership: Lake View | C42: Lake View, SC | F42: Bruzz | G42: 4017 | H42: Fully Executed | I42: Amber emailed 5/15 | J42: 4054 | K42: Fully Executed
A43: Partnership: Palmetto | C43: Darlington, SC | F43: Bruzz | G43: NO SHOW | I43: Amber emailed w/ SOW 6/16 | K43: Fully Executed
A44: KMW: James A Walker | C44: Wilmington, NC | F44: Rogelio - 7/14 put on front desk | G44: No PO | H44: Created - Awaiting Signatures
A45: Anzola BD3 Fully Executed
A46: Anzola DHIC Fully Executed

Sheet Estimate and Scheduling Req
A1: Customer | B1: 1st Contact | C1: Property | D1: Location | E1: Scope
A2: Partnership - Jennifer Hatcher | B2: 45750 | C2: Greenfield Manor | D2: Mullins, SC | E2: PM: Can you price the windows for this building 193. Building 191 and 195 are brick with wooden gables. I’d like to finish that street off and move around to 1101 is all wooden and 1103 is brick with wooden gables. RESPONSE:I do have a question. Only Windows for Building 193, siding is complete. Are the rest of the buildings on the street side 191,195,1101,11,03,1105,1107 needing the windows as well as we do siding? Are we doing 1105 & 1107? PM: Yes, siding and windows for those units.
A3: Partnership - Kellie Atkins | B3: 45777 | C3: Mallard Creek | D3: Auroura, NC 27806 | E3: Replace 22 exterior storage doors - 36 X 80 (Photo to right)
A4: Partnership - Kellie Atkins | B4: Estimate Provided-waiting on approval | C4: Park Place | D4: Snow Hill, NC | E4: $26K Quote
A5: Partnership - Kellie Atkins | B5: 45775 | C5: Park Place | D5: Snow Hill, NC | E5: We also have an existing gazebo there that the floor needs to be replaced however I would like to get a quote to fill in the hole under it with concrete and just build a new shelter. If I could get quotes separately that would be great .
A6: Partnership - Nadia Gallovich | B6: Work approved 5/2/25 - Need dates for contract $110,250 | C6: Wilmington Court | D6: Wallace, NC | E6: 160 window replacements
A7: Partnership - Nadia Gallovich | B7: 45798 | C7: Oak Ridge | D7: Wallace, NC | E7: 16 breezeway windows replaced
A8: Partnership - Tracy Young | B8: Estimate Provided-waiting on approval | C8: Palmetto | E8: Siding & Windows - 7/8/25 added shutter request
A9: Partnership - Jennifer Hatcher | C9: Gatebay | D9: Conway, SC | E9: Gate Bay over bldg. 11 and 12 in Conway. (photo to right)
A11: Partnership | C11: Pinetree Apartments? | D11: Oxford, NC

Sheet Vehicle Log-1st Meeting
A1: Year | B1: Model/Make | C1: Driver | D1: Plate # | E1: Title last 5 digits | F1: Vin # | G1: Renewal Date | H1: Paid Date | I1: Interest Rate | J1: Notes:
A2: 2016 | B2: Silverado C2500 | C2: Service Truck | D2: JK8642 | E2: 65372 | F2: 1GB1CUE82GF269081 | G2: 45657 | H2: 45664
A3: 2019 | B3: Chevy 3500 Dually | C3: Wes Atkinson | D3: JR1324 | E3: 29941 | F3: 1GC4KXEY9KF129941 | G3: 45688 | H3: 45627
A4: 2024 | B4: Toyota Tundra | C4: Chris OKeefe | D4: LAL9805 | E4: 85175 | F4: 5TFKB5DB3RX185175 | G4: 45869 | I4: 0.0879 | J4: Need 2nd key fob from dealer
A5: 2024 | B5: Toyota Rav 4 | C5: Oscar Centeno | D5: LAM1425 | E5: 77918 | F5: 2T3H1RFVXRC277918 | G5: 45869 | H5: 45804 | I5: 0.0449
A6: 2017 | B6: Chevy Suburban | C6: Wes Atkinson | D6: FFJ8206 | E6: 33947 | F6: 1GNSKJKC2HR284780 | G6: 45838
A7: 2020 | B7: Chevy Silverado 2500 | C7: Jesse Warren | D7: KB9444 | E7: 97947 | F7: 1GC1YLEY3LF245650 | G7: 45869 | H7: 45863
A8: 2024 | B8: Toyota Tundra | C8: Joe St. John | D8: LEJ5502 | E8: 26165 | F8: 5TFLA5DBXRX228031 | G8: 46022 | H8: 45627 | I8: 0.0499
A9: 2017 | B9: Chevy Truck | C9: Chuck Atkinson | D9: EHB4862 | E9: 40947 | F9: 1GCVKREC6HZ169664 | G9: 45688 | J9: 2/2025 Wrecked
A10: 2017 | B10: Cadillac Escalade | C10: Evie Atkinson | F10: 1GYS4HKJ9HR385416
A14: Year | B14: Model/Make | C14: Driver | D14: Last Oil Change Date/Mileage | E14: Other Service/Date
A15: 2016 | B15: Silverado C2500 | C15: Service Truck
A16: 2019 | B16: Chevy 3500 Dually | C16: Wes Atkinson
A17: 2017 | B17: Chevy Suburban | C17: Wes Atkinson
A18: 2024 | B18: Toyota Tundra | C18: Chris OKeefe
A19: 2024 | B19: Toyota Rav 4 | C19: Oscar Centeno
A20: 2020 | B20: Chevy Silverado 2500 | C20: Jesse Warren
A21: 2024 | B21: Toyota Tundra | C21: Joe St. John
A22: 2017 | B22: Chevy Truck | C22: Chuck Atkinson
A23: 2017 | B23: Cadillac Escalade | C23: Evie Atkinson

Sheet 6.4.26
A1: 2025 Wesco Notebook | C1: Topics | D1: Team Meeting 6.3.26 Present: Wes, Stephanie, Oscar, Joe, Chris, Rebecca
C2: 1.) | D2: Do we need any contracts for subcontractors? Turn in subcontractor recipts, Review Towa, Martinez, Bruzz
C3: 2.) | D3: Scope
C4: 3.) | D4: Contract Request
C5: 4.)
C6: 5.)
B8: PROJECT SUMMARY | R8: Be sure to include the job name, building number, and/or unit number on the invoice.
B9: Project Name | C9: Customer/ Owner | D9: Start Date | E9: Estimated Job Completion Date | F9: SharePoint Link | G9: Proj Mgr | H9: Scope | I9: Subcontractor & Schedule THIS WEEK | J9: Subcontractor & Schedule NEXT WEEK/FUTURE | K9: Date Inventory Recorded | L9: Weekly Job Summary (Materials Ordered/Arrival Date/Work Performed/Action Taken) | M9: PM Action Items Next Week (Change Order Submission Needed/Unsafe Conditions/Materials/Opportuities) | N9: Others Action Items | O9: Customer Contracts Executed | P9: EXECUTED SUBCONTRACTS
B10: BD3 Ridgeway | C10: KMW | D10: TBD | E10: TBD | G10: Chris | H10: build lean to | L10: Build mailbox addition on maintenance shed. Spoke with Heitor waiting on architect/owners to decide DRAFT CO# 1786 $0.99 | M10: Follow- up | N10: RK contract
B11: Concord | C11: KMW | D11: 46174 | E11: 46388 | F11: Link | G11: Chris 8989 | H11: Interior/Exterior | L11: EST 1568 - in Oscar's court - sections have been sent to him
B12: DHIC Avonlea HILLSTONE WORK | C12: KMW | D12: 45717 | E12: 46191 | G12: Joe | L12: Wesco retention billed 6/5 - Hillstone contract was closed, but reopened so they could bill for rails at dumpster area due to sidewalk slope, Window sash to be replaced 5017 2unit 201 by Pristine 6-18
B13: DHIC Highland | C13: KMW | D13: 45992 | E13: 46203 | G13: Joe | L13: Fence on top of block wall Window opening control device on windows! | M13: PO 3480 - HC Door Order - swing per plans
B14: DHIC Madison Glen | C14: KMW | D14: 46054 | E14: 46220 | G14: Joe | L14: Pristine-Siding the office, 6800, and 6820. Rigo to finish framing 6-19-26. Punch work completed on 7 buildings, will need to add new blinds at 6820 after windows get replaced | N14: Ord 4.14.26 Trucks 6, 7 est del by 5/7 , waiting on ETA for 10, 11 Ordered SA - We have no profit here...review pay app
B15: DHIC Ripley | C15: KMW | D15: 45931 | E15: 46233 | G15: Joe | L15: Stairs are raised for epoxy and need to get rails replaced
B16: DHIC Sedgebrook* | C16: KMW | D16: 45778 | E16: 46203 | G16: Joe | L16: Need to get dumpster fences installed-cleared after 6-18-26
B17: DHIC Tryon | C17: KMW | D17: 45839 | E17: 46142 | G17: Joe | L17: Additional areas were worked with epoxy, will require Pristine to return next week to remove siding and install flashing and siding again. CO 1793 In Procore passed inspections 5/7/26 and will complete this work the week of 5/11 CO 1795 In Procore -6 thresholds and door shoes for riser rooms after doors were cut down for concrete In Procore Door shoes have been installed, will install thresholds this week when we return for siding installation.
B19: River Bend | C19: Partnership
B20: Green Valley | C20: HRP | F20: Link | G20: Chris 8989 | H20: Siding | N20: Are we invoicing for elevator pits or will that be in the contract?
B21: Greenfield | C21: Partnership | D21: 46118 | F21: Link | G21: Chris | H21: Siding / Windows | O21: YES | P21: YES Amber
B22: Holbrook | C22: HRP | D22: 45566 | E22: 46174 | F22: Home | G22: Chris | H22: Siding/Roof/Gutter | I22: Pristine M-F | J22: Pristine M-F | L22: Need to get a very accurate inventory of what's on the ground and in trailers. Would like to consolidate. | M22: CO 1772 Draft | N22: RK - Any retention updates for upcoming 5/15 billing - next building? | O22: YES | P22: YES Zavala & YES Pristine
B23: Lakeview | C23: Partnership | D23: 46139 | E23: /15/26 | F23: Link | G23: Chris | H23: Exterior | O23: YES
B24: Long Branch | C24: Partnership | F24: Link | G24: Chris | H24: Exterior | O24: YES
B25: Martins Landing | C25: Partnership | D25: 46091 | F25: Link | G25: Chris | H25: Roof | O25: YES | P25: NO
B26: Maynard - APS | C26: KMW | D26: 45839 | F26: Link | G26: Wes | H26: Siding
B27: Meadowview | C27: KMW | D27: 45901 | F27: Link | G27: Chris | H27: Exterior & Interior | L27: We are giving an estimate for Siding for this job as well
B28: Mill Pond | C28: Partnership | D28: 46139 | E28: 46157 | F28: Link | G28: Chris | H28: Exterior | O28: YES
B29: Palmetto | C29: Partnership | D29: 46097 | F29: Link | G29: Chris | H29: Siding / Windows
B30: River Park | C30: KMW | G30: Chris
B31: Scotland | C31: KMW | G31: Joe
B32: Silver Trace | C32: Partnership | F32: Silver Trace WescoSOW & Estimate.xlsx | L32: We have a contract for this, but no start dates and it is not on the team meeting notes | O32: Need dates
B33: Greenfield Manor
B34: Silver Trace
B35: Berry Court | C35: Partnership | D35: 46181 | E35: 46185 | L35: we will need to go back to finish this
B37: Upcoming Projects | C37: Customer/ Owner | D37: EstimatedStart Date | E37: Estimated Job Completion Date | F37: SharePoint Link | G37: Proj Mgr | H37: Scope | I37: Subcontractor & Schedule THIS WEEK | J37: Subcontractor & Schedule NEXT WEEK/FUTURE | K37: Date Inventory Recorded
B38: Palmetto | C38: Partnership | H38: Siding / Windows
B45: Pipeline/Bids | C45: Customer/ Owner | D45: Estimated Start Date | E45: Estimated Job Completion Date | F45: SharePoint Link | G45: Proj Mgr | H45: Scope
B46: Mock Place | C46: KMW | D46: TBD | H46: Reno
B47: James A Walker | C47: KMW | D47: TBD | H47: Interior Reno & some Exterior
B48: Gatebay II | C48: Partnership | D48: TBD | H48: Siding
B49: Green Valley | C49: HRP | D49: TBD | H49: Siding
B50: Clemmons Village | C50: HRP | D50: TBD | H50: Siding
B51: The Grayson | C51: KMW | D51: TBD | H51: Siding / Gutters
B52: Pinetree | C52: Partnership | D52: TBD | H52: Windows
B53: Oak Ridge | C53: Partnership | D53: TBD | H53: Windows
B54: West Forest | C54: Partnership | D54: TBD | H54: Windows
B55: Hixson | C55: HRP | D55: TBD | H55: Siding
B56: Tanyard Branch | C56: KMW | D56: TBD | H56: Siding
B57: Sealand Valley | C57: KMW | D57: TBD | H57: Siding
B58: Wilmington Court | C58: Partnership | D58: TBD | H58: Windows | L58: will be adding another estimate for doors, picnic shelter
B59: Granville Place/Plaza | C59: KMW | D59: TBD | H59: Reno

Sheet To Do
B1: Task Summary
B2: Project Name | C2: Proj Mgr | D2: PM Action Items Next Week (Change Order Submission Needed/Unsafe Conditions/Materials/Opportuities) | E2: Others Action Items
B3: ='6.4.26'!B10 -> BD3 Ridgeway | C3: ='6.4.26'!G10 -> Chris | D3: ='6.4.26'!M10 -> Follow- up | E3: ='6.4.26'!N10 -> RK contract
B4: ='6.4.26'!#REF! -> #REF! | C4: ='6.4.26'!#REF! -> #REF! | D4: ='6.4.26'!#REF! -> #REF! | E4: ='6.4.26'!#REF! -> #REF!
B5: ='6.4.26'!#REF! -> #REF! | C5: ='6.4.26'!#REF! -> #REF! | D5: ='6.4.26'!#REF! -> #REF! | E5: ='6.4.26'!#REF! -> #REF!
B6: ='6.4.26'!B11 -> Concord | C6: ='6.4.26'!G11 -> Chris 8989 | D6: ='6.4.26'!M11 -> 0 | E6: ='6.4.26'!N11 -> 0
B7: ='6.4.26'!B12 -> DHIC Avonlea HILLSTONE WORK | C7: ='6.4.26'!G12 -> Joe | D7: ='6.4.26'!M12 -> 0 | E7: ='6.4.26'!N12 -> 0
B8: ='6.4.26'!B13 -> DHIC Highland | C8: ='6.4.26'!G13 -> Joe | D8: ='6.4.26'!M13 -> PO 3480 - HC Door Order - swing per plans | E8: ='6.4.26'!N13 -> 0
B9: ='6.4.26'!B14 -> DHIC Madison Glen | C9: ='6.4.26'!G14 -> Joe | D9: ='6.4.26'!M14 -> 0 | E9: ='6.4.26'!N14 -> Ord 4.14.26 Trucks 6, 7 est del by 5/7 , waiting on ETA for 10, 11 Ordered SA - We have no profit here...review pay app
B10: ='6.4.26'!B15 -> DHIC Ripley | C10: ='6.4.26'!G15 -> Joe | D10: ='6.4.26'!M15 -> 0 | E10: ='6.4.26'!N15 -> 0
B11: ='6.4.26'!B16 -> DHIC Sedgebrook* | C11: ='6.4.26'!G16 -> Joe | D11: ='6.4.26'!M16 -> 0 | E11: ='6.4.26'!N16 -> 0
B12: ='6.4.26'!B17 -> DHIC Tryon | C12: ='6.4.26'!G17 -> Joe | D12: ='6.4.26'!M17 -> 0 | E12: ='6.4.26'!N17 -> 0
B13: ='6.4.26'!B18 -> 0 | C13: ='6.4.26'!G18 -> 0 | D13: ='6.4.26'!M18 -> 0 | E13: ='6.4.26'!N18 -> 0
B14: ='6.4.26'!B19 -> River Bend | C14: ='6.4.26'!G19 -> 0 | D14: ='6.4.26'!M19 -> 0 | E14: ='6.4.26'!N19 -> 0
B15: ='6.4.26'!B20 -> Green Valley | C15: ='6.4.26'!G20 -> Chris 8989 | D15: ='6.4.26'!M20 -> 0 | E15: ='6.4.26'!N20 -> Are we invoicing for elevator pits or will that be in the contract?
B16: ='6.4.26'!B21 -> Greenfield | C16: ='6.4.26'!G21 -> Chris | D16: ='6.4.26'!M21 -> 0 | E16: ='6.4.26'!N21 -> 0
B17: ='6.4.26'!B22 -> Holbrook | C17: ='6.4.26'!G22 -> Chris | D17: ='6.4.26'!M22 -> CO 1772 Draft | E17: ='6.4.26'!N22 -> RK - Any retention updates for upcoming 5/15 billing - next building?
... B29: ='6.4.26'!B34 -> Silver Trace | C29: ='6.4.26'!G34 -> 0 | D29: ='6.4.26'!M34 -> 0 | E29: ='6.4.26'!N34 -> 0
B30: ='6.4.26'!B36 -> 0 | C30: ='6.4.26'!G36 -> 0 | D30: ='6.4.26'!M36 -> 0 | E30: ='6.4.26'!N36 -> 0
B31: ='6.4.26'!B37 -> Upcoming Projects | C31: ='6.4.26'!G37 -> Proj Mgr | D31: ='6.4.26'!M37 -> 0 | E31: ='6.4.26'!N37 -> 0
B32: ='6.4.26'!B38 -> Palmetto | C32: ='6.4.26'!G38 -> 0 | D32: ='6.4.26'!M38 -> 0 | E32: ='6.4.26'!N38 -> 0
B33: ='6.4.26'!B39 -> 0 | E33: ='6.4.26'!N39 -> 0
B34: ='6.4.26'!B40 -> 0 | E34: ='6.4.26'!N40 -> 0
B35: ='6.4.26'!B41 -> 0 | E35: ='6.4.26'!N41 -> 0
E36: ='6.4.26'!N42 -> 0

Sheet 6.26.25
B2: Team Meeting
B3: 6.26.25
B4: Present: Wes, Oscar, Joe, Carson & Stephanie & Rebecca (Septet Team, PRESENT)
B5: Topics
B6: 1.) | C6: Colonial Life @ 12
B7: 2.) | C7: Contract Log
B8: 3.) | C8: Estimate/Scheduling
B9: 4.) | C9: Invoice review - Inventory
B10: 5.) | C10: Oil changes and tires
B11: 6.) | C11: Weekly: Sub calendar update/Daily Job Sheets/Photos Uploaded
B12: 7.) | C12: Pay Apps
B13: 8.)
B14: 9.)
B15: PROJECTS | L15: Be sure to include the job name, building number, and/or unit number on the invoice.
B16: Current Projects (Start Date) | C16: Project Manager (always Chris) | D16: Subcontractor & Schedule THIS WEEK | E16: Subcontractor & Schedule NEXT WEEK/FUTURE | F16: Date Inventory Recorded | G16: Weekly Job Summary (Materials Ordered/Arrival Date/Work Performed/Action Taken) | H16: Action Items Next Week (Change Order Submission Needed/Unsafe Conditions/Materials/Opportuities) | I16: Estimated Job Completion Date | J16: CONTRACTS
B17: HRP Brightwood (4/2023) | C17: x | D17: Pristine | G17: Punch lists for Building 7 & 8 are ready, still waiting on the list from HRP to close out 5 & 6. When we have Siks guys back out there they need to seal the gutter that is leaking on 5. Chris will schedule them for later this week. We also need to get some siding to replace the wall they have been pulling off of in Building 10. | H17: Need to get the siding to replenish the wall they have been pulling off of, also get them scheduled to start the punch work. | I17: 45505 | J17: Done
B18: Pines @ Peach | C18: Joe | D18: Pristine | G18: Outside of 3 done / Working on Outside of 2 - KMW has Pissed off the owners. Change order for Ceilings at top floors & Breezeways has been approved. 2 crews are working on re-insulating the windows on backside on buildings 3 and 2 Also have the same crews working on the breezeways Along with putting in flashing and 2x10 in place (flashing taped and flex taped all joints along with ty-vec work) (Porches are back flush on buildings 2 & 3) | H18: CHANGE ORDERS??? | J18: Done
B19: Mountain Glen | C19: x | D19: Pristine / Rigo | G19: Rigo was installing doors in the UFAS units, sample walls for siding have been hung on building 144 for viewing. Siding order will ship 12/3 and will arrive 12/5 - 12/6. Last truck of doors was delivered by Sik Sunday 12/1. Consolidate containers on site so that we have room to store our siding, and need to be prepared to unload siding when it arrives. | H19: Need to find out what JGBR will be doing at Mountain Glen with Phillip, weather it is exterior work or interior work. Confirm if exterior doors are in the trailer Sik hauled up Sunday.
B20: Holbrook | C20: x | D20: Pristine / Zavala | G20: Zavala has his guys starting to felt Building 3 (Type 3). They have shingles on all amenities and garages. Building 2 also has shingles on it and now needs only the metal roofing. Jonathan also has sent us the material list for the metal he will be needing. | H20: Call Jonathan, and make sure he has guys on site to unload truck of siding. (Carefully)
B21: Dloniak House | C21: Crawl Diddy | D21: Pinnacle | G21: Huntley - Bricking Chimney & House , PEM (plumbing)- waiting on tubs / (electrical) - lighting in kitchen and porches / (HVAC) - relocating lines & gas lines, Steve (Pro Chem) - after PME finished | H21: Inspections? Getting tied into city- Hub cast iron? Gas Lines? Temp power? Structural Protection infront of plumbing fixtures in garages
B22: Woodfield - BD3 | C22: Joe | G22: Should finish 3/7/25
B23: Aaron Mills | D23: Pristine
B24: Jeffries -DHIC | C24: Joe
B25: Avonlea - DHIC | C25: Joe
B26: Sedgbrook - DHIC | C26: Joe
B27: Piney Pointe - BD3 | C27: Joe
B28: Brookside - BD3 | C28: Joe
B29: Burnside - BD3 | C29: Joe
B30: Brittany Place - BD3 | C30: Joe
B31: Scotland Arms - BD3 | C31: Joe
B32: British Arms - BD3 | C32: Joe
B33: River Park - BD3 | E33: Rigo | G33: Monday - 6-23-25 Rigo starting UFAS units 6 & 16 Demo & Framing
B34: Upcoming Projects (Start Date) | C34: Project Manager | D34: Subcontractor | F34: Customer Contact | G34: Weekly Planning Summary (Materials Ordered/Arrival Date/Change Order Submission Needed/Unsafe Conditions/Opportuities) | H34: Action Items This Week | I34: Estimated Start Date
B35: Tryon- DHIC | C35: Joe
B36: Ripley - DHIC | C36: Joe
B37: Highland Village- DHIC | C37: Joe
B38: Madison Glen - DHIC | C38: Joe
B39: Pine Ridge- BD3
B40: Pine View- BD3
B41: Ridgeway- BD3
B44: Pipeline/Bids | C44: Project Manager | D44: Anticipated Subcontractor | E44: Estimated Start Date | F44: Customer Contact | G44: Bid Status | H44: Action Needed/Comments | I44: Estimated Start Date
B50: PPM - Little Pee Dee Manor | C50: Not KW | F50: Jason Buffkin | G50: Gazebo Enclosure, Fountain pricing
B51: PPM - Churchwood Apts | C51: Not KW | F51: Jason Buffkin | G51: 2 story bay window replacement , accent siding, aluminum columns per PM
B52: PPM - Greenfield | C52: Not KW | F52: Jason Buffkin | G52: Storage room doors, roof replacement, siding pricing per building
B53: KMW - Hartwood Village | C53: Not KW | G53: Roofing, windows, interior doors, hardware, dumpster fence | H53: Waiting on pricing back on interior doors/windows from GCL, ABC
B54: PPM - Westridge Apts. | C54: Not KW | F54: Jason Buffkin
B55: HRP Murrayville
B56: KMW - Fairway PH2 | G56: Bid sent to C. Binkowski on 11-10-22 *OCN 11/10/22 * *Again 10-23-24*
B57: KMW - Maynard Rd.

Sheet 6.19.25
B2: Team Meeting
B3: 6.19.25
B4: Present: Wes, Oscar, Joe, Carson & Stephanie & Rebecca (Septet Team, PRESENT)
B5: Topics
B6: 1.) | C6: Weekly: Sub calendar update/Daily Job Sheets/Photos Uploaded
B7: 2.) | C7: Contract Log
B8: 3.) | C8: BCBS 7.1 Renewal
B9: 4.) | C9: Invoice review - Inventory
B10: 5.) | C10: Oil changes and tires
B11: 6.) | C11: Change Order Review & New Process - need info/email to right
B12: 7.) | C12: OneStep GPS Tracker
B13: 8.) | C13: Reminder - Add notes in memo line of estimate/CO emailed to customer
B14: 9.)
B15: PROJECTS | L15: Be sure to include the job name, building number, and/or unit number on the invoice.
B16: Current Projects (Start Date) | C16: Project Manager (always Chris) | D16: Subcontractor & Schedule THIS WEEK | E16: Subcontractor & Schedule NEXT WEEK/FUTURE | F16: Date Inventory Recorded | G16: Weekly Job Summary (Materials Ordered/Arrival Date/Work Performed/Action Taken) | H16: Action Items Next Week (Change Order Submission Needed/Unsafe Conditions/Materials/Opportuities) | I16: Estimated Job Completion Date | J16: CONTRACTS
B17: HRP Brightwood (4/2023) | C17: Chris | D17: Pristine | G17: Punch lists for Building 7 & 8 are ready, still waiting on the list from HRP to close out 5 & 6. When we have Siks guys back out there they need to seal the gutter that is leaking on 5. Chris will schedule them for later this week. We also need to get some siding to replace the wall they have been pulling off of in Building 10. | H17: Need to get the siding to replenish the wall they have been pulling off of, also get them scheduled to start the punch work. | I17: 45505 | J17: Done
B18: Pines @ Peach | C18: Joe | D18: Pristine | G18: Outside of 3 done / Working on Outside of 2 - KMW has Pissed off the owners. Change order for Ceilings at top floors & Breezeways has been approved. 2 crews are working on re-insulating the windows on backside on buildings 3 and 2 Also have the same crews working on the breezeways Along with putting in flashing and 2x10 in place (flashing taped and flex taped all joints along with ty-vec work) (Porches are back flush on buildings 2 & 3) | H18: CHANGE ORDERS??? | J18: Done
B19: Mountain Glen | C19: Chris | D19: Pristine / Rigo | G19: Rigo was installing doors in the UFAS units, sample walls for siding have been hung on building 144 for viewing. Siding order will ship 12/3 and will arrive 12/5 - 12/6. Last truck of doors was delivered by Sik Sunday 12/1. Consolidate containers on site so that we have room to store our siding, and need to be prepared to unload siding when it arrives. | H19: Need to find out what JGBR will be doing at Mountain Glen with Phillip, weather it is exterior work or interior work. Confirm if exterior doors are in the trailer Sik hauled up Sunday.
B20: Holbrook | C20: Chris | D20: Pristine / Zavala | G20: Zavala has his guys starting to felt Building 3 (Type 3). They have shingles on all amenities and garages. Building 2 also has shingles on it and now needs only the metal roofing. Jonathan also has sent us the material list for the metal he will be needing. | H20: Call Jonathan, and make sure he has guys on site to unload truck of siding. (Carefully)
B21: Dloniak House | C21: Crawl Diddy | D21: Pinnacle | G21: Huntley - Bricking Chimney & House , PEM (plumbing)- waiting on tubs / (electrical) - lighting in kitchen and porches / (HVAC) - relocating lines & gas lines, Steve (Pro Chem) - after PME finished | H21: Inspections? Getting tied into city- Hub cast iron? Gas Lines? Temp power? Structural Protection infront of plumbing fixtures in garages
B22: Woodfield - BD3 | C22: Joe | G22: Should finish 3/7/25
B23: Aaron Mills | D23: Pristine
B24: Jeffries -DHIC | C24: Joe
B25: Avonlea - DHIC | C25: Joe
B26: Sedgbrook - DHIC | C26: Joe
B27: Piney Pointe - BD3 | C27: Joe
B28: Brookside - BD3 | C28: Joe
B29: Burnside - BD3 | C29: Joe
B30: Brittany Place - BD3 | C30: Joe
B31: Scotland Arms - BD3 | C31: Joe
B32: British Arms - BD3 | C32: Joe
B33: River Park - BD3 | E33: Rigo | G33: Monday - 6-23-25 Rigo starting UFAS units 6 & 16 Demo & Framing
B34: Upcoming Projects (Start Date) | C34: Project Manager | D34: Subcontractor | F34: Customer Contact | G34: Weekly Planning Summary (Materials Ordered/Arrival Date/Change Order Submission Needed/Unsafe Conditions/Opportuities) | H34: Action Items This Week | I34: Estimated Start Date
B35: Tryon- DHIC | C35: Joe
B36: Ripley - DHIC | C36: Joe
B37: Highland Village- DHIC | C37: Joe
B38: Madison Glen - DHIC | C38: Joe
B39: Pine Ridge- BD3
B40: Pine View- BD3
B41: Ridgeway- BD3
B44: Pipeline/Bids | C44: Project Manager | D44: Anticipated Subcontractor | E44: Estimated Start Date | F44: Customer Contact | G44: Bid Status | H44: Action Needed/Comments | I44: Estimated Start Date
B50: PPM - Little Pee Dee Manor | C50: Not KW | F50: Jason Buffkin | G50: Gazebo Enclosure, Fountain pricing
B51: PPM - Churchwood Apts | C51: Not KW | F51: Jason Buffkin | G51: 2 story bay window replacement , accent siding, aluminum columns per PM
B52: PPM - Greenfield | C52: Not KW | F52: Jason Buffkin | G52: Storage room doors, roof replacement, siding pricing per building
B53: KMW - Hartwood Village | C53: Not KW | G53: Roofing, windows, interior doors, hardware, dumpster fence | H53: Waiting on pricing back on interior doors/windows from GCL, ABC
B54: PPM - Westridge Apts. | C54: Not KW | F54: Jason Buffkin
B55: HRP Murrayville
B56: KMW - Fairway PH2 | G56: Bid sent to C. Binkowski on 11-10-22 *OCN 11/10/22 * *Again 10-23-24*
B57: KMW - Maynard Rd.

Sheet 5.21.25
B2: Team Meeting
B3: 5.21.25
B4: Present: Wes, Oscar, Joe, Carson & Stephanie & Rebecca (Septet Team, PRESENT)
B5: Topics
B6: 1.) | C6: Weekly: Sub calendar update/Daily Job Sheets/Photos Uploaded
B7: 2.) | C7: Contract Log
B8: 3.) | C8: Yale front door codes?
B9: 4.) | C9: Invoice review - Inventory
B10: 5.) | C10: Dario - RK Emailed him 3x, SA texted him daily - still no paperwork - he is not authorized to be onsite yet
B11: 6.) | C11: Change Order Review & New Process - need info/email to right
B12: 7.) | C12: OneStep GPS Tracker
B13: 8.) | C13: Reminder - Add notes in memo line of estimate/CO emailed to customer
B14: 9.)
B15: PROJECTS | L15: Be sure to include the job name, building number, and/or unit number on the invoice.
B16: Current Projects (Start Date) | C16: Project Manager (always Chris & Joe) | D16: Subcontractor & Schedule THIS WEEK | E16: Subcontractor & Schedule NEXT WEEK/FUTURE | F16: Date Inventory Recorded | G16: Weekly Job Summary (Materials Ordered/Arrival Date/Work Performed/Action Taken) | H16: Action Items Next Week (Change Order Submission Needed/Unsafe Conditions/Materials/Opportuities) | I16: Estimated Job Completion Date | J16: CONTRACTS
B17: HRP Brightwood (4/2023) | C17: Chris | D17: Pristine | G17: Punch lists for Building 7 & 8 are ready, still waiting on the list from HRP to close out 5 & 6. When we have Siks guys back out there they need to seal the gutter that is leaking on 5. Chris will schedule them for later this week. We also need to get some siding to replace the wall they have been pulling off of in Building 10. | H17: Need to get the siding to replenish the wall they have been pulling off of, also get them scheduled to start the punch work. | I17: 45505 | J17: Done
B18: Pines @ Peach | C18: Joe | D18: Pristine | G18: Outside of 3 done / Working on Outside of 2 - KMW has Pissed off the owners. Change order for Ceilings at top floors & Breezeways has been approved. 2 crews are working on re-insulating the windows on backside on buildings 3 and 2 Also have the same crews working on the breezeways Along with putting in flashing and 2x10 in place (flashing taped and flex taped all joints along with ty-vec work) (Porches are back flush on buildings 2 & 3) | H18: CHANGE ORDERS??? | J18: Done
B19: Mountain Glen | C19: Chris | D19: Pristine / Rigo | G19: Rigo was installing doors in the UFAS units, sample walls for siding have been hung on building 144 for viewing. Siding order will ship 12/3 and will arrive 12/5 - 12/6. Last truck of doors was delivered by Sik Sunday 12/1. Consolidate containers on site so that we have room to store our siding, and need to be prepared to unload siding when it arrives. | H19: Need to find out what JGBR will be doing at Mountain Glen with Phillip, weather it is exterior work or interior work. Confirm if exterior doors are in the trailer Sik hauled up Sunday.
B20: Holbrook | C20: Chris | D20: Pristine / Zavala | G20: Zavala has his guys starting to felt Building 3 (Type 3). They have shingles on all amenities and garages. Building 2 also has shingles on it and now needs only the metal roofing. Jonathan also has sent us the material list for the metal he will be needing. | H20: Call Jonathan, and make sure he has guys on site to unload truck of siding. (Carefully)
B21: Dloniak House | C21: Crawl Diddy | D21: Pinnacle | G21: Huntley - Bricking Chimney & House , PEM (plumbing)- waiting on tubs / (electrical) - lighting in kitchen and porches / (HVAC) - relocating lines & gas lines, Steve (Pro Chem) - after PME finished | H21: Inspections? Getting tied into city- Hub cast iron? Gas Lines? Temp power? Structural Protection infront of plumbing fixtures in garages
B22: Woodfield - BD3 | C22: Joe | G22: Should finish 3/7/25
B28: Upcoming Projects (Start Date) | C28: Project Manager | D28: Subcontractor | F28: Customer Contact | G28: Weekly Planning Summary (Materials Ordered/Arrival Date/Change Order Submission Needed/Unsafe Conditions/Opportuities) | H28: Action Items This Week | I28: Estimated Start Date
B30: Aaron Mills | C30: Chris | D30: Pristine | F30: Brandon | G30: Framing in Process
B31: Jeffries -DHIC | C31: Joe
B32: Avonlea - DHIC | C32: Joe
B33: Sedgbrook - DHIC | C33: Joe
B34: Piney Pointe - BD3 | C34: Joe
B35: Brookside - BD3 | C35: Joe
B36: Woodfield - BD3 | C36: Joe
B37: Burnside - BD3 | C37: Joe
B38: Pipeline/Bids | C38: Project Manager | D38: Anticipated Subcontractor | E38: Estimated Start Date | F38: Customer Contact | G38: Bid Status | H38: Action Needed/Comments | I38: Estimated Start Date
B40: PPM - Regal Oaks | F40: Jason Buffkin | G40: Resent Estimate on 5-28-24 - OCN
B41: PPM-Kings Crossing | C41: Not KW | F41: Buffkin | G41: Stair replacement, site steps, sidewalk plates
B42: PPM - Plantation Village | C42: Not KW | F42: Jason Buffkin | G42: Roofing, Windows, Dumpster Fence, Mailbox Posts, 8x8
B44: PPM - Little Pee Dee Manor | C44: Not KW | F44: Jason Buffkin | G44: Gazebo Enclosure, Fountain pricing
B45: PPM - Churchwood Apts | C45: Not KW | F45: Jason Buffkin | G45: 2 story bay window replacement , accent siding, aluminum columns per PM
B46: PPM - Greenfield | C46: Not KW | F46: Jason Buffkin | G46: Storage room doors, roof replacement, siding pricing per building
B47: KMW - Hartwood Village | C47: Not KW | G47: Roofing, windows, interior doors, hardware, dumpster fence | H47: Waiting on pricing back on interior doors/windows from GCL, ABC
B48: PPM - Westridge Apts. | C48: Not KW | F48: Jason Buffkin
B49: HRP Murrayville
B50: KMW - Fairway PH2 | G50: Bid sent to C. Binkowski on 11-10-22 *OCN 11/10/22 * *Again 10-23-24*
B51: KMW - Maynard Rd. | G51: Working on revised plans.

Sheet 4.25.25
B2: Team Meeting
B3: 4.25.25
B4: Present: Wes, Oscar, Joe, Carson & Stephanie & Rebecca (Septet Team, PRESENT) - we need more space, more chairs - Chris on Phone, Sick Boi
B5: Topics
B6: 1.) | C6: Weekly: Sub calendar update/Daily Job Sheets/Photos Uploaded
B7: 2.) | C7: Contract Log
B8: 3.) | C8: Alarm/Doors/Gates in 208 - does everyone know how to operate
B9: 4.) | C9: Invoice review
B10: 5.) | C10: Jesus, JSH Update
B11: 6.) | C11: Change Order Review
B12: 7.) | C12: Pay App Review - Bond Deal Little Jobs Done?
B13: 8.) | C13: Reminder - Add notes in memo line of estimate/CO emailed to customer
B14: 9.) | C14: Make sure all completed jobs are billed
B15: PROJECTS
B16: Current Projects (Start Date) | C16: Project Manager (always Chris) | D16: Subcontractor & Schedule THIS WEEK | E16: Subcontractor & Schedule NEXT WEEK/FUTURE | F16: Date Inventory Recorded | G16: Weekly Job Summary (Materials Ordered/Arrival Date/Work Performed/Action Taken) | H16: Action Items Next Week (Change Order Submission Needed/Unsafe Conditions/Materials/Opportuities) | I16: Estimated Job Completion Date | J16: CONTRACTS
B17: HRP Brightwood (4/2023) | C17: Chris | D17: Pristine | G17: Punch lists for Building 7 & 8 are ready, still waiting on the list from HRP to close out 5 & 6. When we have Siks guys back out there they need to seal the gutter that is leaking on 5. Chris will schedule them for later this week. We also need to get some siding to replace the wall they have been pulling off of in Building 10. | H17: Need to get the siding to replenish the wall they have been pulling off of, also get them scheduled to start the punch work. | I17: 45505 | J17: Done
B18: Pines @ Peach | C18: Joe | D18: Pristine | G18: Outside of 3 done / Working on Outside of 2 - KMW has Pissed off the owners. Change order for Ceilings at top floors & Breezeways has been approved. 2 crews are working on re-insulating the windows on backside on buildings 3 and 2 Also have the same crews working on the breezeways Along with putting in flashing and 2x10 in place (flashing taped and flex taped all joints along with ty-vec work) (Porches are back flush on buildings 2 & 3) | H18: CHANGE ORDERS??? | J18: Done
B19: Mountain Glen | C19: Chris | D19: Pristine / Rigo | G19: Rigo was installing doors in the UFAS units, sample walls for siding have been hung on building 144 for viewing. Siding order will ship 12/3 and will arrive 12/5 - 12/6. Last truck of doors was delivered by Sik Sunday 12/1. Consolidate containers on site so that we have room to store our siding, and need to be prepared to unload siding when it arrives. | H19: Need to find out what JGBR will be doing at Mountain Glen with Phillip, weather it is exterior work or interior work. Confirm if exterior doors are in the trailer Sik hauled up Sunday.
B20: Holbrook | C20: Chris | D20: Pristine / Zavala | G20: Zavala has his guys starting to felt Building 3 (Type 3). They have shingles on all amenities and garages. Building 2 also has shingles on it and now needs only the metal roofing. Jonathan also has sent us the material list for the metal he will be needing. | H20: Call Jonathan, and make sure he has guys on site to unload truck of siding. (Carefully)
B21: Dloniak House | C21: Crawl Diddy | D21: Pinnacle | G21: Huntley - Bricking Chimney & House , PEM (plumbing)- waiting on tubs / (electrical) - lighting in kitchen and porches / (HVAC) - relocating lines & gas lines, Steve (Pro Chem) - after PME finished | H21: Inspections? Getting tied into city- Hub cast iron? Gas Lines? Temp power? Structural Protection infront of plumbing fixtures in garages
B22: Woodfield - BD3 | C22: Joe | G22: Should finish 3/7/25
B25: Upcoming Projects (Start Date) | C25: Project Manager | D25: Subcontractor | F25: Customer Contact | G25: Weekly Planning Summary (Materials Ordered/Arrival Date/Change Order Submission Needed/Unsafe Conditions/Opportuities) | H25: Action Items This Week | I25: Estimated Start Date
B27: Aaron Mills | C27: Chris | D27: Pristine | F27: Brandon | G27: Framing in Process
B28: Jeffries -DHIC | C28: Joe
B29: Avonlea - DHIC | C29: Joe
B30: Sedgbrook - DHIC | C30: Joe
B31: Piney Pointe - BD3 | C31: Joe
B32: Brookside - BD3 | C32: Joe
B33: Woodfield - BD3 | C33: Joe
B34: Burnside - BD3 | C34: Joe
B35: Pipeline/Bids | C35: Project Manager | D35: Anticipated Subcontractor | E35: Estimated Start Date | F35: Customer Contact | G35: Bid Status | H35: Action Needed/Comments | I35: Estimated Start Date
B37: PPM - Regal Oaks | F37: Jason Buffkin | G37: Resent Estimate on 5-28-24 - OCN
B38: PPM-Kings Crossing | C38: Not KW | F38: Buffkin | G38: Stair replacement, site steps, sidewalk plates
B39: PPM - Plantation Village | C39: Not KW | F39: Jason Buffkin | G39: Roofing, Windows, Dumpster Fence, Mailbox Posts, 8x8
B41: PPM - Little Pee Dee Manor | C41: Not KW | F41: Jason Buffkin | G41: Gazebo Enclosure, Fountain pricing
B42: PPM - Churchwood Apts | C42: Not KW | F42: Jason Buffkin | G42: 2 story bay window replacement , accent siding, aluminum columns per PM
B43: PPM - Greenfield | C43: Not KW | F43: Jason Buffkin | G43: Storage room doors, roof replacement, siding pricing per building
B44: KMW - Hartwood Village | C44: Not KW | G44: Roofing, windows, interior doors, hardware, dumpster fence | H44: Waiting on pricing back on interior doors/windows from GCL, ABC
B45: PPM - Westridge Apts. | C45: Not KW | F45: Jason Buffkin
B46: HRP Murrayville
B47: KMW - Fairway PH2 | G47: Bid sent to C. Binkowski on 11-10-22 *OCN 11/10/22 * *Again 10-23-24*
B48: KMW - Maynard Rd. | G48: Working on revised plans.

Sheet 3-12.25
B2: Team Meeting
B3: 3.12.25
B4: Present: Wes, Oscar, Chris, Joe, Carson & Stephanie & Rebecca (Septet Team, PRESENT) - we need more space, more chairs
B5: Topics
B6: 1.) | C6: Weekly: Sub calendar update/Daily Job Sheets/Photos Uploaded
B7: 2.) | C7: Calendar - use to help track Change Order Work
B8: 3.) | C8: Signed, CLOSING on Building for down the street
B9: 4.)
B10: 5.)
B11: 6.)
B12: 7.) | C12: Reminder - Add notes in memo line of estimate/CO emailed to customer
B13: 8.) | C13: Make sure all completed jobs are billed
B14: PROJECTS
B15: Current Projects (Start Date) | C15: Project Manager (always Chris) | D15: Subcontractor & Schedule THIS WEEK | E15: Subcontractor & Schedule NEXT WEEK/FUTURE | F15: Date Inventory Recorded | G15: Weekly Job Summary (Materials Ordered/Arrival Date/Work Performed/Action Taken) | H15: Action Items Next Week (Change Order Submission Needed/Unsafe Conditions/Materials/Opportuities) | I15: Estimated Job Completion Date | J15: CONTRACTS
B16: HRP Brightwood (4/2023) | C16: Chris | D16: Pristine | G16: Punch lists for Building 7 & 8 are ready, still waiting on the list from HRP to close out 5 & 6. When we have Siks guys back out there they need to seal the gutter that is leaking on 5. Chris will schedule them for later this week. We also need to get some siding to replace the wall they have been pulling off of in Building 10. | H16: Need to get the siding to replenish the wall they have been pulling off of, also get them scheduled to start the punch work. | I16: 45505 | J16: Done
B17: Pines @ Peach | C17: Joe | D17: Pristine | G17: Outside of 3 done / Working on Outside of 2 - KMW has Pissed off the owners. Change order for Ceilings at top floors & Breezeways has been approved. 2 crews are working on re-insulating the windows on backside on buildings 3 and 2 Also have the same crews working on the breezeways Along with putting in flashing and 2x10 in place (flashing taped and flex taped all joints along with ty-vec work) (Porches are back flush on buildings 2 & 3) | H17: CHANGE ORDERS??? | J17: Done
B18: Mountain Glen | C18: Chris | D18: Pristine / Rigo | G18: Rigo was installing doors in the UFAS units, sample walls for siding have been hung on building 144 for viewing. Siding order will ship 12/3 and will arrive 12/5 - 12/6. Last truck of doors was delivered by Sik Sunday 12/1. Consolidate containers on site so that we have room to store our siding, and need to be prepared to unload siding when it arrives. | H18: Need to find out what JGBR will be doing at Mountain Glen with Phillip, weather it is exterior work or interior work. Confirm if exterior doors are in the trailer Sik hauled up Sunday.
B19: Holbrook | C19: Chris | D19: Pristine / Zavala | G19: Zavala has his guys starting to felt Building 3 (Type 3). They have shingles on all amenities and garages. Building 2 also has shingles on it and now needs only the metal roofing. Jonathan also has sent us the material list for the metal he will be needing. | H19: Call Jonathan, and make sure he has guys on site to unload truck of siding. (Carefully)
B20: Dloniak House | C20: Crawl Diddy | D20: Pinnacle | G20: 3rd party Footing Inspection for Pinnacle Footers due to bad weather and emailed a copy of the Inspection to City of Greensboro (James Wolffe) / (Huntley Brothers) are wrapping up foundation perimeter (CMU block, brick and mortar) *Trash Dumpster is on site along with porty potty* CONTACTED Castro (framer) & Riverside Truss - Cliff (trusses) they want to meet 12/24 at 9AM and call Steve (Pro-Chem) for Termite spray before fondation inspection | H20: HOA Approval for Shingle and Metal color / Cables at front of site need to be burried lower for driveway (Call contacts on email)
B21: Woodfield - BD3 | C21: Joe | G21: Should finish 3/7/25
B24: Upcoming Projects (Start Date) | C24: Project Manager | D24: Subcontractor | F24: Customer Contact | G24: Weekly Planning Summary (Materials Ordered/Arrival Date/Change Order Submission Needed/Unsafe Conditions/Opportuities) | H24: Action Items This Week | I24: Estimated Start Date
B26: Aaron Mills | C26: Chris | D26: ? | G26: Framing in Process
B27: Jeffries -DHIC | C27: Joe
B28: Avonlea - DHIC | C28: Joe
B29: Sedgbrook - DHIC | C29: Joe
B30: Piney Pointe - BD3 | C30: Joe
B31: Brookside - BD3 | C31: Joe
B32: Woodfield - BD3 | C32: Joe
B33: Burnside - BD3 | C33: Joe
B34: Pipeline/Bids | C34: Project Manager | D34: Anticipated Subcontractor | E34: Estimated Start Date | F34: Customer Contact | G34: Bid Status | H34: Action Needed/Comments | I34: Estimated Start Date
B36: PPM - Regal Oaks | F36: Jason Buffkin | G36: Resent Estimate on 5-28-24 - OCN
B37: PPM-Kings Crossing | C37: Not KW | F37: Buffkin | G37: Stair replacement, site steps, sidewalk plates
B38: PPM - Plantation Village | C38: Not KW | F38: Jason Buffkin | G38: Roofing, Windows, Dumpster Fence, Mailbox Posts, 8x8
B40: PPM - Little Pee Dee Manor | C40: Not KW | F40: Jason Buffkin | G40: Gazebo Enclosure, Fountain pricing
B41: PPM - Churchwood Apts | C41: Not KW | F41: Jason Buffkin | G41: 2 story bay window replacement , accent siding, aluminum columns per PM
B42: PPM - Greenfield | C42: Not KW | F42: Jason Buffkin | G42: Storage room doors, roof replacement, siding pricing per building
B43: KMW - Hartwood Village | C43: Not KW | G43: Roofing, windows, interior doors, hardware, dumpster fence | H43: Waiting on pricing back on interior doors/windows from GCL, ABC
B44: PPM - Westridge Apts. | C44: Not KW | F44: Jason Buffkin
B45: HRP Murrayville
B46: KMW - Fairway PH2 | G46: Bid sent to C. Binkowski on 11-10-22 *OCN 11/10/22 * *Again 10-23-24*
B47: KMW - Maynard Rd. | G47: Working on revised plans.

Sheet 3-26.25 
B2: Team Meeting
B3: 45742
B4: Present: Wes, Oscar, Joe, Carson & Stephanie & Rebecca (Septet Team, PRESENT) - we need more space, more chairs
B5: Topics
B6: 1.) | C6: Weekly: Sub calendar update/Daily Job Sheets/Photos Uploaded
B7: 2.) | C7: Calendar - use to help track Change Order Work
B8: 3.) | C8: Flooring - 3/28, 2 offices and conference room in back
B9: 4.) | C9: 208 Door codes
B10: 5.) | C10: Invoices -
B11: 6.) | C11: Vendor set -up
B12: 7.) | C12: Reminder - Add notes in memo line of estimate/CO emailed to customer
B13: 8.) | C13: Make sure all completed jobs are billed
B14: PROJECTS
B15: Current Projects (Start Date) | C15: Project Manager (always Chris) | D15: Subcontractor & Schedule THIS WEEK | E15: Subcontractor & Schedule NEXT WEEK/FUTURE | F15: Date Inventory Recorded | G15: Weekly Job Summary (Materials Ordered/Arrival Date/Work Performed/Action Taken) | H15: Action Items Next Week (Change Order Submission Needed/Unsafe Conditions/Materials/Opportuities) | I15: Estimated Job Completion Date | J15: CONTRACTS
B16: HRP Brightwood (4/2023) | C16: Chris | D16: Pristine | G16: Punch lists for Building 7 & 8 are ready, still waiting on the list from HRP to close out 5 & 6. When we have Siks guys back out there they need to seal the gutter that is leaking on 5. Chris will schedule them for later this week. We also need to get some siding to replace the wall they have been pulling off of in Building 10. | H16: Need to get the siding to replenish the wall they have been pulling off of, also get them scheduled to start the punch work. | I16: 45505 | J16: Done
B17: Pines @ Peach | C17: Joe | D17: Pristine | G17: Outside of 3 done / Working on Outside of 2 - KMW has Pissed off the owners. Change order for Ceilings at top floors & Breezeways has been approved. 2 crews are working on re-insulating the windows on backside on buildings 3 and 2 Also have the same crews working on the breezeways Along with putting in flashing and 2x10 in place (flashing taped and flex taped all joints along with ty-vec work) (Porches are back flush on buildings 2 & 3) | H17: CHANGE ORDERS??? | J17: Done
B18: Mountain Glen | C18: Chris | D18: Pristine / Rigo | G18: Rigo was installing doors in the UFAS units, sample walls for siding have been hung on building 144 for viewing. Siding order will ship 12/3 and will arrive 12/5 - 12/6. Last truck of doors was delivered by Sik Sunday 12/1. Consolidate containers on site so that we have room to store our siding, and need to be prepared to unload siding when it arrives. | H18: Need to find out what JGBR will be doing at Mountain Glen with Phillip, weather it is exterior work or interior work. Confirm if exterior doors are in the trailer Sik hauled up Sunday.
B19: Holbrook | C19: Chris | D19: Pristine / Zavala | G19: Zavala has his guys starting to felt Building 3 (Type 3). They have shingles on all amenities and garages. Building 2 also has shingles on it and now needs only the metal roofing. Jonathan also has sent us the material list for the metal he will be needing. | H19: Call Jonathan, and make sure he has guys on site to unload truck of siding. (Carefully)
B20: Dloniak House | C20: Crawl Diddy | D20: Pinnacle | G20: Huntley - Bricking Chimney & House , PEM (plumbing)- waiting on tubs / (electrical) - lighting in kitchen and porches / (HVAC) - relocating lines & gas lines, Steve (Pro Chem) - after PME finished | H20: Inspections? Getting tied into city- Hub cast iron? Gas Lines? Temp power? Structural Protection infront of plumbing fixtures in garages
B21: Woodfield - BD3 | C21: Joe | G21: Should finish 3/7/25
B24: Upcoming Projects (Start Date) | C24: Project Manager | D24: Subcontractor | F24: Customer Contact | G24: Weekly Planning Summary (Materials Ordered/Arrival Date/Change Order Submission Needed/Unsafe Conditions/Opportuities) | H24: Action Items This Week | I24: Estimated Start Date
B26: Aaron Mills | C26: Chris | D26: ? | G26: Framing in Process
B27: Jeffries -DHIC | C27: Joe
B28: Avonlea - DHIC | C28: Joe
B29: Sedgbrook - DHIC | C29: Joe
B30: Piney Pointe - BD3 | C30: Joe
B31: Brookside - BD3 | C31: Joe
B32: Woodfield - BD3 | C32: Joe
B33: Burnside - BD3 | C33: Joe
B34: Pipeline/Bids | C34: Project Manager | D34: Anticipated Subcontractor | E34: Estimated Start Date | F34: Customer Contact | G34: Bid Status | H34: Action Needed/Comments | I34: Estimated Start Date
B36: PPM - Regal Oaks | F36: Jason Buffkin | G36: Resent Estimate on 5-28-24 - OCN
B37: PPM-Kings Crossing | C37: Not KW | F37: Buffkin | G37: Stair replacement, site steps, sidewalk plates
B38: PPM - Plantation Village | C38: Not KW | F38: Jason Buffkin | G38: Roofing, Windows, Dumpster Fence, Mailbox Posts, 8x8
B40: PPM - Little Pee Dee Manor | C40: Not KW | F40: Jason Buffkin | G40: Gazebo Enclosure, Fountain pricing
B41: PPM - Churchwood Apts | C41: Not KW | F41: Jason Buffkin | G41: 2 story bay window replacement , accent siding, aluminum columns per PM
B42: PPM - Greenfield | C42: Not KW | F42: Jason Buffkin | G42: Storage room doors, roof replacement, siding pricing per building
B43: KMW - Hartwood Village | C43: Not KW | G43: Roofing, windows, interior doors, hardware, dumpster fence | H43: Waiting on pricing back on interior doors/windows from GCL, ABC
B44: PPM - Westridge Apts. | C44: Not KW | F44: Jason Buffkin
B45: HRP Murrayville
B46: KMW - Fairway PH2 | G46: Bid sent to C. Binkowski on 11-10-22 *OCN 11/10/22 * *Again 10-23-24*
B47: KMW - Maynard Rd. | G47: Working on revised plans.

Sheet 2-28-25
B2: Team Meeting
B3: 2.28.25
B4: Present: Wes, Oscar, Chris, Joe, Carson & Stephanie & Rebecca (Septet Team, PRESENT) - we need more space, more chairs
B5: Topics
B6: 1.) | C6: Weekly: Sub calendar update/Daily Job Sheets/Photos Uploaded
B7: 2.) | C7: Calendar - use to help track Change Order Work
B8: 3.) | C8: Signed, CLOSING on Building for down the street
B9: 4.) | C9: Review Employee P&P
B10: 5.)
B11: 6.)
B12: 7.) | C12: Reminder - Add notes in memo line of estimate/CO emailed to customer
B13: 8.) | C13: Make sure all completed jobs are billed
B14: PROJECTS
B15: Current Projects (Start Date) | C15: Project Manager (always Chris) | D15: Subcontractor & Schedule THIS WEEK | E15: Subcontractor & Schedule NEXT WEEK/FUTURE | F15: Date Inventory Recorded | G15: Weekly Job Summary (Materials Ordered/Arrival Date/Work Performed/Action Taken) | H15: Action Items Next Week (Change Order Submission Needed/Unsafe Conditions/Materials/Opportuities) | I15: Estimated Job Completion Date | J15: CONTRACTS
B16: HRP Brightwood (4/2023) | C16: Chris | D16: Pristine | G16: Punch lists for Building 7 & 8 are ready, still waiting on the list from HRP to close out 5 & 6. When we have Siks guys back out there they need to seal the gutter that is leaking on 5. Chris will schedule them for later this week. We also need to get some siding to replace the wall they have been pulling off of in Building 10. | H16: Need to get the siding to replenish the wall they have been pulling off of, also get them scheduled to start the punch work. | I16: 45505 | J16: Done
B17: Pines @ Peach | C17: Joe | D17: Pristine | G17: Outside of 3 done / Working on Outside of 2 - KMW has Pissed off the owners. Change order for Ceilings at top floors & Breezeways has been approved. 2 crews are working on re-insulating the windows on backside on buildings 3 and 2 Also have the same crews working on the breezeways Along with putting in flashing and 2x10 in place (flashing taped and flex taped all joints along with ty-vec work) (Porches are back flush on buildings 2 & 3) | H17: CHANGE ORDERS??? | J17: Done
B18: Mountain Glen | C18: Chris | D18: Pristine / Rigo | G18: Rigo was installing doors in the UFAS units, sample walls for siding have been hung on building 144 for viewing. Siding order will ship 12/3 and will arrive 12/5 - 12/6. Last truck of doors was delivered by Sik Sunday 12/1. Consolidate containers on site so that we have room to store our siding, and need to be prepared to unload siding when it arrives. | H18: Need to find out what JGBR will be doing at Mountain Glen with Phillip, weather it is exterior work or interior work. Confirm if exterior doors are in the trailer Sik hauled up Sunday.
B19: Holbrook | C19: Chris | D19: Pristine / Zavala | G19: Zavala has his guys starting to felt Building 3 (Type 3). They have shingles on all amenities and garages. Building 2 also has shingles on it and now needs only the metal roofing. Jonathan also has sent us the material list for the metal he will be needing. | H19: Call Jonathan, and make sure he has guys on site to unload truck of siding. (Carefully)
B20: Dloniak House | C20: Crawl Diddy | D20: Pinnacle | G20: 3rd party Footing Inspection for Pinnacle Footers due to bad weather and emailed a copy of the Inspection to City of Greensboro (James Wolffe) / (Huntley Brothers) are wrapping up foundation perimeter (CMU block, brick and mortar) *Trash Dumpster is on site along with porty potty* CONTACTED Castro (framer) & Riverside Truss - Cliff (trusses) they want to meet 12/24 at 9AM and call Steve (Pro-Chem) for Termite spray before fondation inspection | H20: HOA Approval for Shingle and Metal color / Cables at front of site need to be burried lower for driveway (Call contacts on email)
B21: Woodfield - BD3 | C21: Joe | G21: Should finish 3/7/25
B24: Upcoming Projects (Start Date) | C24: Project Manager | D24: Subcontractor | F24: Customer Contact | G24: Weekly Planning Summary (Materials Ordered/Arrival Date/Change Order Submission Needed/Unsafe Conditions/Opportuities) | H24: Action Items This Week | I24: Estimated Start Date
B26: Aaron Mills | C26: Chris | D26: ? | G26: Framing in Process
B27: Jeffries -DHIC | C27: Joe
B28: Avonlea - DHIC | C28: Joe
B29: Sedgbrook - DHIC | C29: Joe
B30: Piney Pointe - BD3 | C30: Joe
B31: Brookside - BD3 | C31: Joe
B32: Woodfield - BD3 | C32: Joe
B33: Burnside - BD3 | C33: Joe
B34: Pipeline/Bids | C34: Project Manager | D34: Anticipated Subcontractor | E34: Estimated Start Date | F34: Customer Contact | G34: Bid Status | H34: Action Needed/Comments | I34: Estimated Start Date
B36: PPM - Regal Oaks | F36: Jason Buffkin | G36: Resent Estimate on 5-28-24 - OCN
B37: PPM-Kings Crossing | C37: Not KW | F37: Buffkin | G37: Stair replacement, site steps, sidewalk plates
B38: PPM - Plantation Village | C38: Not KW | F38: Jason Buffkin | G38: Roofing, Windows, Dumpster Fence, Mailbox Posts, 8x8
B40: PPM - Little Pee Dee Manor | C40: Not KW | F40: Jason Buffkin | G40: Gazebo Enclosure, Fountain pricing
B41: PPM - Churchwood Apts | C41: Not KW | F41: Jason Buffkin | G41: 2 story bay window replacement , accent siding, aluminum columns per PM
B42: PPM - Greenfield | C42: Not KW | F42: Jason Buffkin | G42: Storage room doors, roof replacement, siding pricing per building
B43: KMW - Hartwood Village | C43: Not KW | G43: Roofing, windows, interior doors, hardware, dumpster fence | H43: Waiting on pricing back on interior doors/windows from GCL, ABC
B44: PPM - Westridge Apts. | C44: Not KW | F44: Jason Buffkin
B45: HRP Murrayville
B46: KMW - Fairway PH2 | G46: Bid sent to C. Binkowski on 11-10-22 *OCN 11/10/22 * *Again 10-23-24*
B47: KMW - Maynard Rd. | G47: Working on revised plans.

Sheet 12-2-24
B2: Team Meeting
B3: 12.2.24
B4: Present: Wes, Oscar, Chris, Joe, Carson & Stephanie (Seal Team 6, PRESENT)
B5: Topics
B6: 1.) | C6: Weekly: Sub calendar update/Daily Job Sheets/Photos Uploaded
B7: 2.) | C7: Calendar - use to help track Change Order Work
B8: 3.) | C8: Vehicles - keep oil changed, some inspections due 12/31 service truck
B9: 4.) | C9: Contract log -Need - CO Pungo waiting on this, DHIC, Mountain Glen
B10: 5.) | C10: Container lock keys on all vehicle key rings
B11: 6.) | C11: Retail: please add address of work performed
B12: 7.) | C12: Reminder - Add notes in memo line of estimate/CO emailed to customer
B13: 8.) | C13: Make sure all completed jobs are billed
B14: PROJECTS
B15: Current Projects (Start Date) | C15: Project Manager (always Chris) | D15: Subcontractor & Schedule THIS WEEK | E15: Subcontractor & Schedule NEXT WEEK/FUTURE | F15: Date Inventory Recorded | G15: Weekly Job Summary (Materials Ordered/Arrival Date/Work Performed/Action Taken) | H15: Action Items Next Week (Change Order Submission Needed/Unsafe Conditions/Materials/Opportuities) | I15: Estimated Job Completion Date | J15: CONTRACTS
B16: HRP Brightwood (4/2023) | C16: Chris | D16: Pristine | G16: Punch lists for Building 7 & 8 are ready, still waiting on the list from HRP to close out 5 & 6. When we have Siks guys back out there they need to seal the gutter that is leaking on 5. Chris will schedule them for later this week. We also need to get some siding to replace the wall they have been pulling off of in Building 10. | H16: Need to get the siding to replenish the wall they have been pulling off of, also get them scheduled to start the punch work. | I16: 45505 | J16: Done
B17: KMW Townsend Trace | C17: Chris | G17: Gutter Repair, Rigo | H17: Maybe this needs to be done on a Saturday | J17: Done
B18: Pines @ Peach | C18: Joe | D18: Pristine | G18: Outside of 3 done / Working on Outside of 2 - KMW has Pissed off the owners. Change order for Ceilings at top floors & Breezeways has been approved. 2 crews are working on re-insulating the windows on backside on buildings 3 and 2 Also have the same crews working on the breezeways Along with putting in flashing and 2x10 in place (flashing taped and flex taped all joints along with ty-vec work) (Porches are back flush on buildings 2 & 3) | H18: CHANGE ORDERS??? | J18: Done
B19: (KMW)Wakefield (5/2023) | C19: Joe | D19: Pristine | G19: Pristine was to re-install the fence infront of building 2, needed to widen the fence. - OCN Dropped off grate and it fits perfectly inside building (Wes welded it) | J19: Done
B20: KMW Evoke | C20: Chris | D20: Rogelio/Hillstone | G20: Rain delays for Hillstone. Rogelio work is change orders we will charge for. SA to send CO to Josh.
B21: KMW Pungo | C21: Joe | D21: Pristine /Concrete Manuel | G21: Want Stair rails done by wednsday, want to start ramp rails on Monday. Carson took trailer load of handrails 12/10/24 and Rogelio's crew was working on them this week. 12/18/24 Handrails were finished; Wes recieved messeages and pictures on handrails in place at 7pm. | H21: Bank recieved photos of work.
B22: Gatebay | C22: Joe/ Chris | D22: Pristine | G22: Finished up, need to call in a final inspection to close out the permits in their system. Joe had gone back to install siding on the second shed there and job was closed up after that.
B23: Mountain Glen | C23: Chris | D23: Pristine / Rigo | G23: Rigo was installing doors in the UFAS units, sample walls for siding have been hung on building 144 for viewing. Siding order will ship 12/3 and will arrive 12/5 - 12/6. Last truck of doors was delivered by Sik Sunday 12/1. Consolidate containers on site so that we have room to store our siding, and need to be prepared to unload siding when it arrives. | H23: Need to find out what JGBR will be doing at Mountain Glen with Phillip, weather it is exterior work or interior work. Confirm if exterior doors are in the trailer Sik hauled up Sunday.
B24: Holbrook | C24: Chris | D24: Pristine / Zavala | G24: Zavala has his guys starting to felt Building 3 (Type 3). They have shingles on all amenities and garages. Building 2 also has shingles on it and now needs only the metal roofing. Jonathan also has sent us the material list for the metal he will be needing. | H24: Call Jonathan, and make sure he has guys on site to unload truck of siding. (Carefully)
B25: Dloniak House | C25: Crawl Diddy | D25: Pinnacle | G25: 3rd party Footing Inspection for Pinnacle Footers due to bad weather and emailed a copy of the Inspection to City of Greensboro (James Wolffe) / (Huntley Brothers) are wrapping up foundation perimeter (CMU block, brick and mortar) *Trash Dumpster is on site along with porty potty* CONTACTED Castro (framer) & Riverside Truss - Cliff (trusses) they want to meet 12/24 at 9AM and call Steve (Pro-Chem) for Termite spray before fondation inspection | H25: HOA Approval for Shingle and Metal color / Cables at front of site need to be burried lower for driveway (Call contacts on email)
B26: Charlotte Park | G26: Bill to Evoke - Going to Fix Columns & Trim behind Meter box, dog wash
B27: PartnShip - Parkview | C27: Chris | J27: Cost Plus
B28: Ridgeway BD3 | C28: Chris | D28: Zavala | G28: Roofing for Building 5 & 6
B31: Upcoming Projects (Start Date) | C31: Project Manager | D31: Subcontractor | F31: Customer Contact | G31: Weekly Planning Summary (Materials Ordered/Arrival Date/Change Order Submission Needed/Unsafe Conditions/Opportuities) | H31: Action Items This Week | I31: Estimated Start Date
B33: Aaron Mills | C33: Chris | D33: ? | G33: Framing in Process
B34: Jeffries -DHIC | C34: Joe
B35: Avonlea - DHIC | C35: Joe
B36: Sedgbrook - DHIC | C36: Joe
B37: Piney Pointe - BD3 | C37: Joe
B38: Brookside - BD3 | C38: Joe
B39: Woodfield - BD3 | C39: Joe
B40: Burnside - BD3 | C40: Joe
B41: Pipeline/Bids | C41: Project Manager | D41: Anticipated Subcontractor | E41: Estimated Start Date | F41: Customer Contact | G41: Bid Status | H41: Action Needed/Comments | I41: Estimated Start Date
B43: PPM - Regal Oaks | F43: Jason Buffkin | G43: Resent Estimate on 5-28-24 - OCN
B44: PPM-Kings Crossing | C44: Not KW | F44: Buffkin | G44: Stair replacement, site steps, sidewalk plates
B45: PPM - Plantation Village | C45: Not KW | F45: Jason Buffkin | G45: Roofing, Windows, Dumpster Fence, Mailbox Posts, 8x8
B47: PPM - Little Pee Dee Manor | C47: Not KW | F47: Jason Buffkin | G47: Gazebo Enclosure, Fountain pricing
B48: PPM - Churchwood Apts | C48: Not KW | F48: Jason Buffkin | G48: 2 story bay window replacement , accent siding, aluminum columns per PM
B49: PPM - Greenfield | C49: Not KW | F49: Jason Buffkin | G49: Storage room doors, roof replacement, siding pricing per building
B50: KMW - Hartwood Village | C50: Not KW | G50: Roofing, windows, interior doors, hardware, dumpster fence | H50: Waiting on pricing back on interior doors/windows from GCL, ABC
B51: PPM - Westridge Apts. | C51: Not KW | F51: Jason Buffkin
B52: HRP Murrayville
B53: KMW - Fairway PH2 | G53: Bid sent to C. Binkowski on 11-10-22 *OCN 11/10/22 * *Again 10-23-24*
B54: KMW - Maynard Rd. | G54: Working on revised plans.

Sheet 8-26-24
B2: Team Meeting
B3: 8.26.24
B4: Present: Wes, Oscar, Chris & Stephanie (the fab 4 all here)
B5: Topics
B6: 1.) | C6: Weekly: Sub calendar update/Daily Job Sheets/Photos Uploaded
B7: 2.) | C7: Calendar - use to help track Change Order Work
B8: 3.) | C8: Travis Fisher H&E Equipment Services
B9: 4.) | C9: Contract log -Need - CO Pungo waiting on this, DHIC, Mountain Glen
B10: 5.) | C10: Container lock keys on all vehicle key rings
B11: 6.) | C11: Retail: please add address of work performed
B12: 7.) | C12: Reminder - Add notes in memo line of estimate/CO emailed to customer
B13: 8.) | C13: Make sure all completed jobs are billed
B14: PROJECTS
B15: Current Projects (Start Date) | C15: Project Manager (always Chris) | D15: Subcontractor & Schedule THIS WEEK | E15: Subcontractor & Schedule NEXT WEEK/FUTURE | F15: Date Inventory Recorded | G15: Weekly Job Summary (Materials Ordered/Arrival Date/Work Performed/Action Taken) | H15: Action Items Next Week (Change Order Submission Needed/Unsafe Conditions/Materials/Opportuities) | I15: Estimated Job Completion Date | J15: CONTRACTS
B16: HRP Brightwood (4/2023) | C16: Chris | D16: Pristine | G16: Punch list being completed, roof leaks being address, leak in clubhouse - Zavala to address when rain stop. Roofing to be picked up - Chris to have brought back to office, Oscar to call to pick up container once empty. | I16: 45505 | J16: Done
B17: KMW Townsend Trace | C17: Chris | J17: Done
B18: Pines @ Peach | C18: Chris | D18: Pristine | E18: Clubhouse | F18: TBD after framing complete on bldg 3 | G18: 7-29-24 - 1st truckloads arrived on site today, Chris went with Pristine to get them started to unload and staged. Flashing needs to be bent. Omar JR needs to give us the MF info.. - OCN | J18: Done
B19: (KMW)Wakefield (5/2023) | C19: Chris | G19: Pristine was to re-install the fence infront of building 2, needed to widen the fence. - OCN | J19: Done
B20: KMW Evoke | C20: Chris | D20: Rogelio/Hillstone | G20: Rain delays for Hillstone. Rogelio work is change orders we will charge for. SA to send CO to Josh. | H20: SA to enter CO for Rogelio work.
B21: KMW Pungo | C21: Chris | D21: Pristine /Concrete Manuel | G21: 7-29-24 - Rigo started to install Doors and trim in ADA units. we will need to get base trim from Lowes to complete. Need 4 Post for each rear deck
B22: Gatebay | C22: Chris | G22: Oscar to sign contracts, Chris working on permits
B23: Mountain Glen | G23: Need contract, Oscar working on unit pricing-Wes & Chris going this week - Rigo there 8/26. Sik to do siding, skip breezeways
B24: Holbrook
B28: Upcoming Projects (Start Date) | C28: Project Manager | D28: Subcontractor | F28: Customer Contact | G28: Weekly Planning Summary (Materials Ordered/Arrival Date/Change Order Submission Needed/Unsafe Conditions/Opportuities) | H28: Action Items This Week | I28: Estimated Start Date
B29: HRP Holbrook | D29: Eldin????
B30: Aaron Mills | D30: ?
B31: Mountain Glen - Brevard | C31: Chris | F31: Jason Buffkin | G31: 8-5-24 - Want to start demo in closets, need contract! - OCN
B32: Gatebay I&II | G32: 7-29-24 We have contracts for siding and 6 doors. Dont have windows? Still waiting to see what Frankie has to say. - OCN
B33: Pipeline/Bids | C33: Project Manager | D33: Anticipated Subcontractor | E33: Estimated Start Date | F33: Customer Contact | G33: Bid Status | H33: Action Needed/Comments | I33: Estimated Start Date
B35: PPM - Regal Oaks | F35: Jason Buffkin | G35: Resent Estimate on 5-28-24 - OCN
B36: PPM-Kings Crossing | C36: Not KW | F36: Buffkin | G36: Stair replacement, site steps, sidewalk plates
B37: PPM - Plantation Village | C37: Not KW | F37: Jason Buffkin | G37: Roofing, Windows, Dumpster Fence, Mailbox Posts, 8x8
B38: Mountain Glen - Brevard | G38: Re-Estimating, Should start after Pungo, Maybe August? - OCN
B39: PPM - Little Pee Dee Manor | C39: Not KW | F39: Jason Buffkin | G39: Gazebo Enclosure, Fountain pricing
B40: PPM - Churchwood Apts | C40: Not KW | F40: Jason Buffkin | G40: 2 story bay window replacement , accent siding, aluminum columns per PM
B41: PPM - Greenfield | C41: Not KW | F41: Jason Buffkin | G41: Storage room doors, roof replacement, siding pricing per building
B42: KMW - Hartwood Village | C42: Not KW | G42: Roofing, windows, interior doors, hardware, dumpster fence | H42: Waiting on pricing back on interior doors/windows from GCL, ABC
B43: PPM - Westridge Apts. | C43: Not KW | F43: Jason Buffkin
B44: HRP Murrayville
B45: KMW - Fairway PH2 | G45: Bid sent to C. Binkowski on 11-10-22 *OCN 11/10/22
B46: KMW - Maynard Rd. | G46: Working on revised plans.

Sheet 8-8-24
B2: Team Meeting
B3: 08.08.24
B4: Present: Wes, Oscar, Chris & Stephanie (the fab 4 all here)
B5: Topics
B6: 1.) | C6: Weekly: Sub calendar update/Daily Job Sheets/Photos Uploaded
B7: 2.) | C7: Calendar - use to help track Change Order Work
B8: 3.) | C8: PO - PM to enter prior to job start; note if it is a subcategory of a job the name doesn't feed down BOLO for this
B9: 4.) | C9: Contract log -Need - CO Pungo waiting on this, DHIC, Mountain Glen
B10: 5.) | C10: Container lock keys on all vehicle key rings
B11: 6.) | C11: Retail: please add address of work performed
B12: 7.) | C12: Reminder - Add notes in memo line of estimate/CO emailed to customer
B13: 8.) | C13: Make sure all completed jobs are billed
B14: PROJECTS
B15: Current Projects (Start Date) | C15: Project Manager (always Chris) | D15: Subcontractor & Schedule THIS WEEK | E15: Subcontractor & Schedule NEXT WEEK/FUTURE | F15: Date Inventory Recorded | G15: Weekly Job Summary (Materials Ordered/Arrival Date/Work Performed/Action Taken) | H15: Action Items Next Week (Change Order Submission Needed/Unsafe Conditions/Materials/Opportuities) | I15: Estimated Job Completion Date | J15: CONTRACTS
B16: HRP Brightwood (4/2023) | C16: Chris | D16: Pristine | G16: Punch list being completed, roof leaks being address, leak in clubhouse - Zavala to address when rain stop. Roofing to be picked up - Chris to have brought back to office, Oscar to call to pick up container once empty. | I16: 45505 | J16: Done
B17: KMW Townsend Trace | C17: Chris | J17: Done
B18: Pines @ Peach | C18: Chris | D18: Pristine | E18: Clubhouse | F18: TBD after framing complete on bldg 3 | G18: 7-29-24 - 1st truckloads arrived on site today, Chris went with Pristine to get them started to unload and staged. Flashing needs to be bent. Omar JR needs to give us the MF info.. - OCN | J18: Done
B19: (KMW)Wakefield (5/2023) | C19: Chris | G19: Pristine was to re-install the fence infront of building 2, needed to widen the fence. - OCN | J19: Done
B20: KMW Evoke | C20: Chris | D20: Rogelio/Hillstone | G20: Rain delays for Hillstone. Rogelio work is change orders we will charge for. SA to send CO to Josh. | H20: SA to enter CO for Rogelio work.
B21: KMW Pungo | C21: Chris | D21: Pristine /Concrete Manuel | G21: 7-29-24 - Rigo started to install Doors and trim in ADA units. we will need to get base trim from Lowes to complete. Need 4 Post for each rear deck
B22: Gatebay | C22: Chris | G22: Oscar to sign contracts, Chris working on permits
B23: Mountain Glen | G23: Need contract, Oscar working on unit pricing
B24: Holbrook
B28: Upcoming Projects (Start Date) | C28: Project Manager | D28: Subcontractor | F28: Customer Contact | G28: Weekly Planning Summary (Materials Ordered/Arrival Date/Change Order Submission Needed/Unsafe Conditions/Opportuities) | H28: Action Items This Week | I28: Estimated Start Date
B29: HRP Holbrook | D29: Eldin????
B30: Aaron Mills | D30: ?
B31: Mountain Glen - Brevard | C31: Chris | F31: Jason Buffkin | G31: 8-5-24 - Want to start demo in closets, need contract! - OCN
B32: Gatebay I&II | G32: 7-29-24 We have contracts for siding and 6 doors. Dont have windows? Still waiting to see what Frankie has to say. - OCN
B33: Pipeline/Bids | C33: Project Manager | D33: Anticipated Subcontractor | E33: Estimated Start Date | F33: Customer Contact | G33: Bid Status | H33: Action Needed/Comments | I33: Estimated Start Date
B35: PPM - Regal Oaks | F35: Jason Buffkin | G35: Resent Estimate on 5-28-24 - OCN
B36: PPM-Kings Crossing | C36: Not KW | F36: Buffkin | G36: Stair replacement, site steps, sidewalk plates
B37: PPM - Plantation Village | C37: Not KW | F37: Jason Buffkin | G37: Roofing, Windows, Dumpster Fence, Mailbox Posts, 8x8
B38: Mountain Glen - Brevard | G38: Re-Estimating, Should start after Pungo, Maybe August? - OCN
B39: PPM - Little Pee Dee Manor | C39: Not KW | F39: Jason Buffkin | G39: Gazebo Enclosure, Fountain pricing
B40: PPM - Churchwood Apts | C40: Not KW | F40: Jason Buffkin | G40: 2 story bay window replacement , accent siding, aluminum columns per PM
B41: PPM - Greenfield | C41: Not KW | F41: Jason Buffkin | G41: Storage room doors, roof replacement, siding pricing per building
B42: KMW - Hartwood Village | C42: Not KW | G42: Roofing, windows, interior doors, hardware, dumpster fence | H42: Waiting on pricing back on interior doors/windows from GCL, ABC
B43: PPM - Westridge Apts. | C43: Not KW | F43: Jason Buffkin
B44: HRP Murrayville
B45: KMW - Fairway PH2 | G45: Bid sent to C. Binkowski on 11-10-22 *OCN 11/10/22
B46: KMW - Maynard Rd. | G46: Working on revised plans.

Sheet 7-29-24
B2: Team Meeting
B3: 07.29.24
B4: Present: Wes, Oscar, Chris & Stephanie (the fab 4 all here)
B5: Topics
B6: 1.) | C6: Weekly: Sub calendar update/Daily Job Sheets/Photos Uploaded
B7: 2.) | C7: Started meeting at pm
B8: 3.) | C8: PO - PM to enter prior to job start; note if it is a subcategory of a job the name doesn't feed down BOLO for this
B9: 4.) | C9: Contract log
B10: 5.)
B11: 6.)
B12: 7.) | C12: Make sure all completed jobs are billed
B13: 8.)
B14: PROJECTS
B15: Current Projects (Start Date) | C15: Project Manager (always Chris) | D15: Subcontractor & Schedule THIS WEEK | E15: Subcontractor & Schedule NEXT WEEK/FUTURE | F15: Date Inventory Recorded | G15: Weekly Job Summary (Materials Ordered/Arrival Date/Work Performed/Action Taken) | H15: Action Items Next Week (Change Order Submission Needed/Unsafe Conditions/Materials/Opportuities) | I15: Estimated Job Completion Date | J15: CONTRACTS
B16: HRP Brightwood (4/2023) | C16: Chris | D16: Pristine | J16: Done
B17: KMW Townsend Trace | C17: Chris | D17: ELV | G17: 7-26-29 - Chris and Oscar picked up some left over material. Will still need said material for punch work, still waiting on siding to show up @ ABC so punch can be completed. - OCN | J17: Done
B18: Pines @ Peach | C18: Chris | D18: Pristine / Rogelio | G18: 7-29-24 - 1st truckloads arrived on site today, Chris went with Pristine to get them started to unload and staged. Flashing needs to be bent. Omar JR needs to give us the MF info.. - OCN
B19: (KMW)Wakefield (5/2023) | C19: Chris | D19: Pristine | G19: 7-29-24 - Pristine was to re-install the fence infront of building 2, needed to widen the fence. - OCN | J19: Done
B20: KMW Evoke | C20: Chris | D20: Towa / Rogelio
B21: KMW Pungo | C21: Chris | D21: Pristine / Rogelio / Concrete Manuel | G21: 7-29-24 - Rigo started to install Doors and trim in ADA units. we will need to get base trim from Lowes to complete. Need 4 Post for each rear deck
B28: Upcoming Projects (Start Date) | C28: Project Manager | D28: Subcontractor | F28: Customer Contact | G28: Weekly Planning Summary (Materials Ordered/Arrival Date/Change Order Submission Needed/Unsafe Conditions/Opportuities) | H28: Action Items This Week | I28: Estimated Start Date
B29: HRP Holbrook | D29: Eldin????
B30: Aaron Mills | D30: ?
B31: Mountain Glen - Brevard | C31: Chris | F31: Jason Buffkin | G31: 8-5-24 - Want to start demo in closets, need contract! - OCN
B32: Gatebay I&II | G32: 7-29-24 We have contracts for siding and 6 doors. Dont have windows? Still waiting to see what Frankie has to say. - OCN
B33: Pipeline/Bids | C33: Project Manager | D33: Anticipated Subcontractor | E33: Estimated Start Date | F33: Customer Contact | G33: Bid Status | H33: Action Needed/Comments | I33: Estimated Start Date
B35: PPM - Regal Oaks | F35: Jason Buffkin | G35: Resent Estimate on 5-28-24 - OCN
B36: PPM-Kings Crossing | C36: Not KW | F36: Buffkin | G36: Stair replacement, site steps, sidewalk plates
B37: PPM - Plantation Village | C37: Not KW | F37: Jason Buffkin | G37: Roofing, Windows, Dumpster Fence, Mailbox Posts, 8x8
B38: Mountain Glen - Brevard | G38: Re-Estimating, Should start after Pungo, Maybe August? - OCN
B39: PPM - Little Pee Dee Manor | C39: Not KW | F39: Jason Buffkin | G39: Gazebo Enclosure, Fountain pricing
B40: PPM - Churchwood Apts | C40: Not KW | F40: Jason Buffkin | G40: 2 story bay window replacement , accent siding, aluminum columns per PM
B41: PPM - Greenfield | C41: Not KW | F41: Jason Buffkin | G41: Storage room doors, roof replacement, siding pricing per building
B42: KMW - Hartwood Village | C42: Not KW | G42: Roofing, windows, interior doors, hardware, dumpster fence | H42: Waiting on pricing back on interior doors/windows from GCL, ABC
B43: PPM - Westridge Apts. | C43: Not KW | F43: Jason Buffkin
B44: HRP Murrayville
B45: KMW - Fairway PH2 | G45: Bid sent to C. Binkowski on 11-10-22 *OCN 11/10/22
B46: KMW - Maynard Rd. | G46: Working on revised plans.

Sheet 7-11-24
B2: Team Meeting
B3: 07.11.24
B4: Present: Wes, Oscar, Chris & Stephanie (the fab 4 all here)
B5: Topics
B6: 1.) | C6: Weekly: Sub calendar update/Daily Job Sheets/Photos Uploaded
B7: 2.) | C7: Started meeting at 3:35 am
B8: 3.) | C8: PO - PM to enter prior to job start; note if it is a subcategory of a job the name doesn't feed down BOLO for this
B9: 4.) | C9: Contract log
B10: 5.)
B11: 6.)
B12: 7.) | C12: Make sure all completed jobs are billed
B13: 8.)
B14: PROJECTS
B15: Current Projects (Start Date) | C15: Project Manager (always Chris) | D15: Subcontractor & Schedule THIS WEEK | E15: Subcontractor & Schedule NEXT WEEK/FUTURE | F15: Date Inventory Recorded | G15: Weekly Job Summary (Materials Ordered/Arrival Date/Work Performed/Action Taken) | H15: Action Items Next Week (Change Order Submission Needed/Unsafe Conditions/Materials/Opportuities) | I15: Estimated Job Completion Date | J15: CONTRACTS
B16: HRP Brightwood (4/2023) | C16: Chris | D16: Pristine | J16: Done
B17: KMW Townsend Trace | C17: Chris | D17: ELV | J17: Done
B18: Pines @ Peach | C18: Chris | D18: Pristine / Rogelio
B19: (KMW)Wakefield (5/2023) | C19: Chris | D19: Pristine | J19: Done
B20: KMW Evoke | C20: Chris | D20: Towa / Rogelio
B21: KMW Pungo | C21: Chris | D21: Pristine / Rogelio
B22: HRP Pine Forest | C22: Chris | D22: Pristine
B23: HRP Weaverville | C23: Chris | D23: Towa
B28: Upcoming Projects (Start Date) | C28: Project Manager | D28: Subcontractor | G28: Weekly Planning Summary (Materials Ordered/Arrival Date/Change Order Submission Needed/Unsafe Conditions/Opportuities) | H28: Action Items This Week | I28: Estimated Start Date
B29: HRP Holbrook | D29: Eldin???? | G29: Should poured concrete for clubhous this week - OCN
B30: Aaron Mills | D30: ? | G30: Awarded, Will start working on initial setup - OCN
B31: Mountain Glen - Brevard | C31: Chris | F31: Jason Buffkin | G31: Wes/Chris/Rigo going to reframe an HVAC closet
B32: Pipeline/Bids | C32: Project Manager | D32: Anticipated Subcontractor | E32: Estimated Start Date | F32: Customer Contact | G32: Bid Status | H32: Action Needed/Comments | I32: Estimated Start Date
B34: PPM - Regal Oaks | F34: Jason Buffkin | G34: Resent Estimate on 5-28-24 - OCN
B35: PPM-Kings Crossing | C35: Not KW | F35: Buffkin | G35: Stair replacement, site steps, sidewalk plates
B36: PPM - Plantation Village | C36: Not KW | F36: Jason Buffkin | G36: Roofing, Windows, Dumpster Fence, Mailbox Posts, 8x8
B37: Mountain Glen - Brevard | G37: Re-Estimating, Should start after Pungo, Maybe August? - OCN
B38: PPM - Little Pee Dee Manor | C38: Not KW | F38: Jason Buffkin | G38: Gazebo Enclosure, Fountain pricing
B39: PPM - Churchwood Apts | C39: Not KW | F39: Jason Buffkin | G39: 2 story bay window replacement , accent siding, aluminum columns per PM
B40: PPM - Greenfield | C40: Not KW | F40: Jason Buffkin | G40: Storage room doors, roof replacement, siding pricing per building
B41: KMW - Hartwood Village | C41: Not KW | G41: Roofing, windows, interior doors, hardware, dumpster fence | H41: Waiting on pricing back on interior doors/windows from GCL, ABC
B42: PPM - Westridge Apts. | C42: Not KW | F42: Jason Buffkin
B43: HRP Murrayville
B44: KMW - Fairway PH2 | G44: Bid sent to C. Binkowski on 11-10-22 *OCN 11/10/22
B45: KMW - Maynard Rd. | G45: Sent pricing revision to C. Binkowski on 7/28/22.

Sheet 6-7-24
B2: Team Meeting
B3: 06.7.24
B4: Present: Wes, Oscar, Chris (the fab 4 minus Stephanie)
B5: Topics
B6: 1.) | C6: Weekly: Sub calendar update/Daily Job Sheets/Photos Uploaded
B7: 2.) | C7: Started meeting at 10:15am, Ended very fast, Restarted with Andy's around 3pm
B8: 3.) | C8: PO - PM to enter prior to job start; note if it is a subcategory of a job the name doesn't feed down BOLO for this
B9: 4.) | C9: Contract log
B10: 5.)
B11: 6.)
B12: 7.) | C12: Make sure all completed jobs are billed
B13: 8.)
B14: PROJECTS
B15: Current Projects (Start Date) | C15: Project Manager (always Chris) | D15: Subcontractor & Schedule THIS WEEK | E15: Subcontractor & Schedule NEXT WEEK/FUTURE | F15: Date Inventory Recorded | G15: Weekly Job Summary (Materials Ordered/Arrival Date/Work Performed/Action Taken) | H15: Action Items Next Week (Change Order Submission Needed/Unsafe Conditions/Materials/Opportuities) | I15: Estimated Job Completion Date | J15: CONTRACTS
B16: HRP Brightwood (4/2023) | C16: Chris | D16: Pristine | G16: Currently on 9,10, breezeways in 7. Some Fiber Cement on 11 started - OCN | J16: Done
B17: KMW Townsend Trace | C17: Chris | D17: ELV | G17: Almost finished, Rogelio cleaning out materials in containers. Taking back to ABC - OCN | J17: Done
B18: (KMW)Wakefield (5/2023) | C18: Chris | D18: Pristine | G18: Punch work - OCN | J18: Done
B19: KMW Evoke | C19: Chris | D19: Towa / Rogelio | G19: Monday/Tuesday Rails - OCN
B20: KMW Pungo | C20: Chris | D20: Pristine / Rogelio | G20: Send Rogelio to possibly do trim around doors in laundries Behind MF's- Wednesday? possibly go on the 17th. But if Traco goes faster, we could go Wednesday(12th) - OCN
B21: HRP Pine Forest | C21: Chris | D21: Pristine | G21: Siki repairing B&B - OCN
B22: Jerrets house | C22: Chris | D22: Towa | G22: Rigo did Gutters 6-6-24 - OCN
B23: HRP Weaverville | C23: Chris | D23: Towa | G23: Needs to fix what he did or didnt do - OCN
B28: Upcoming Projects (Start Date) | C28: Project Manager | D28: Subcontractor | G28: Weekly Planning Summary (Materials Ordered/Arrival Date/Change Order Submission Needed/Unsafe Conditions/Opportuities) | H28: Action Items This Week | I28: Estimated Start Date
B29: HRP Holbrook | D29: Eldin???? | G29: Should poured concrete for clubhous this week - OCN
B30: Pines @ Peach | C30: Chris | D30: Pristine / Rogelio | G30: Hardie material was sent to contract, writing contract for Prestine, building Truck Builder. Need to set up "Project" - OCN | H30: Writing up contract,
B31: Aaron Mills | D31: ? | G31: Awarded, Will start working on initial setup - OCN
B32: Mountain Glen - Brevard | C32: Chris | F32: Jason Buffkin | G32: Re-Estimating, Should start after Pungo, Maybe August? -OCN
B33: Pipeline/Bids | C33: Project Manager | D33: Anticipated Subcontractor | E33: Estimated Start Date | F33: Customer Contact | G33: Bid Status | H33: Action Needed/Comments | I33: Estimated Start Date
B35: PPM - Regal Oaks | F35: Jason Buffkin | G35: Resent Estimate on 5-28-24 - OCN
B36: PPM-Kings Crossing | C36: Not KW | F36: Buffkin | G36: Stair replacement, site steps, sidewalk plates
B37: PPM - Plantation Village | C37: Not KW | F37: Jason Buffkin | G37: Roofing, Windows, Dumpster Fence, Mailbox Posts, 8x8
B38: Mountain Glen - Brevard | G38: Re-Estimating, Should start after Pungo, Maybe August? - OCN
B39: PPM - Little Pee Dee Manor | C39: Not KW | F39: Jason Buffkin | G39: Gazebo Enclosure, Fountain pricing
B40: PPM - Churchwood Apts | C40: Not KW | F40: Jason Buffkin | G40: 2 story bay window replacement , accent siding, aluminum columns per PM
B41: PPM - Greenfield | C41: Not KW | F41: Jason Buffkin | G41: Storage room doors, roof replacement, siding pricing per building
B42: KMW - Hartwood Village | C42: Not KW | G42: Roofing, windows, interior doors, hardware, dumpster fence | H42: Waiting on pricing back on interior doors/windows from GCL, ABC
B43: PPM - Westridge Apts. | C43: Not KW | F43: Jason Buffkin
B44: HRP Murrayville
B45: KMW - Fairway PH2 | G45: Bid sent to C. Binkowski on 11-10-22 *OCN 11/10/22
B46: KMW - Maynard Rd. | G46: Sent pricing revision to C. Binkowski on 7/28/22.

Sheet 4-26-24
A2: Team Meeting
A3: 04.26.24
A4: Present: Wes, Oscar, Chris & Liam (the fab 4 All HERE)
A5: Topics
A6: 1.) | B6: Weekly: Sub calendar update/Daily Job Sheets/Photos Uploaded
A7: 2.) | B7: Started meeting at 8:10am
A8: 3.) | B8: PO - PM to enter prior to job start; note if it is a subcategory of a job the name doesn't feed down BOLO for this
A9: 4.) | B9: Contract log
A10: 5.)
A11: 6.)
A12: 7.) | B12: Make sure all completed jobs are billed
A13: 8.)
A14: PROJECTS
A15: Current Projects (Start Date) | B15: Project Manager | C15: Subcontractor & Schedule THIS WEEK | D15: Subcontractor & Schedule NEXT WEEK/FUTURE | E15: Date Inventory Recorded | F15: Weekly Job Summary (Materials Ordered/Arrival Date/Work Performed/Action Taken) | G15: Action Items Next Week (Change Order Submission Needed/Unsafe Conditions/Materials/Opportuities) | H15: Estimated Job Completion Date | I15: CONTRACTS
A16: HRP Brightwood (4/2023)
A17: KMW Townsend Trace | B17: Matt | C17: Pato
A18: (KMW)Wakefield (5/2023) | C18: Tulio
A19: KMW Pungo | C19: Sik, Rogelio
A30: Upcoming Projects (Start Date) | B30: Project Manager | C30: Subcontractor | F30: Weekly Planning Summary (Materials Ordered/Arrival Date/Change Order Submission Needed/Unsafe Conditions/Opportuities) | G30: Action Items This Week | H30: Estimated Start Date
B34: Wes
A35: Pipeline/Bids | B35: Project Manager | C35: Anticipated Subcontractor | D35: Estimated Start Date | E35: Customer Contact | F35: Bid Status | G35: Action Needed/Comments | H35: Estimated Start Date
A37: PPM - Regal Oaks | E37: Jason Buffkin | F37: Need to send Jason pricing for structural repairs ASAP. *SJH - 10/19/22
A38: PPM-Kings Crossing | B38: Not KW | E38: Jason Bufkin | F38: Stair replacement, site steps, sidewalk plates
A39: PPM - Plantation Village | B39: Not KW | E39: Jason Bufkin | F39: Roofing, Windows, Dumpster Fence, Mailbox Posts, 8x8
A40: PPM - Silver Trace Apts | B40: Not KW | E40: Jason Bufkin | F40: Stair Tread replacement, mailbox posts (8x8)
A41: PPM - Little Pee Dee Manor | B41: Not KW | E41: Jason Bufkin | F41: Gazebo Enclosure, Fountain pricing
A42: PPM - Churchwood Apts | B42: Not KW | E42: Jason Bufkin | F42: 2 story bay window replacement , accent siding, aluminum columns per PM
A43: PPM - Greenfield | B43: Not KW | E43: Jason Bufkin | F43: Storage room doors, roof replacement, siding pricing per building
A44: KMW Pines @ Peach Rd | F44: Estimate revised *OCN 1-6-23 | G44: Wes submitting. Due 1-9-23
A45: Mountain Glen - Brevard | B45: Not KW | D45: 44795 | E45: KMW | F45: Put off until 2023 | G45: Go measure week of 8/29-9/2/22
A46: KMW - Hartwood Village | B46: Not KW | F46: Roofing, windows, interior doors, hardware, dumpster fence | G46: Waiting on pricing back on interior doors/windows from GCL, ABC
A47: PPM - Westridge Apts. | B47: Not KW | E47: Jason Bufkin
A48: KMW - Wesleyan Homes | B48: Not KW | E48: Kyle McDowell | F48: Initial pricing estimate sent to KMac on Thursday, 5/19/22. *SJH 5/20/22 | G48: Potential start of February/Q1 of 2023
A49: HRP Murrayville | F49: Potentially starting on first week of June - waiting on contract approval. *SJH 5/20/22
A50: HRP Brightwood Farms | F50: Bid Submitted on 5/25/22. *SJH 5/27/22
A51: KMW - Fairway PH2 | F51: Bid sent to C. Binkowski on 11-10-22 *OCN 11/10/22
A52: KMW - Maynard Rd. | F52: Sent pricing revision to C. Binkowski on 7/28/22.
A53: HKJ Magnolia Hills
A54: HKJ Broadstone | F54: Bid has been sent
A55: HKJ Wynslow | F55: Bid has been sent
A56: Evolve @ North Shore | F56: working on quote
A57: Evolve @ Headwaters | F57: working on quote
A58: Evovle @ Northwest | F58: working on quote
A59: WC - Pegram Landing Ph2 | F59: Updated quote sent 11/1/22 *OCN
A60: Park @ Aventino | C60: SAVALA | G60: WA WORKING ON BID
A61: Windsor 4th&Elm | F61: Estimate sent *OCN 10/18/22
A63: Ginkgo - Glendare | E63: Paul Sidam | F63: Received return correspondence from Ginkgo that they are reviewing our price, but said that on first glance it is significantly higher. *SJH 8/24/22
A64: Ashley Oaks - Living Well Homes | F64: Waiting on payment for completed work in Sept. '22. No future jobs scheduled.
A65: SC Hail Job

Sheet 9-22-23
A2: Team Meeting
A3: 09.08.23
A4: Present: Wes, Oscar & Matt (the fab 3 All HERE)
A5: Topics
A6: 1.) | B6: Weekly: Sub calendar update/Daily Job Sheets/Photos Uploaded
A7: 2.) | B7: Started meeting at 8:15am
A8: 3.) | B8: PO - PM to enter prior to job start; note if it is a subcategory of a job the name doesn't feed down BOLO for this
A9: 4.) | B9: Contract log
A10: 5.)
A11: 6.)
A12: 7.) | B12: Make sure all completed jobs are billed
A13: 8.)
A14: PROJECTS
A15: Current Projects (Start Date) | B15: Project Manager | C15: Subcontractor & Schedule THIS WEEK | D15: Subcontractor & Schedule NEXT WEEK/FUTURE | E15: Date Inventory Recorded | F15: Weekly Job Summary (Materials Ordered/Arrival Date/Work Performed/Action Taken) | G15: Action Items Next Week (Change Order Submission Needed/Unsafe Conditions/Materials/Opportuities) | H15: Estimated Job Completion Date | I15: CONTRACTS
A16: HRP Brightwood (4/2023)
A17: KMW Townsend Trace | B17: Matt | C17: Pato | F17: Started on Clubhouse & Bld 1 9-21-23
A18: (KMW)Wakefield (5/2023) | C18: Tulio
A19: KMW Leo Loso/Gateway @ CLT Park $$$
A21: KMW Springfield
A23: HRP Waterway
A30: Upcoming Projects (Start Date) | B30: Project Manager | C30: Subcontractor | F30: Weekly Planning Summary (Materials Ordered/Arrival Date/Change Order Submission Needed/Unsafe Conditions/Opportuities) | G30: Action Items This Week | H30: Estimated Start Date
B34: Wes
A35: Pipeline/Bids | B35: Project Manager | C35: Anticipated Subcontractor | D35: Estimated Start Date | E35: Customer Contact | F35: Bid Status | G35: Action Needed/Comments | H35: Estimated Start Date
A37: PPM - Regal Oaks | E37: Jason Buffkin | F37: Need to send Jason pricing for structural repairs ASAP. *SJH - 10/19/22
A38: PPM-Kings Crossing | B38: Not KW | E38: Jason Bufkin | F38: Stair replacement, site steps, sidewalk plates
A39: PPM - Plantation Village | B39: Not KW | E39: Jason Bufkin | F39: Roofing, Windows, Dumpster Fence, Mailbox Posts, 8x8
A40: PPM - Silver Trace Apts | B40: Not KW | E40: Jason Bufkin | F40: Stair Tread replacement, mailbox posts (8x8)
A41: PPM - Little Pee Dee Manor | B41: Not KW | E41: Jason Bufkin | F41: Gazebo Enclosure, Fountain pricing
A42: PPM - Churchwood Apts | B42: Not KW | E42: Jason Bufkin | F42: 2 story bay window replacement , accent siding, aluminum columns per PM
A43: PPM - Greenfield | B43: Not KW | E43: Jason Bufkin | F43: Storage room doors, roof replacement, siding pricing per building
A44: KMW Pines @ Peach Rd | F44: Estimate revised *OCN 1-6-23 | G44: Wes submitting. Due 1-9-23
A45: Mountain Glen - Brevard | B45: Not KW | D45: 44795 | E45: KMW | F45: Put off until 2023 | G45: Go measure week of 8/29-9/2/22
A46: KMW - Hartwood Village | B46: Not KW | F46: Roofing, windows, interior doors, hardware, dumpster fence | G46: Waiting on pricing back on interior doors/windows from GCL, ABC
A47: PPM - Westridge Apts. | B47: Not KW | E47: Jason Bufkin
A48: KMW - Wesleyan Homes | B48: Not KW | E48: Kyle McDowell | F48: Initial pricing estimate sent to KMac on Thursday, 5/19/22. *SJH 5/20/22 | G48: Potential start of February/Q1 of 2023
A49: HRP Murrayville | F49: Potentially starting on first week of June - waiting on contract approval. *SJH 5/20/22
A50: HRP Brightwood Farms | F50: Bid Submitted on 5/25/22. *SJH 5/27/22
A51: KMW - Fairway PH2 | F51: Bid sent to C. Binkowski on 11-10-22 *OCN 11/10/22
A52: KMW - Maynard Rd. | F52: Sent pricing revision to C. Binkowski on 7/28/22.
A53: HKJ Magnolia Hills
A54: HKJ Broadstone | F54: Bid has been sent
A55: HKJ Wynslow | F55: Bid has been sent
A56: Evolve @ North Shore | F56: working on quote
A57: Evolve @ Headwaters | F57: working on quote
A58: Evovle @ Northwest | F58: working on quote
A59: WC - Pegram Landing Ph2 | F59: Updated quote sent 11/1/22 *OCN
A60: Park @ Aventino | C60: SAVALA | G60: WA WORKING ON BID
A61: Windsor 4th&Elm | F61: Estimate sent *OCN 10/18/22
A63: Ginkgo - Glendare | E63: Paul Sidam | F63: Received return correspondence from Ginkgo that they are reviewing our price, but said that on first glance it is significantly higher. *SJH 8/24/22
A64: Ashley Oaks - Living Well Homes | F64: Waiting on payment for completed work in Sept. '22. No future jobs scheduled.
A65: SC Hail Job

Sheet 9-8-23
A2: Team Meeting
A3: 09.08.23
A4: Present: Wes, Oscar & Matt (the fab 3 All HERE)
A5: Topics
A6: 1.) | B6: Weekly: Sub calendar update/Daily Job Sheets/Photos Uploaded
A7: 2.) | B7: Started meeting at 10:30am, Stephanie M.I.A - showed up late, at 10:45am and left at 10:55am. 10:56am Wes told Steph to GTFO
A8: 3.) | B8: PO - PM to enter prior to job start; note if it is a subcategory of a job the name doesn't feed down BOLO for this
A9: 4.) | B9: Contract log
A10: 5.)
A11: 6.)
A12: 7.) | B12: Make sure all completed jobs are billed
A13: 8.)
A14: PROJECTS
A15: Current Projects (Start Date) | B15: Project Manager | C15: Subcontractor & Schedule THIS WEEK | D15: Subcontractor & Schedule NEXT WEEK/FUTURE | E15: Date Inventory Recorded | F15: Weekly Job Summary (Materials Ordered/Arrival Date/Work Performed/Action Taken) | G15: Action Items Next Week (Change Order Submission Needed/Unsafe Conditions/Materials/Opportuities) | H15: Estimated Job Completion Date | I15: CONTRACTS
A16: HRP Brightwood (4/2023)
A17: KMW Townsend Trace
A18: (KMW)Wakefield (5/2023)
A19: KMW Leo Loso/Gateway @ CLT Park $$$
A21: KMW Springfield
A23: HRP Waterway
A30: Upcoming Projects (Start Date) | B30: Project Manager | C30: Subcontractor | F30: Weekly Planning Summary (Materials Ordered/Arrival Date/Change Order Submission Needed/Unsafe Conditions/Opportuities) | G30: Action Items This Week | H30: Estimated Start Date
B34: Wes
A35: Pipeline/Bids | B35: Project Manager | C35: Anticipated Subcontractor | D35: Estimated Start Date | E35: Customer Contact | F35: Bid Status | G35: Action Needed/Comments | H35: Estimated Start Date
A37: PPM - Regal Oaks | E37: Jason Buffkin | F37: Need to send Jason pricing for structural repairs ASAP. *SJH - 10/19/22
A38: PPM-Kings Crossing | B38: Not KW | E38: Jason Bufkin | F38: Stair replacement, site steps, sidewalk plates
A39: PPM - Plantation Village | B39: Not KW | E39: Jason Bufkin | F39: Roofing, Windows, Dumpster Fence, Mailbox Posts, 8x8
A40: PPM - Silver Trace Apts | B40: Not KW | E40: Jason Bufkin | F40: Stair Tread replacement, mailbox posts (8x8)
A41: PPM - Little Pee Dee Manor | B41: Not KW | E41: Jason Bufkin | F41: Gazebo Enclosure, Fountain pricing
A42: PPM - Churchwood Apts | B42: Not KW | E42: Jason Bufkin | F42: 2 story bay window replacement , accent siding, aluminum columns per PM
A43: PPM - Greenfield | B43: Not KW | E43: Jason Bufkin | F43: Storage room doors, roof replacement, siding pricing per building
A44: KMW Pines @ Peach Rd | F44: Estimate revised *OCN 1-6-23 | G44: Wes submitting. Due 1-9-23
A45: Mountain Glen - Brevard | B45: Not KW | D45: 44795 | E45: KMW | F45: Put off until 2023 | G45: Go measure week of 8/29-9/2/22
A46: KMW - Hartwood Village | B46: Not KW | F46: Roofing, windows, interior doors, hardware, dumpster fence | G46: Waiting on pricing back on interior doors/windows from GCL, ABC
A47: PPM - Westridge Apts. | B47: Not KW | E47: Jason Bufkin
A48: KMW - Wesleyan Homes | B48: Not KW | E48: Kyle McDowell | F48: Initial pricing estimate sent to KMac on Thursday, 5/19/22. *SJH 5/20/22 | G48: Potential start of February/Q1 of 2023
A49: HRP Murrayville | F49: Potentially starting on first week of June - waiting on contract approval. *SJH 5/20/22
A50: HRP Brightwood Farms | F50: Bid Submitted on 5/25/22. *SJH 5/27/22
A51: KMW - Fairway PH2 | F51: Bid sent to C. Binkowski on 11-10-22 *OCN 11/10/22
A52: KMW - Maynard Rd. | F52: Sent pricing revision to C. Binkowski on 7/28/22.
A53: HKJ Magnolia Hills
A54: HKJ Broadstone | F54: Bid has been sent
A55: HKJ Wynslow | F55: Bid has been sent
A56: Evolve @ North Shore | F56: working on quote
A57: Evolve @ Headwaters | F57: working on quote
A58: Evovle @ Northwest | F58: working on quote
A59: WC - Pegram Landing Ph2 | F59: Updated quote sent 11/1/22 *OCN
A60: Park @ Aventino | C60: SAVALA | G60: WA WORKING ON BID
A61: Windsor 4th&Elm | F61: Estimate sent *OCN 10/18/22
A63: Ginkgo - Glendare | E63: Paul Sidam | F63: Received return correspondence from Ginkgo that they are reviewing our price, but said that on first glance it is significantly higher. *SJH 8/24/22
A64: Ashley Oaks - Living Well Homes | F64: Waiting on payment for completed work in Sept. '22. No future jobs scheduled.
A65: SC Hail Job

Sheet 7-27-23
A2: Team Meeting
A3: 6.29.23
A4: Present: Wes, Oscar, Stephanie (who looks very nice today) and The Prince(the fab 4 All HERE)
A5: Topics
A6: 1.) | B6: Weekly: Sub calendar update/Daily Job Sheets/Photos Uploaded
A7: 2.) | B7: Siding/roofing/gutter/door/window pricing template (Do we have this? Timeline of initiative?) Nov 15 target date **Uplouded to SharePoint 10/28/22 *OCN**
A8: 3.) | B8: PO - PM to enter prior to job start; note if it is a subcategory of a job the name doesn't feed down BOLO for this
A9: 4.) | B9: Contract log
A10: 5.) | B10: Wesco 2016 Service truck. Inspection done 1-19-23 . Needs tires and brakes
A11: 6.) | B11: Wes' 2019 at Randy Marion Chevy in Statesville. Will have oil change, and inspection if needed. Possibly new tires while its there.
A12: 7.) | B12: Make sure all completed jobs are billed (Burlington Job) We should have at least partial billed this if roofing was going to be this far out from being done.
A13: 8.)
A14: PROJECTS
A15: Current Projects (Start Date) | B15: Project Manager | C15: Subcontractor & Schedule THIS WEEK | D15: Subcontractor & Schedule NEXT WEEK/FUTURE | E15: Date Inventory Recorded | F15: Weekly Job Summary (Materials Ordered/Arrival Date/Work Performed/Action Taken) | G15: Action Items Next Week (Change Order Submission Needed/Unsafe Conditions/Materials/Opportuities) | H15: Estimated Job Completion Date | I15: CONTRACTS
A16: HRP Haywood II | B16: Wes/Oscar | C16: Bruzz / Pato | E16: 44953 | F16: There is 100+ squares of siding coming in (Friday Feb 3rd that will need to be picked up/delivered to office) and delivered up to Asheville Monday Feb. 6th for Pato to start siding. Rigo may need to be there this week if available to do a little punch work. Otherwise Bruzz can do if need be. | G16: Get gutter material out of conex. Lets try to get rid of one of these conex's next week. (2-6-23) Need to make sure Pato has updated Insurance**Asked for updated insurance, their agent should be sending it over to us. OCN 2/3/23 **Lansing has a delay for siding, they are sendnig a truck up to Winchester VA to pick it up, and will try to deliver it to us Monday afternoon.** OCN 2-3-23 | H16: 44985 | I16: Zavala contract executed - Villeda need to see if in service truck
A17: HRP Pine Forest II | B17: Wes /CJ | E17: 44953 | F17: Samir is more than likely going to finish rest of project. I would say about 3 weeks. Need to get rest of shake material on the job and probably more solid soffit for breezeways. Need to confirm and get on job if necessary. | G17: Get gutter material inventory on job. Lansing should have remainder
A18: KMW Church St Lofts (4/2022) | B18: SJH | F18: Rigo at Church Street for week of 1/30-2/3 to complete scope of work, Change Orders, and punch list.
A19: KMW Leo Loso/Gateway @ CLT Park $$$ | B19: Wes/Sam | C19: Rogelio 4/13 | D19: Cipriano June-August | F19: Need to make sure left side of building 2 is finished. Need to get columns started and balconies finished. Where are we with Tiger Wood? Need to start moving materials off building 3 pad. Josh Has not yet submitted approval for use of the 4x4 posts in lieu of the steel posts. SH to follow up with Josh first thing on 1/30/23. | G19: SH sent email to J. Blevins on morning of 1/30/23. Will follow up by 1/31/23 if response is not received.
A20: KMW Retreat $$$ | B20: Wes | C20: Rogelio/Cipriano | D20: 44961 | F20: Rogelio and Cipriano are there finishing BS for KMW. Wes needs to get CO list together. | H20: 44788
A21: KMW Springfield | B21: SJH | F21: Manuel working on finishing last of initial push units. Should be completed by 2/1 or 2/2. Second push to begin immediately following - to include installation of windows, doors, door and bath hardware. ANTWAN WANTS TWO CREWS THERE FOR THIS PART IF POSSIBLE. | H21: 44985
A22: St. Marks | B22: SJH | F22: Jonathan completed final metal roofs - SH to visit site on 1/30 or 1/31 to walk last building to comfirm completion. Caleb says everything is done, but need to verify.
A23: HRP Waterway | B23: Wes/CJ | C23: Samir | F23: CJ this is for you! Get inspections on the Machines, and find someone local to work on them. Thanks Oscar | G23: Need subcontract for Samir*?? Has this been done CJ??
A24: PPM - Larchmont (Asheville, NC) | B24: SJH | C24: Rigo | E24: Jason Buffkin | F24: Carlos checking on final pricing for masonry repair. SH to give PPM price on interior repair completion outside of masonry repairs. SH will have estimate to PM by 1/31/23. Will pull permits and schedule repair work pending approval by PPM. | G24: Talked to Carlos on 1/31/23. He hopes to have his pricing back by 1/31/23-2/1/23 - SJH
A25: Springbranch - Becon (Wilmington, NC) | B25: Wes/Oscar | C25: Rogelio/Rigo | F25: Oscar - Alside's ship date is Feb13th / Maintenace wants to know if they need access inside the units or not, said last time they were able to do everything from outside. | G25: Waiting for confirmation for materials to arrive.
A26: 111 Tarpley St. | B26: SJH | C26: El Bruzz, Zavala | F26: Zavala installing roof morning of 1/30/23. Gutters to be installed as soon as weather permits. Invoice to be sent the same day gutters are completed | H26: 44965
A27: PPM - Wind Ridge | E27: Jason Buffkin | F27: Need (4) columns installed and beam wrapped on front porch. Can El Bruzz or Pato do this while at Haywood? Yes | H27: 2/3/23?
A28: PPM - Rocky Knoll | B28: SJH | F28: Unit 1G - Campbell electric to complete electrical repairs on 1/30/23. SH to confirm completion by end of day 1/30. Return to unit on Wednesday, 2/1/23 to install drywall and cabinets. **Working on schedule with trades to complete unit 1C.
A29: Melanie's House | F29: Plumbing? Insulation? When to deliver Drywall? | G29: Oscar has Hanger and Finisher lined up.
A30: Upcoming Projects (Start Date) | B30: Project Manager | C30: Subcontractor | F30: Weekly Planning Summary (Materials Ordered/Arrival Date/Change Order Submission Needed/Unsafe Conditions/Opportuities) | G30: Action Items This Week | H30: Estimated Start Date
A31: HRP Brightwood (4/2023)
A32: KMW Townsend Trace | B32: Wes
A33: (KMW)Wakefield (5/2023) | B33: Sam | F33: Lets get material list together. Need to order around 3-15-23
A34: Ariston Place - Windsor | B34: Wes | F34: We need to get samples submitted. See email from Windsor | G34: Get samples, a piece of each color cut in half, panels
A35: Pipeline/Bids | B35: Project Manager | C35: Anticipated Subcontractor | D35: Estimated Start Date | E35: Customer Contact | F35: Bid Status | G35: Action Needed/Comments | H35: Estimated Start Date
A37: PPM - Regal Oaks | E37: Jason Buffkin | F37: Need to send Jason pricing for structural repairs ASAP. *SJH - 10/19/22
A38: PPM-Kings Crossing | B38: Not KW | E38: Jason Bufkin | F38: Stair replacement, site steps, sidewalk plates
A39: PPM - Plantation Village | B39: Not KW | E39: Jason Bufkin | F39: Roofing, Windows, Dumpster Fence, Mailbox Posts, 8x8
A40: PPM - Silver Trace Apts | B40: Not KW | E40: Jason Bufkin | F40: Stair Tread replacement, mailbox posts (8x8)
A41: PPM - Little Pee Dee Manor | B41: Not KW | E41: Jason Bufkin | F41: Gazebo Enclosure, Fountain pricing
A42: PPM - Churchwood Apts | B42: Not KW | E42: Jason Bufkin | F42: 2 story bay window replacement , accent siding, aluminum columns per PM
A43: PPM - Greenfield | B43: Not KW | E43: Jason Bufkin | F43: Storage room doors, roof replacement, siding pricing per building
A44: KMW Pines @ Peach Rd | F44: Estimate revised *OCN 1-6-23 | G44: Wes submitting. Due 1-9-23
A45: Mountain Glen - Brevard | B45: Not KW | D45: 44795 | E45: KMW | F45: Put off until 2023 | G45: Go measure week of 8/29-9/2/22
A46: KMW - Hartwood Village | B46: Not KW | F46: Roofing, windows, interior doors, hardware, dumpster fence | G46: Waiting on pricing back on interior doors/windows from GCL, ABC
A47: PPM - Westridge Apts. | B47: Not KW | E47: Jason Bufkin
A48: KMW - Wesleyan Homes | B48: Not KW | E48: Kyle McDowell | F48: Initial pricing estimate sent to KMac on Thursday, 5/19/22. *SJH 5/20/22 | G48: Potential start of February/Q1 of 2023
A49: HRP Murrayville | F49: Potentially starting on first week of June - waiting on contract approval. *SJH 5/20/22
A50: HRP Brightwood Farms | F50: Bid Submitted on 5/25/22. *SJH 5/27/22
A51: KMW - Fairway PH2 | F51: Bid sent to C. Binkowski on 11-10-22 *OCN 11/10/22
A52: KMW - Maynard Rd. | F52: Sent pricing revision to C. Binkowski on 7/28/22.
A53: HKJ Magnolia Hills
A54: HKJ Broadstone | F54: Bid has been sent
A55: HKJ Wynslow | F55: Bid has been sent
A56: Evolve @ North Shore | F56: working on quote
A57: Evolve @ Headwaters | F57: working on quote
A58: Evovle @ Northwest | F58: working on quote
A59: WC - Pegram Landing Ph2 | F59: Updated quote sent 11/1/22 *OCN
A60: Park @ Aventino | C60: SAVALA | G60: WA WORKING ON BID
A61: Windsor 4th&Elm | F61: Estimate sent *OCN 10/18/22
A63: Ginkgo - Glendare | E63: Paul Sidam | F63: Received return correspondence from Ginkgo that they are reviewing our price, but said that on first glance it is significantly higher. *SJH 8/24/22
A64: Ashley Oaks - Living Well Homes | F64: Waiting on payment for completed work in Sept. '22. No future jobs scheduled.
A65: SC Hail Job

Sheet 6-29-23
A2: Team Meeting
A3: 6.29.23
A4: Present: Wes, Oscar, Stephanie (who looks very nice today) and The Prince(the fab 4 All HERE)
A5: Topics
A6: 1.) | B6: Weekly: Sub calendar update/Daily Job Sheets/Photos Uploaded
A7: 2.) | B7: Siding/roofing/gutter/door/window pricing template (Do we have this? Timeline of initiative?) Nov 15 target date **Uplouded to SharePoint 10/28/22 *OCN**
A8: 3.) | B8: PO - PM to enter prior to job start; note if it is a subcategory of a job the name doesn't feed down BOLO for this
A9: 4.) | B9: Contract log
A10: 5.) | B10: Wesco 2016 Service truck. Inspection done 1-19-23 . Needs tires and brakes
A11: 6.) | B11: Wes' 2019 at Randy Marion Chevy in Statesville. Will have oil change, and inspection if needed. Possibly new tires while its there.
A12: 7.) | B12: Make sure all completed jobs are billed (Burlington Job) We should have at least partial billed this if roofing was going to be this far out from being done.
A13: 8.)
A14: PROJECTS
A15: Current Projects (Start Date) | B15: Project Manager | C15: Subcontractor & Schedule THIS WEEK | D15: Subcontractor & Schedule NEXT WEEK/FUTURE | E15: Date Inventory Recorded | F15: Weekly Job Summary (Materials Ordered/Arrival Date/Work Performed/Action Taken) | G15: Action Items Next Week (Change Order Submission Needed/Unsafe Conditions/Materials/Opportuities) | H15: Estimated Job Completion Date | I15: CONTRACTS
A16: HRP Haywood II | B16: Wes/Oscar | C16: Bruzz / Pato | E16: 44953 | F16: There is 100+ squares of siding coming in (Friday Feb 3rd that will need to be picked up/delivered to office) and delivered up to Asheville Monday Feb. 6th for Pato to start siding. Rigo may need to be there this week if available to do a little punch work. Otherwise Bruzz can do if need be. | G16: Get gutter material out of conex. Lets try to get rid of one of these conex's next week. (2-6-23) Need to make sure Pato has updated Insurance**Asked for updated insurance, their agent should be sending it over to us. OCN 2/3/23 **Lansing has a delay for siding, they are sendnig a truck up to Winchester VA to pick it up, and will try to deliver it to us Monday afternoon.** OCN 2-3-23 | H16: 44985 | I16: Zavala contract executed - Villeda need to see if in service truck
A17: HRP Pine Forest II | B17: Wes /CJ | E17: 44953 | F17: Samir is more than likely going to finish rest of project. I would say about 3 weeks. Need to get rest of shake material on the job and probably more solid soffit for breezeways. Need to confirm and get on job if necessary. | G17: Get gutter material inventory on job. Lansing should have remainder
A18: KMW Church St Lofts (4/2022) | B18: SJH | F18: Rigo at Church Street for week of 1/30-2/3 to complete scope of work, Change Orders, and punch list.
A19: KMW Leo Loso/Gateway @ CLT Park $$$ | B19: Wes/Sam | C19: Rogelio 4/13 | D19: Cipriano June-August | F19: Need to make sure left side of building 2 is finished. Need to get columns started and balconies finished. Where are we with Tiger Wood? Need to start moving materials off building 3 pad. Josh Has not yet submitted approval for use of the 4x4 posts in lieu of the steel posts. SH to follow up with Josh first thing on 1/30/23. | G19: SH sent email to J. Blevins on morning of 1/30/23. Will follow up by 1/31/23 if response is not received.
A20: KMW Retreat $$$ | B20: Wes | C20: Rogelio/Cipriano | D20: 44961 | F20: Rogelio and Cipriano are there finishing BS for KMW. Wes needs to get CO list together. | H20: 44788
A21: KMW Springfield | B21: SJH | F21: Manuel working on finishing last of initial push units. Should be completed by 2/1 or 2/2. Second push to begin immediately following - to include installation of windows, doors, door and bath hardware. ANTWAN WANTS TWO CREWS THERE FOR THIS PART IF POSSIBLE. | H21: 44985
A22: St. Marks | B22: SJH | F22: Jonathan completed final metal roofs - SH to visit site on 1/30 or 1/31 to walk last building to comfirm completion. Caleb says everything is done, but need to verify.
A23: HRP Waterway | B23: Wes/CJ | C23: Samir | F23: CJ this is for you! Get inspections on the Machines, and find someone local to work on them. Thanks Oscar | G23: Need subcontract for Samir*?? Has this been done CJ??
A24: PPM - Larchmont (Asheville, NC) | B24: SJH | C24: Rigo | E24: Jason Buffkin | F24: Carlos checking on final pricing for masonry repair. SH to give PPM price on interior repair completion outside of masonry repairs. SH will have estimate to PM by 1/31/23. Will pull permits and schedule repair work pending approval by PPM. | G24: Talked to Carlos on 1/31/23. He hopes to have his pricing back by 1/31/23-2/1/23 - SJH
A25: Springbranch - Becon (Wilmington, NC) | B25: Wes/Oscar | C25: Rogelio/Rigo | F25: Oscar - Alside's ship date is Feb13th / Maintenace wants to know if they need access inside the units or not, said last time they were able to do everything from outside. | G25: Waiting for confirmation for materials to arrive.
A26: 111 Tarpley St. | B26: SJH | C26: El Bruzz, Zavala | F26: Zavala installing roof morning of 1/30/23. Gutters to be installed as soon as weather permits. Invoice to be sent the same day gutters are completed | H26: 44965
A27: PPM - Wind Ridge | E27: Jason Buffkin | F27: Need (4) columns installed and beam wrapped on front porch. Can El Bruzz or Pato do this while at Haywood? Yes | H27: 2/3/23?
A28: PPM - Rocky Knoll | B28: SJH | F28: Unit 1G - Campbell electric to complete electrical repairs on 1/30/23. SH to confirm completion by end of day 1/30. Return to unit on Wednesday, 2/1/23 to install drywall and cabinets. **Working on schedule with trades to complete unit 1C.
A29: Melanie's House | F29: Plumbing? Insulation? When to deliver Drywall? | G29: Oscar has Hanger and Finisher lined up.
A30: Upcoming Projects (Start Date) | B30: Project Manager | C30: Subcontractor | F30: Weekly Planning Summary (Materials Ordered/Arrival Date/Change Order Submission Needed/Unsafe Conditions/Opportuities) | G30: Action Items This Week | H30: Estimated Start Date | I30: Shits going to hit the fan, it is for sure! Bruh
A31: HRP Brightwood (4/2023)
A32: KMW Townsend Trace | B32: Wes
A33: (KMW)Wakefield (5/2023) | B33: Sam | F33: Lets get material list together. Need to order around 3-15-23
A34: Ariston Place - Windsor | B34: Wes | F34: We need to get samples submitted. See email from Windsor | G34: Get samples, a piece of each color cut in half, panels
A35: Pipeline/Bids | B35: Project Manager | C35: Anticipated Subcontractor | D35: Estimated Start Date | E35: Customer Contact | F35: Bid Status | G35: Action Needed/Comments | H35: Estimated Start Date
A37: PPM - Regal Oaks | E37: Jason Buffkin | F37: Need to send Jason pricing for structural repairs ASAP. *SJH - 10/19/22
A38: PPM-Kings Crossing | B38: Not KW | E38: Jason Bufkin | F38: Stair replacement, site steps, sidewalk plates
A39: PPM - Plantation Village | B39: Not KW | E39: Jason Bufkin | F39: Roofing, Windows, Dumpster Fence, Mailbox Posts, 8x8
A40: PPM - Silver Trace Apts | B40: Not KW | E40: Jason Bufkin | F40: Stair Tread replacement, mailbox posts (8x8)
A41: PPM - Little Pee Dee Manor | B41: Not KW | E41: Jason Bufkin | F41: Gazebo Enclosure, Fountain pricing
A42: PPM - Churchwood Apts | B42: Not KW | E42: Jason Bufkin | F42: 2 story bay window replacement , accent siding, aluminum columns per PM
A43: PPM - Greenfield | B43: Not KW | E43: Jason Bufkin | F43: Storage room doors, roof replacement, siding pricing per building
A44: KMW Pines @ Peach Rd | F44: Estimate revised *OCN 1-6-23 | G44: Wes submitting. Due 1-9-23
A45: Mountain Glen - Brevard | B45: Not KW | D45: 44795 | E45: KMW | F45: Put off until 2023 | G45: Go measure week of 8/29-9/2/22
A46: KMW - Hartwood Village | B46: Not KW | F46: Roofing, windows, interior doors, hardware, dumpster fence | G46: Waiting on pricing back on interior doors/windows from GCL, ABC
A47: PPM - Westridge Apts. | B47: Not KW | E47: Jason Bufkin
A48: KMW - Wesleyan Homes | B48: Not KW | E48: Kyle McDowell | F48: Initial pricing estimate sent to KMac on Thursday, 5/19/22. *SJH 5/20/22 | G48: Potential start of February/Q1 of 2023
A49: HRP Murrayville | F49: Potentially starting on first week of June - waiting on contract approval. *SJH 5/20/22
A50: HRP Brightwood Farms | F50: Bid Submitted on 5/25/22. *SJH 5/27/22
A51: KMW - Fairway PH2 | F51: Bid sent to C. Binkowski on 11-10-22 *OCN 11/10/22
A52: KMW - Maynard Rd. | F52: Sent pricing revision to C. Binkowski on 7/28/22.
A53: HKJ Magnolia Hills
A54: HKJ Broadstone | F54: Bid has been sent
A55: HKJ Wynslow | F55: Bid has been sent
A56: Evolve @ North Shore | F56: working on quote
A57: Evolve @ Headwaters | F57: working on quote
A58: Evovle @ Northwest | F58: working on quote
A59: WC - Pegram Landing Ph2 | F59: Updated quote sent 11/1/22 *OCN
A60: Park @ Aventino | C60: SAVALA | G60: WA WORKING ON BID
A61: Windsor 4th&Elm | F61: Estimate sent *OCN 10/18/22
A63: Ginkgo - Glendare | E63: Paul Sidam | F63: Received return correspondence from Ginkgo that they are reviewing our price, but said that on first glance it is significantly higher. *SJH 8/24/22
A64: Ashley Oaks - Living Well Homes | F64: Waiting on payment for completed work in Sept. '22. No future jobs scheduled.
A65: SC Hail Job

Sheet 4-3-23
A2: Team Meeting
A3: 4.3.23
A4: Present: Wes, Oscar, Stephanie (who looks very nice today) and The Prince(the fab 4 All HERE)
A5: Topics
A6: 1.) | B6: Weekly: Sub calendar update/Daily Job Sheets/Photos Uploaded
A7: 2.) | B7: Siding/roofing/gutter/door/window pricing template (Do we have this? Timeline of initiative?) Nov 15 target date **Uplouded to SharePoint 10/28/22 *OCN**
A8: 3.) | B8: PO - PM to enter prior to job start; note if it is a subcategory of a job the name doesn't feed down BOLO for this
A9: 4.) | B9: Contract log
A10: 5.) | B10: Wesco 2016 Service truck. Inspection done 1-19-23 . Needs tires and brakes
A11: 6.) | B11: Wes' 2019 at Randy Marion Chevy in Statesville. Will have oil change, and inspection if needed. Possibly new tires while its there.
A12: 7.) | B12: Make sure all completed jobs are billed (Burlington Job) We should have at least partial billed this if roofing was going to be this far out from being done.
A13: 8.)
A14: PROJECTS
A15: Current Projects (Start Date) | B15: Project Manager | C15: Subcontractor & Schedule THIS WEEK | D15: Subcontractor & Schedule NEXT WEEK/FUTURE | E15: Date Inventory Recorded | F15: Weekly Job Summary (Materials Ordered/Arrival Date/Work Performed/Action Taken) | G15: Action Items Next Week (Change Order Submission Needed/Unsafe Conditions/Materials/Opportuities) | H15: Estimated Job Completion Date | I15: CONTRACTS
A16: HRP Haywood II | B16: Wes/Oscar | C16: Bruzz / Pato | E16: 44953 | F16: There is 100+ squares of siding coming in (Friday Feb 3rd that will need to be picked up/delivered to office) and delivered up to Asheville Monday Feb. 6th for Pato to start siding. Rigo may need to be there this week if available to do a little punch work. Otherwise Bruzz can do if need be. | G16: Get gutter material out of conex. Lets try to get rid of one of these conex's next week. (2-6-23) Need to make sure Pato has updated Insurance**Asked for updated insurance, their agent should be sending it over to us. OCN 2/3/23 **Lansing has a delay for siding, they are sendnig a truck up to Winchester VA to pick it up, and will try to deliver it to us Monday afternoon.** OCN 2-3-23 | H16: 44985 | I16: Zavala contract executed - Villeda need to see if in service truck
A17: HRP Pine Forest II | B17: Wes /CJ | E17: 44953 | F17: Samir is more than likely going to finish rest of project. I would say about 3 weeks. Need to get rest of shake material on the job and probably more solid soffit for breezeways. Need to confirm and get on job if necessary. | G17: Get gutter material inventory on job. Lansing should have remainder
A18: KMW Church St Lofts (4/2022) | B18: SJH | F18: Rigo at Church Street for week of 1/30-2/3 to complete scope of work, Change Orders, and punch list.
A19: KMW Leo Loso/Gateway @ CLT Park $$$ | B19: Wes/Sam | C19: Rogelio 4/13 | D19: Cipriano June-August | F19: Need to make sure left side of building 2 is finished. Need to get columns started and balconies finished. Where are we with Tiger Wood? Need to start moving materials off building 3 pad. Josh Has not yet submitted approval for use of the 4x4 posts in lieu of the steel posts. SH to follow up with Josh first thing on 1/30/23. | G19: SH sent email to J. Blevins on morning of 1/30/23. Will follow up by 1/31/23 if response is not received.
A20: KMW Retreat $$$ | B20: Wes | C20: Rogelio/Cipriano | D20: 44961 | F20: Rogelio and Cipriano are there finishing BS for KMW. Wes needs to get CO list together. | H20: 44788
A21: KMW Springfield | B21: SJH | F21: Manuel working on finishing last of initial push units. Should be completed by 2/1 or 2/2. Second push to begin immediately following - to include installation of windows, doors, door and bath hardware. ANTWAN WANTS TWO CREWS THERE FOR THIS PART IF POSSIBLE. | H21: 44985
A22: St. Marks | B22: SJH | F22: Jonathan completed final metal roofs - SH to visit site on 1/30 or 1/31 to walk last building to comfirm completion. Caleb says everything is done, but need to verify.
A23: HRP Waterway | B23: Wes/CJ | C23: Samir | F23: CJ this is for you! Get inspections on the Machines, and find someone local to work on them. Thanks Oscar | G23: Need subcontract for Samir*?? Has this been done CJ??
A24: PPM - Larchmont (Asheville, NC) | B24: SJH | C24: Rigo | E24: Jason Buffkin | F24: Carlos checking on final pricing for masonry repair. SH to give PPM price on interior repair completion outside of masonry repairs. SH will have estimate to PM by 1/31/23. Will pull permits and schedule repair work pending approval by PPM. | G24: Talked to Carlos on 1/31/23. He hopes to have his pricing back by 1/31/23-2/1/23 - SJH
A25: Springbranch - Becon (Wilmington, NC) | B25: Wes/Oscar | C25: Rogelio/Rigo | F25: Oscar - Alside's ship date is Feb13th / Maintenace wants to know if they need access inside the units or not, said last time they were able to do everything from outside. | G25: Waiting for confirmation for materials to arrive.
A26: 111 Tarpley St. | B26: SJH | C26: El Bruzz, Zavala | F26: Zavala installing roof morning of 1/30/23. Gutters to be installed as soon as weather permits. Invoice to be sent the same day gutters are completed | H26: 44965
A27: PPM - Wind Ridge | E27: Jason Buffkin | F27: Need (4) columns installed and beam wrapped on front porch. Can El Bruzz or Pato do this while at Haywood? Yes | H27: 2/3/23?
A28: PPM - Rocky Knoll | B28: SJH | F28: Unit 1G - Campbell electric to complete electrical repairs on 1/30/23. SH to confirm completion by end of day 1/30. Return to unit on Wednesday, 2/1/23 to install drywall and cabinets. **Working on schedule with trades to complete unit 1C.
A29: Melanie's House | F29: Plumbing? Insulation? When to deliver Drywall? | G29: Oscar has Hanger and Finisher lined up.
A30: Upcoming Projects (Start Date) | B30: Project Manager | C30: Subcontractor | F30: Weekly Planning Summary (Materials Ordered/Arrival Date/Change Order Submission Needed/Unsafe Conditions/Opportuities) | G30: Action Items This Week | H30: Estimated Start Date | I30: Shits going to hit the fan, it is for sure! Bruh
A31: HRP Brightwood (4/2023)
A32: KMW Townsend Trace | B32: Wes
A33: (KMW)Wakefield (5/2023) | B33: Sam | F33: Lets get material list together. Need to order around 3-15-23
A34: Ariston Place - Windsor | B34: Wes | F34: We need to get samples submitted. See email from Windsor | G34: Get samples, a piece of each color cut in half, panels
A35: Pipeline/Bids | B35: Project Manager | C35: Anticipated Subcontractor | D35: Estimated Start Date | E35: Customer Contact | F35: Bid Status | G35: Action Needed/Comments | H35: Estimated Start Date
A37: PPM - Regal Oaks | E37: Jason Buffkin | F37: Need to send Jason pricing for structural repairs ASAP. *SJH - 10/19/22
A38: PPM-Kings Crossing | B38: Not KW | E38: Jason Bufkin | F38: Stair replacement, site steps, sidewalk plates
A39: PPM - Plantation Village | B39: Not KW | E39: Jason Bufkin | F39: Roofing, Windows, Dumpster Fence, Mailbox Posts, 8x8
A40: PPM - Silver Trace Apts | B40: Not KW | E40: Jason Bufkin | F40: Stair Tread replacement, mailbox posts (8x8)
A41: PPM - Little Pee Dee Manor | B41: Not KW | E41: Jason Bufkin | F41: Gazebo Enclosure, Fountain pricing
A42: PPM - Churchwood Apts | B42: Not KW | E42: Jason Bufkin | F42: 2 story bay window replacement , accent siding, aluminum columns per PM
A43: PPM - Greenfield | B43: Not KW | E43: Jason Bufkin | F43: Storage room doors, roof replacement, siding pricing per building
A44: KMW Pines @ Peach Rd | F44: Estimate revised *OCN 1-6-23 | G44: Wes submitting. Due 1-9-23
A45: Mountain Glen - Brevard | B45: Not KW | D45: 44795 | E45: KMW | F45: Put off until 2023 | G45: Go measure week of 8/29-9/2/22
A46: KMW - Hartwood Village | B46: Not KW | F46: Roofing, windows, interior doors, hardware, dumpster fence | G46: Waiting on pricing back on interior doors/windows from GCL, ABC
A47: PPM - Westridge Apts. | B47: Not KW | E47: Jason Bufkin
A48: KMW - Wesleyan Homes | B48: Not KW | E48: Kyle McDowell | F48: Initial pricing estimate sent to KMac on Thursday, 5/19/22. *SJH 5/20/22 | G48: Potential start of February/Q1 of 2023
A49: HRP Murrayville | F49: Potentially starting on first week of June - waiting on contract approval. *SJH 5/20/22
A50: HRP Brightwood Farms | F50: Bid Submitted on 5/25/22. *SJH 5/27/22
A51: KMW - Fairway PH2 | F51: Bid sent to C. Binkowski on 11-10-22 *OCN 11/10/22
A52: KMW - Maynard Rd. | F52: Sent pricing revision to C. Binkowski on 7/28/22.
A53: HKJ Magnolia Hills
A54: HKJ Broadstone | F54: Bid has been sent
A55: HKJ Wynslow | F55: Bid has been sent
A56: Evolve @ North Shore | F56: working on quote
A57: Evolve @ Headwaters | F57: working on quote
A58: Evovle @ Northwest | F58: working on quote
A59: WC - Pegram Landing Ph2 | F59: Updated quote sent 11/1/22 *OCN
A60: Park @ Aventino | C60: SAVALA | G60: WA WORKING ON BID
A61: Windsor 4th&Elm | F61: Estimate sent *OCN 10/18/22
A63: Ginkgo - Glendare | E63: Paul Sidam | F63: Received return correspondence from Ginkgo that they are reviewing our price, but said that on first glance it is significantly higher. *SJH 8/24/22
A64: Ashley Oaks - Living Well Homes | F64: Waiting on payment for completed work in Sept. '22. No future jobs scheduled.
A65: SC Hail Job

Sheet 1.30.23
A2: Team Meeting
A3: 1.30.23
A4: Present: Wes, Sam, Oscar, Stephanie (who looks very nice today) and The Prince(the fab 5 All HERE)
A5: Topics
A6: 1.) | B6: Weekly: Sub calendar update/Daily Job Sheets/Photos Uploaded
A7: 2.) | B7: Siding/roofing/gutter/door/window pricing template (Do we have this? Timeline of initiative?) Nov 15 target date **Uplouded to SharePoint 10/28/22 *OCN**
A8: 3.) | B8: PO - PM to enter prior to job start; note if it is a subcategory of a job the name doesn't feed down BOLO for this
A9: 4.) | B9: Contract log
A10: 5.) | B10: Wesco 2016 Service truck. Inspection done 1-19-23 . Needs tires and brakes
A11: 6.) | B11: Wes' 2019 at Randy Marion Chevy in Statesville. Will have oil change, and inspection if needed. Possibly new tires while its there.
A12: 7.) | B12: Make sure all completed jobs are billed (Burlington Job) We should have at least partial billed this if roofing was going to be this far out from being done.
A13: 8.)
A14: PROJECTS
A15: Current Projects (Start Date) | B15: Project Manager | C15: Subcontractor & Schedule THIS WEEK | D15: Subcontractor & Schedule NEXT WEEK/FUTURE | E15: Date Inventory Recorded | F15: Weekly Job Summary (Materials Ordered/Arrival Date/Work Performed/Action Taken) | G15: Action Items Next Week (Change Order Submission Needed/Unsafe Conditions/Materials/Opportuities) | H15: Estimated Job Completion Date | I15: CONTRACTS
A16: HRP Haywood II | B16: Wes/Oscar | C16: Bruzz / Pato | E16: 44953 | F16: Material is ordered to finish the last building. There is 10 boxes of j channel onsite and 2 more boxes at Lansing. There is 100+ squares of siding coming in (Friday Feb 3rd that will need to be picked up/delivered to office) and delivered up to Asheville Monday Feb. 6th for Pato to start siding. Rigo may need to be there this week if available to do a little punch work. Otherwise Bruzz can do if need be. | G16: Get gutter material out of conex. Lets try to get rid of one of these conex's next week. (1-30-23) Need to make sure Pato has updated Insurance** | H16: 44985 | I16: Zavala contract executed - Villeda need to see if in service truck
A17: HRP Pine Forest II | B17: Wes /CJ | E17: 44953 | F17: Samir is more than likely going to finish rest of project. I would say about 3 weeks. Need to get rest of shake material on the job and probably more solid soffit for breezeways. Need to confirm and get on job if necessary. | G17: Get gutter material inventory on job. Lansing should have remainder
A18: KMW Church St Lofts (4/2022) | B18: SJH | F18: Rigo at Church Street for week of 1/30-2/3 to complete scope of work, Change Orders, and punch list.
A19: KMW Leo Loso/Gateway @ CLT Park $$$ | B19: Wes/Sam | C19: Rogelio 4/13 | D19: Cipriano June-August | F19: Need to make sure left side of building 2 is finished. Need to get columns started and balconies finished. Where are we with Tiger Wood? Need to start moving materials off building 3 pad. Josh Has not yet submitted approval for use of the 4x4 posts in lieu of the steel posts. SH to follow up with Josh first thing on 1/30/23. | G19: SH sent email to J. Blevins on morning of 1/30/23. Will follow up by 1/31/23 if response is not received.
A20: KMW Retreat $$$ | B20: Wes | C20: Rogelio/Cipriano | D20: 44961 | F20: Rogelio and Cipriano are there finishing BS for KMW. Wes needs to get CO list together. | H20: 44788
A21: KMW Springfield | B21: SJH | F21: Manuel working on finishing last of initial push units. Should be completed by 2/1 or 2/2. Second push to begin immediately following - to include installation of windows, doors, door and bath hardware. ANTWAN WANTS TWO CREWS THERE FOR THIS PART IF POSSIBLE. | H21: 44985
A22: St. Marks | B22: SJH | F22: Jonathan completed final metal roofs - SH to visit site on 1/30 or 1/31 to walk last building to comfirm completion. Caleb says everything is done, but need to verify.
A23: HRP Waterway | B23: Wes/CJ | C23: Samir | F23: CJ this is for you! Get inspections on the Machines, and find someone local to work on them. Thanks Oscar | G23: Need subcontract for Samir*
A24: PPM - Larchmont (Asheville, NC) | B24: SJH | C24: Rigo | E24: Jason Buffkin | F24: Carlos checking on final pricing for masonry repair. SH to give PPM price on interior repair completion outside of masonry repairs. SH will have estimate to PM by 1/31/23. Will pull permits and schedule repair work pending approval by PPM. | G24: Talked to Carlos on 1/31/23. He hopes to have his pricing back by 1/31/23-2/1/23 - SJH
A25: Springbranch - Becon (Wilmington, NC) | B25: Wes/Oscar | C25: Rogelio/Rigo | F25: Please let maintence know what ship dates are. Oscar - Need contact info for maintenace, Alside's ship date is Feb13th | G25: Waiting for confirmation for materials to arrive.
A26: 111 Tarpley St. | B26: SJH | C26: El Bruzz, Zavala | F26: Zavala installing roof morning of 1/30/23. Gutters to be installed as soon as weather permits. Invoice to be sent the same day gutters are completed | H26: 44965
A27: PPM - Wind Ridge | E27: Jason Buffkin | F27: Need (4) columns installed and beam wrapped on front porch. Can El Bruzz or Pato do this while at Haywood? Yes | H27: 2/3/23?
A28: PPM - Rocky Knoll | B28: SJH | F28: Unit 1G - Campbell electric to complete electrical repairs on 1/30/23. SH to confirm completion by end of day 1/30. Return to unit on Wednesday, 2/1/23 to install drywall and cabinets. **Working on schedule with trades to complete unit 1C.
A29: Melanie's House | F29: Plumbing? Insulation? When to deliver Drywall? | G29: Oscar has Hanger and Finisher lined up.
A30: Upcoming Projects (Start Date) | B30: Project Manager | C30: Subcontractor | F30: Weekly Planning Summary (Materials Ordered/Arrival Date/Change Order Submission Needed/Unsafe Conditions/Opportuities) | G30: Action Items This Week | H30: Estimated Start Date | I30: Shits going to hit the fan, it is for sure! Bruh
A31: HRP Brightwood (4/2023)
A32: KMW Townsend Trace | B32: Wes
A33: (KMW)Wakefield (4/2023) | B33: Sam | F33: Lets get material list together. Need to order around 3-15-23
A34: Ariston Place - Windsor | B34: Wes | F34: We need to get samples submitted. See email from Windsor | G34: Get samples, a piece of each color cut in half, panels
A35: Pipeline/Bids | B35: Project Manager | C35: Anticipated Subcontractor | D35: Estimated Start Date | E35: Customer Contact | F35: Bid Status | G35: Action Needed/Comments | H35: Estimated Start Date
A37: PPM - Regal Oaks | E37: Jason Buffkin | F37: Need to send Jason pricing for structural repairs ASAP. *SJH - 10/19/22
A38: PPM-Kings Crossing | B38: Not KW | E38: Jason Bufkin | F38: Stair replacement, site steps, sidewalk plates
A39: PPM - Plantation Village | B39: Not KW | E39: Jason Bufkin | F39: Roofing, Windows, Dumpster Fence, Mailbox Posts, 8x8
A40: PPM - Silver Trace Apts | B40: Not KW | E40: Jason Bufkin | F40: Stair Tread replacement, mailbox posts (8x8)
A41: PPM - Little Pee Dee Manor | B41: Not KW | E41: Jason Bufkin | F41: Gazebo Enclosure, Fountain pricing
A42: PPM - Churchwood Apts | B42: Not KW | E42: Jason Bufkin | F42: 2 story bay window replacement , accent siding, aluminum columns per PM
A43: PPM - Greenfield | B43: Not KW | E43: Jason Bufkin | F43: Storage room doors, roof replacement, siding pricing per building
A44: KMW Pines @ Peach Rd | F44: Estimate revised *OCN 1-6-23 | G44: Wes submitting. Due 1-9-23
A45: Mountain Glen - Brevard | B45: Not KW | D45: 44795 | E45: KMW | F45: Put off until 2023 | G45: Go measure week of 8/29-9/2/22
A46: KMW - Hartwood Village | B46: Not KW | F46: Roofing, windows, interior doors, hardware, dumpster fence | G46: Waiting on pricing back on interior doors/windows from GCL, ABC
A47: PPM - Westridge Apts. | B47: Not KW | E47: Jason Bufkin
A48: KMW - Wesleyan Homes | B48: Not KW | E48: Kyle McDowell | F48: Initial pricing estimate sent to KMac on Thursday, 5/19/22. *SJH 5/20/22 | G48: Potential start of February/Q1 of 2023
A49: HRP Murrayville | F49: Potentially starting on first week of June - waiting on contract approval. *SJH 5/20/22
A50: HRP Brightwood Farms | F50: Bid Submitted on 5/25/22. *SJH 5/27/22
A51: KMW - Fairway PH2 | F51: Bid sent to C. Binkowski on 11-10-22 *OCN 11/10/22
A52: KMW - Maynard Rd. | F52: Sent pricing revision to C. Binkowski on 7/28/22.
A53: HKJ Magnolia Hills
A54: HKJ Broadstone | F54: Bid has been sent
A55: HKJ Wynslow | F55: Bid has been sent
A56: Evolve @ North Shore | F56: working on quote
A57: Evolve @ Headwaters | F57: working on quote
A58: Evovle @ Northwest | F58: working on quote
A59: WC - Pegram Landing Ph2 | F59: Updated quote sent 11/1/22 *OCN
A60: Park @ Aventino | C60: SAVALA | G60: WA WORKING ON BID
A61: Windsor 4th&Elm | F61: Estimate sent *OCN 10/18/22
A63: Ginkgo - Glendare | E63: Paul Sidam | F63: Received return correspondence from Ginkgo that they are reviewing our price, but said that on first glance it is significantly higher. *SJH 8/24/22
A64: Ashley Oaks - Living Well Homes | F64: Waiting on payment for completed work in Sept. '22. No future jobs scheduled.
A65: SC Hail Job

Sheet 1.6.23
A2: Team Meeting
A3: 1.6.23
A4: Present: Wes, Sam, Oscar, Stephanie (who looks very nice today even though she is in an exam) and The Prince(the fab 5 All HERE)
A5: Topics
A6: 1.) | B6: Weekly: Sub calendar update/Daily Job Sheets/Photos Uploaded
A7: 2.) | B7: Siding/roofing/gutter/door/window pricing template (Do we have this? Timeline of initiative?) Nov 15 target date **Uplouded to SharePoint 10/28/22 *OCN**
A8: 3.) | B8: PO - PM to enter prior to job start; note if it is a subcategory of a job the name doesn't feed down BOLO for this
A9: 4.) | B9: Contract log
A10: 5.)
A11: 6.) | B11: Vehicle Inspections 1998 GMC, 2007 Chevy, Service Truck, Wes
A12: 7.) | B12: Christmas
A13: 8.)
A14: PROJECTS
A15: Current Projects (Start Date) | B15: Project Manager | C15: Subcontractor & Schedule THIS WEEK | D15: Subcontractor & Schedule NEXT WEEK/FUTURE | E15: Date Inventory Recorded | F15: Weekly Job Summary (Materials Ordered/Arrival Date/Work Performed/Action Taken) | G15: Action Items Next Week (Change Order Submission Needed/Unsafe Conditions/Materials/Opportuities) | H15: Estimated Job Completion Date | I15: CONTRACTS
A16: HRP Haywood II | B16: Wes | C16: Cipriano | D16: Cipriano mid-April-June | F16: Manuel installed handrails on bldg 2 breezeways on 10/17. Waiting on bldgs 1 & 3 to be ready to install breezeway siding and soffit. *SJH - 10/19/22 | H16: 44798 | I16: Zavala contract executed - Villeda need to see if in service truck
A17: HRP Holly Springs | B17: Wes | C17: Abel Gamboa | D17: Abel through June (Crew 1) | F17: Building 1300 concrete poured 8-23. Was supposed to be poured first week of august. Was told on 8-19 by CSM and TC that 1300 was ready. Sent crew on Monday and it was not ready. See 8-23 job report for more info. 1500 concrete to be poured 9-8? | H17: 44795
A18: HRP Pine Forest II (4/16/22) | B18: Wes | D18: Abel Start Beg Aug. | E18: estimated start mid-May | F18: Remaining metal roofing order delivered on Tuesday, 8/30/22. Roofers began installing shingles on bldg 4 and metal on all bldgs. Zavala's measurements and quantities were incorrect - please see action items to the right. *SJH 9/6/22 | G18: Supplementary metal to be picked up between 9/8-9/9. Wes/CJ to take it if it arrives on 9/8, SJH to take it if it arrives on 9/9. *SJH 9/8/22
A19: KMW Church St Lofts (4/2022) | B19: SJH | F19: TKG working on installing corridor base and handrails backing, exterior and storage doors throughout the rest of the building, and hardware kits for units that are ready. *SJH - 10/19/22 | G19: Stay up to date on drywall progress.
A20: KMW Leo Loso/Gateway @ CLT Park $$$ | B20: Wes | C20: Rogelio 4/13 | D20: Cipriano June-August | F20: Cipriano working on courtyard of #2 until the weekend of 10/21, then he's moving to the outside of the building while grading and pool are installed. Hardie truck #11 scheduled for delivery on 10/20/22. Caulk delivered by SJH on 10/14. EZ.21 truck delivery is still en route, no tracking is available and they can't give us any more information on the driver's progress. *SJH - 10/19/22 | G20: Tiger wood planks sourced through Beeson Hardware, per Scott Boswell. Order not yet placed, but distributor has confirmed availability. *SJH 8/15/22
A21: KMW Retreat $$$ | B21: Wes | C21: Abel Gamboa | D21: Through 6-30(Crew 2) | E21: estimated 5/25/22 | F21: Guys not onsite this week due to wtf? 2 weeks to finish columns. waiting on abel for confirmation. | G21: Will need (4) pallets of 4x10 to finish columns. CJ to "make it happen" with other material *WA 8/4/22 | H21: 44788
A22: KMW Springfield | B22: SJH | F22: All preordered materials have arrived and are either on-site or in Wesco warehouse $80K profit - why? missing/miscoded invoices? Extra profit is from bathroom hardware order (not yet placed to save space in shop - pricing held on quote from HD Supply) *SJH - 10/19/22 | G22: Jason B. & Kyle M. Say that the job is likely to CLOSE in October, with work beginning in November. Still no confirmation on start date from KMW - *SJH - 10/19/22
A23: St. Marks | B23: SJH | F23: CO for storage fees approved and charged. Still no definite date on completion of breezeway gypcrete, but Caleb says the building should be ready for us "in two weeks". They have asked us to install gutters on #5 & Pool house ASAP - Rigo might be able to go as early as 10/20/22. *SJH - 10/19/22 | G23: Potential future job - vinyl ceilings in breezeways. Nothing new as of 9/2/22. No decision has been made here yet. *Caleb still doesn't have answer on this - it is not likely that this will be awarded at this point since the property is selling in a few weeks. *SJH - 10/19/22
A24: HRP Waterway | C24: Samir | F24: First 5 Truckloads have been delivered, Next 9 Trucks should arrive on or before 11/29. Also Ordered Breezeway Solid Soffit from Alside. *OCN 10/19/22. Need subcontract agreements - Samir - Hardie picking up 320 of 5/4x12 *OCN 11/10/22 | G24: Need subcontract for Samir*
A25: Carlisle Reno | F25: Job is completed and invoice was sent a month ago. Waiting on payment to be made. *SJH - 10/19/22
A26: PPM - Larchmont (Asheville, NC) | B26: SJH | C26: Rigo | E26: Jason Buffkin | F26: Manuel making corrections to framing repairs, reinstalling jack posts as permanent fixtures with (3) 2x8 beam, installing drywall and getting ready for final inspections. At current pace, Manuel should finish with work on 10/20 or 10/21. Final inspections to be performed at beginning of following week based on inspectors availability. *SJH - 10/19/22 | G26: Sam working with engineer to get pricing together for recently damaged exterior wall. Engineer is to submit repair plan for review on 10/19/22. *SJH - 10/19/22
A27: Springbranch - Becon (Wilmington, NC) | B27: Wes | C27: Rogelio/Rigo | F27: Replace 60 sashes | G27: Waiting for confirmation for materials to arrive.
A28: Upcoming Projects (Start Date) | B28: Project Manager | C28: Subcontractor | F28: Weekly Planning Summary (Materials Ordered/Arrival Date/Change Order Submission Needed/Unsafe Conditions/Opportuities) | G28: Action Items This Week | H28: Estimated Start Date
A29: HRP Brightwood (4/2023)
A31: Wakefield (4/2023) | F31: Sent Pricing hold list to C. Little on 7/11/22. Working on final ordering takeoff in preparation of job ordering. Job is delayed due to extensive blasting that is not yet complete. *SJH 7/11/22 | G31: SJH to follow up with Lansing on duration of pricing hold, as well as with KMW for job progress. Materials need to be ordered before contract pricing increases, but need to hold out as long as possible due to delayed job-start date. *SJH 8/24/22
A32: Melanie Combs house
A33: Pipeline/Bids | B33: Project Manager | C33: Anticipated Subcontractor | D33: Estimated Start Date | E33: Customer Contact | F33: Bid Status | G33: Action Needed/Comments | H33: Estimated Start Date
A34: PPM - Wind Ridge | E34: Jason Buffkin | F34: Get pricing together to complete panel replacement. *SJH - 10/19/22
A35: PPM - Regal Oaks | E35: Jason Buffkin | F35: Need to send Jason pricing for structural repairs ASAP. *SJH - 10/19/22
A36: PPM-Kings Crossing | B36: Not KW | E36: Jason Bufkin | F36: Stair replacement, site steps, sidewalk plates
A37: PPM - Plantation Village | B37: Not KW | E37: Jason Bufkin | F37: Roofing, Windows, Dumpster Fence, Mailbox Posts, 8x8
A38: PPM - Silver Trace Apts | B38: Not KW | E38: Jason Bufkin | F38: Stair Tread replacement, mailbox posts (8x8)
A39: PPM - Little Pee Dee Manor | B39: Not KW | E39: Jason Bufkin | F39: Gazebo Enclosure, Fountain pricing
A40: PPM - Churchwood Apts | B40: Not KW | E40: Jason Bufkin | F40: 2 story bay window replacement , accent siding, aluminum columns per PM
A41: PPM - Greenfield | B41: Not KW | E41: Jason Bufkin | F41: Storage room doors, roof replacement, siding pricing per building
A42: KMW Pines @ Peach Rd | F42: Estimate revised *OCN 1-6-23 | G42: Wes submitting. Due 1-9-23
A43: Mountain Glen - Brevard | B43: Not KW | D43: 44795 | E43: KMW | F43: Put off until 2023 | G43: Go measure week of 8/29-9/2/22
A44: KMW - Hartwood Village | B44: Not KW | F44: Roofing, windows, interior doors, hardware, dumpster fence | G44: Waiting on pricing back on interior doors/windows from GCL, ABC
A45: PPM - Westridge Apts. | B45: Not KW | E45: Jason Bufkin
A46: KMW - Wesleyan Homes | B46: Not KW | E46: Kyle McDowell | F46: Initial pricing estimate sent to KMac on Thursday, 5/19/22. *SJH 5/20/22 | G46: Potential start of February/Q1 of 2023
A47: HRP Murrayville | F47: Potentially starting on first week of June - waiting on contract approval. *SJH 5/20/22
A48: HRP Brightwood Farms | F48: Bid Submitted on 5/25/22. *SJH 5/27/22
A49: KMW - Fairway PH2 | F49: Bid sent to C. Binkowski on 11-10-22 *OCN 11/10/22
A50: KMW - Maynard Rd. | F50: Sent pricing revision to C. Binkowski on 7/28/22.
A51: HKJ Magnolia Hills
A52: HKJ Broadstone | F52: Bid has been sent
A53: HKJ Wynslow | F53: Bid has been sent
A54: WC - Pegram Landing Ph2 | F54: Updated quote sent 11/1/22 *OCN
A55: Park @ Aventino | C55: SAVALA | G55: WA WORKING ON BID
A56: Windsor 4th&Elm | F56: Estimate sent *OCN 10/18/22
A57: Ariston Place - Windsor | F57: Awaiting Subcontract *OCN 10/26/22
A58: Ginkgo - Glendare | E58: Paul Sidam | F58: Received return correspondence from Ginkgo that they are reviewing our price, but said that on first glance it is significantly higher. *SJH 8/24/22
A59: Ashley Oaks - Living Well Homes | F59: All currently awarded work has been completed. Property is working through budgets to approve outstanding quotes.
A60: SC Hail Job

Sheet 12.16.22
A2: Team Meeting
A3: 12.16.22
A4: Present: Wes, Sam, Oscar, Stephanie (who looks very nice today even though she is in an exam) and The Prince(the fab 5 All HERE)
A5: Topics
A6: 1.) | B6: Weekly: Sub calendar update/Daily Job Sheets/Photos Uploaded
A7: 2.) | B7: Siding/roofing/gutter/door/window pricing template (Do we have this? Timeline of initiative?) Nov 15 target date **Uplouded to SharePoint 10/28/22 *OCN**
A8: 3.) | B8: PO - PM to enter prior to job start; note if it is a subcategory of a job the name doesn't feed down BOLO for this
A9: 4.) | B9: Contract log
A10: 5.)
A11: 6.) | B11: Vehicle Inspections 1998 GMC, 2007 Chevy, Service Truck, Wes
A12: 7.) | B12: Christmas
A13: 8.)
A14: PROJECTS
A15: Current Projects (Start Date) | B15: Project Manager | C15: Subcontractor & Schedule THIS WEEK | D15: Subcontractor & Schedule NEXT WEEK/FUTURE | E15: Date Inventory Recorded | F15: Weekly Job Summary (Materials Ordered/Arrival Date/Work Performed/Action Taken) | G15: Action Items Next Week (Change Order Submission Needed/Unsafe Conditions/Materials/Opportuities) | H15: Estimated Job Completion Date | I15: CONTRACTS
A16: HRP Haywood II | B16: Wes | C16: Cipriano | D16: Cipriano mid-April-June | F16: Manuel installed handrails on bldg 2 breezeways on 10/17. Waiting on bldgs 1 & 3 to be ready to install breezeway siding and soffit. *SJH - 10/19/22 | H16: 44798 | I16: Zavala contract executed - Villeda need to see if in service truck
A17: HRP Holly Springs | B17: Wes | C17: Abel Gamboa | D17: Abel through June (Crew 1) | F17: Building 1300 concrete poured 8-23. Was supposed to be poured first week of august. Was told on 8-19 by CSM and TC that 1300 was ready. Sent crew on Monday and it was not ready. See 8-23 job report for more info. 1500 concrete to be poured 9-8? | H17: 44795
A18: HRP Pine Forest II (4/16/22) | B18: Wes | D18: Abel Start Beg Aug. | E18: estimated start mid-May | F18: Remaining metal roofing order delivered on Tuesday, 8/30/22. Roofers began installing shingles on bldg 4 and metal on all bldgs. Zavala's measurements and quantities were incorrect - please see action items to the right. *SJH 9/6/22 | G18: Supplementary metal to be picked up between 9/8-9/9. Wes/CJ to take it if it arrives on 9/8, SJH to take it if it arrives on 9/9. *SJH 9/8/22
A19: KMW Church St Lofts (4/2022) | B19: SJH | F19: TKG working on installing corridor base and handrails backing, exterior and storage doors throughout the rest of the building, and hardware kits for units that are ready. *SJH - 10/19/22 | G19: Stay up to date on drywall progress.
A20: KMW Leo Loso/Gateway @ CLT Park $$$ | B20: Wes | C20: Rogelio 4/13 | D20: Cipriano June-August | F20: Cipriano working on courtyard of #2 until the weekend of 10/21, then he's moving to the outside of the building while grading and pool are installed. Hardie truck #11 scheduled for delivery on 10/20/22. Caulk delivered by SJH on 10/14. EZ.21 truck delivery is still en route, no tracking is available and they can't give us any more information on the driver's progress. *SJH - 10/19/22 | G20: Tiger wood planks sourced through Beeson Hardware, per Scott Boswell. Order not yet placed, but distributor has confirmed availability. *SJH 8/15/22
A21: KMW Retreat $$$ | B21: Wes | C21: Abel Gamboa | D21: Through 6-30(Crew 2) | E21: estimated 5/25/22 | F21: Guys not onsite this week due to wtf? 2 weeks to finish columns. waiting on abel for confirmation. | G21: Will need (4) pallets of 4x10 to finish columns. CJ to "make it happen" with other material *WA 8/4/22 | H21: 44788
A22: KMW Springfield | B22: SJH | F22: All preordered materials have arrived and are either on-site or in Wesco warehouse $80K profit - why? missing/miscoded invoices? Extra profit is from bathroom hardware order (not yet placed to save space in shop - pricing held on quote from HD Supply) *SJH - 10/19/22 | G22: Jason B. & Kyle M. Say that the job is likely to CLOSE in October, with work beginning in November. Still no confirmation on start date from KMW - *SJH - 10/19/22
A23: St. Marks | B23: SJH | F23: CO for storage fees approved and charged. Still no definite date on completion of breezeway gypcrete, but Caleb says the building should be ready for us "in two weeks". They have asked us to install gutters on #5 & Pool house ASAP - Rigo might be able to go as early as 10/20/22. *SJH - 10/19/22 | G23: Potential future job - vinyl ceilings in breezeways. Nothing new as of 9/2/22. No decision has been made here yet. *Caleb still doesn't have answer on this - it is not likely that this will be awarded at this point since the property is selling in a few weeks. *SJH - 10/19/22
A24: HRP Waterway | C24: Samir | F24: First 5 Truckloads have been delivered, Next 9 Trucks should arrive on or before 11/29. Also Ordered Breezeway Solid Soffit from Alside. *OCN 10/19/22. Need subcontract agreements - Samir - Hardie picking up 320 of 5/4x12 *OCN 11/10/22 | G24: Need subcontract for Samir*
A25: Carlisle Reno | F25: Job is completed and invoice was sent a month ago. Waiting on payment to be made. *SJH - 10/19/22
A26: PPM - Larchmont (Asheville, NC) | B26: SJH | C26: Rigo | E26: Jason Buffkin | F26: Manuel making corrections to framing repairs, reinstalling jack posts as permanent fixtures with (3) 2x8 beam, installing drywall and getting ready for final inspections. At current pace, Manuel should finish with work on 10/20 or 10/21. Final inspections to be performed at beginning of following week based on inspectors availability. *SJH - 10/19/22 | G26: Sam working with engineer to get pricing together for recently damaged exterior wall. Engineer is to submit repair plan for review on 10/19/22. *SJH - 10/19/22
A27: Springbranch - Becon (Wilmington, NC) | B27: Wes | C27: Rogelio/Rigo | F27: Replace 60 sashes | G27: Waiting for confirmation for materials to arrive.
A28: Upcoming Projects (Start Date) | B28: Project Manager | C28: Subcontractor | F28: Weekly Planning Summary (Materials Ordered/Arrival Date/Change Order Submission Needed/Unsafe Conditions/Opportuities) | G28: Action Items This Week | H28: Estimated Start Date
A29: HRP Brightwood (4/2023)
A30: Wakefield (4/2023) | F30: Sent Pricing hold list to C. Little on 7/11/22. Working on final ordering takeoff in preparation of job ordering. Job is delayed due to extensive blasting that is not yet complete. *SJH 7/11/22 | G30: SJH to follow up with Lansing on duration of pricing hold, as well as with KMW for job progress. Materials need to be ordered before contract pricing increases, but need to hold out as long as possible due to delayed job-start date. *SJH 8/24/22
A31: Melanie Combs house
A32: Pipeline/Bids | B32: Project Manager | C32: Anticipated Subcontractor | D32: Estimated Start Date | E32: Customer Contact | F32: Bid Status | G32: Action Needed/Comments | H32: Estimated Start Date
A33: PPM - Wind Ridge | E33: Jason Buffkin | F33: Get pricing together to complete panel replacement. *SJH - 10/19/22
A34: PPM - Regal Oaks | E34: Jason Buffkin | F34: Need to send Jason pricing for structural repairs ASAP. *SJH - 10/19/22
A35: PPM-Kings Crossing | B35: Not KW | E35: Jason Bufkin | F35: Stair replacement, site steps, sidewalk plates
A36: PPM - Plantation Village | B36: Not KW | E36: Jason Bufkin | F36: Roofing, Windows, Dumpster Fence, Mailbox Posts, 8x8
A37: PPM - Silver Trace Apts | B37: Not KW | E37: Jason Bufkin | F37: Stair Tread replacement, mailbox posts (8x8)
A38: PPM - Little Pee Dee Manor | B38: Not KW | E38: Jason Bufkin | F38: Gazebo Enclosure, Fountain pricing
A39: PPM - Churchwood Apts | B39: Not KW | E39: Jason Bufkin | F39: 2 story bay window replacement , accent siding, aluminum columns per PM
A40: PPM - Greenfield | B40: Not KW | E40: Jason Bufkin | F40: Storage room doors, roof replacement, siding pricing per building
A41: Mountain Glen - Brevard | B41: Not KW | D41: 44795 | E41: KMW | F41: Put off until 2023 | G41: Go measure week of 8/29-9/2/22
A42: KMW - Hartwood Village | B42: Not KW | F42: Roofing, windows, interior doors, hardware, dumpster fence | G42: Waiting on pricing back on interior doors/windows from GCL, ABC
A43: PPM - Westridge Apts. | B43: Not KW | E43: Jason Bufkin
A44: KMW - Wesleyan Homes | B44: Not KW | E44: Kyle McDowell | F44: Initial pricing estimate sent to KMac on Thursday, 5/19/22. *SJH 5/20/22 | G44: Potential start of February/Q1 of 2023
A45: HRP Murrayville | F45: Potentially starting on first week of June - waiting on contract approval. *SJH 5/20/22
A46: HRP Brightwood Farms | F46: Bid Submitted on 5/25/22. *SJH 5/27/22
A47: KMW - Fairway PH2 | F47: Bid sent to C. Binkowski on 11-10-22 *OCN 11/10/22
A48: KMW - Maynard Rd. | F48: Sent pricing revision to C. Binkowski on 7/28/22.
A49: HKJ Magnolia Hills
A50: HKJ Broadstone | F50: Bid has been sent
A51: HKJ Wynslow | F51: Bid has been sent
A52: WC - Pegram Landing Ph2 | F52: Updated quote sent 11/1/22 *OCN
A53: Park @ Aventino | C53: SAVALA | G53: WA WORKING ON BID
A54: Windsor 4th&Elm | F54: Estimate sent *OCN 10/18/22
A55: Ariston Place - Windsor | F55: Awaiting Subcontract *OCN 10/26/22
A56: Ginkgo - Glendare | E56: Paul Sidam | F56: Received return correspondence from Ginkgo that they are reviewing our price, but said that on first glance it is significantly higher. *SJH 8/24/22
A57: Ashley Oaks - Living Well Homes | F57: All currently awarded work has been completed. Property is working through budgets to approve outstanding quotes.
A58: SC Hail Job

Sheet 12.2.22
A2: Team Meeting
A3: 12.2.22
A4: Present: Wes, Sam, Oscar, Stephanie (who looks very nice today) and The Prince(the fab 5 All HERE)
A5: Topics
A6: 1.) | B6: File Naming Strategies - use descriptive words like "Plans" as this makes it easier to locate later on
A7: 2.) | B7: Siding/roofing/gutter/door/window pricing template (Do we have this? Timeline of initiative?) Nov 15 target date **Uplouded to SharePoint 10/28/22 *OCN**
A8: 3.) | B8: Sub calendar
A9: 4.) | B9: Daily JOB sheets must be filled out. They will cover our ass eventually due to the sorry ass superintendents we are dealing with on 90% of our jobs. Follow up with emails and/or text messages.
A10: 5.) | B10: Prelim Job Checklist - PO - enter prior to job start - Contract (new log - in this workbook)
A11: 6.) | B11: Vehicle Inspections 1998 GMC, 2007 Chevy, Service Truck
A12: 7.) | B12: Time to tidy up office - Trash days Tuesday and Friday - if trash hasn't been taken out to curb when you are leaving the night before or arriving , please take it out.
A13: 8.) | B13: Hotels - ask your subs to send you receipts so you can check to be sure we aren't over charged. Put receipts in their CC folder with your initials and date on it so we know it's been reviewed.
A14: PROJECTS
A15: Current Projects (Start Date) | B15: Project Manager | C15: Subcontractor & Schedule THIS WEEK | D15: Subcontractor & Schedule NEXT WEEK/FUTURE | E15: Date Inventory Recorded | F15: Weekly Job Summary (Materials Ordered/Arrival Date/Work Performed/Action Taken) | G15: Action Items Next Week (Change Order Submission Needed/Unsafe Conditions/Materials/Opportuities) | H15: Estimated Job Completion Date | I15: CONTRACTS
A16: HRP Haywood II | B16: Wes | C16: Cipriano | D16: Cipriano mid-April-June | F16: Manuel installed handrails on bldg 2 breezeways on 10/17. Waiting on bldgs 1 & 3 to be ready to install breezeway siding and soffit. *SJH - 10/19/22 | H16: 44798 | I16: Zavala contract executed - Villeda need to see if in service truck
A17: HRP Holly Springs | B17: Wes | C17: Abel Gamboa | D17: Abel through June (Crew 1) | F17: Building 1300 concrete poured 8-23. Was supposed to be poured first week of august. Was told on 8-19 by CSM and TC that 1300 was ready. Sent crew on Monday and it was not ready. See 8-23 job report for more info. 1500 concrete to be poured 9-8? | H17: 44795
A18: HRP Pine Forest II (4/16/22) | B18: Wes | D18: Abel Start Beg Aug. | E18: estimated start mid-May | F18: Remaining metal roofing order delivered on Tuesday, 8/30/22. Roofers began installing shingles on bldg 4 and metal on all bldgs. Zavala's measurements and quantities were incorrect - please see action items to the right. *SJH 9/6/22 | G18: Supplementary metal to be picked up between 9/8-9/9. Wes/CJ to take it if it arrives on 9/8, SJH to take it if it arrives on 9/9. *SJH 9/8/22
A19: KMW Church St Lofts (4/2022) | B19: SJH | F19: TKG working on installing corridor base and handrails backing, exterior and storage doors throughout the rest of the building, and hardware kits for units that are ready. *SJH - 10/19/22 | G19: Stay up to date on drywall progress.
A20: KMW Leo Loso/Gateway @ CLT Park $$$ | B20: Wes | C20: Rogelio 4/13 | D20: Cipriano June-August | F20: Cipriano working on courtyard of #2 until the weekend of 10/21, then he's moving to the outside of the building while grading and pool are installed. Hardie truck #11 scheduled for delivery on 10/20/22. Caulk delivered by SJH on 10/14. EZ.21 truck delivery is still en route, no tracking is available and they can't give us any more information on the driver's progress. *SJH - 10/19/22 | G20: Tiger wood planks sourced through Beeson Hardware, per Scott Boswell. Order not yet placed, but distributor has confirmed availability. *SJH 8/15/22
A21: KMW Retreat $$$ | B21: Wes | C21: Abel Gamboa | D21: Through 6-30(Crew 2) | E21: estimated 5/25/22 | F21: Guys not onsite this week due to wtf? 2 weeks to finish columns. waiting on abel for confirmation. | G21: Will need (4) pallets of 4x10 to finish columns. CJ to "make it happen" with other material *WA 8/4/22 | H21: 44788
A22: KMW Springfield | B22: SJH | F22: All preordered materials have arrived and are either on-site or in Wesco warehouse $80K profit - why? missing/miscoded invoices? Extra profit is from bathroom hardware order (not yet placed to save space in shop - pricing held on quote from HD Supply) *SJH - 10/19/22 | G22: Jason B. & Kyle M. Say that the job is likely to CLOSE in October, with work beginning in November. Still no confirmation on start date from KMW - *SJH - 10/19/22
A23: St. Marks | B23: SJH | F23: CO for storage fees approved and charged. Still no definite date on completion of breezeway gypcrete, but Caleb says the building should be ready for us "in two weeks". They have asked us to install gutters on #5 & Pool house ASAP - Rigo might be able to go as early as 10/20/22. *SJH - 10/19/22 | G23: Potential future job - vinyl ceilings in breezeways. Nothing new as of 9/2/22. No decision has been made here yet. *Caleb still doesn't have answer on this - it is not likely that this will be awarded at this point since the property is selling in a few weeks. *SJH - 10/19/22
A24: HRP Waterway | C24: Samir | F24: First 5 Truckloads have been delivered, Next 9 Trucks should arrive on or before 11/29. Also Ordered Breezeway Solid Soffit from Alside. *OCN 10/19/22. Need subcontract agreements - Samir - Hardie picking up 320 of 5/4x12 *OCN 11/10/22 | G24: Need subcontract for Samir*
A25: Carlisle Reno | F25: Job is completed and invoice was sent a month ago. Waiting on payment to be made. *SJH - 10/19/22
A26: PPM - Larchmont (Asheville, NC) | B26: SJH | C26: Rigo | E26: Jason Buffkin | F26: Manuel making corrections to framing repairs, reinstalling jack posts as permanent fixtures with (3) 2x8 beam, installing drywall and getting ready for final inspections. At current pace, Manuel should finish with work on 10/20 or 10/21. Final inspections to be performed at beginning of following week based on inspectors availability. *SJH - 10/19/22 | G26: Sam working with engineer to get pricing together for recently damaged exterior wall. Engineer is to submit repair plan for review on 10/19/22. *SJH - 10/19/22
A27: Springbranch - Becon (Wilmington, NC) | B27: Wes | C27: Rogelio/Rigo | F27: Replace 60 sashes | G27: Waiting for confirmation for materials to arrive.
A28: Upcoming Projects (Start Date) | B28: Project Manager | C28: Subcontractor | F28: Weekly Planning Summary (Materials Ordered/Arrival Date/Change Order Submission Needed/Unsafe Conditions/Opportuities) | G28: Action Items This Week | H28: Estimated Start Date
A29: HRP Brightwood (4/2023)
A30: Wakefield (4/2023) | F30: Sent Pricing hold list to C. Little on 7/11/22. Working on final ordering takeoff in preparation of job ordering. Job is delayed due to extensive blasting that is not yet complete. *SJH 7/11/22 | G30: SJH to follow up with Lansing on duration of pricing hold, as well as with KMW for job progress. Materials need to be ordered before contract pricing increases, but need to hold out as long as possible due to delayed job-start date. *SJH 8/24/22
A31: Melanie Combs house
A32: Pipeline/Bids | B32: Project Manager | C32: Anticipated Subcontractor | D32: Estimated Start Date | E32: Customer Contact | F32: Bid Status | G32: Action Needed/Comments | H32: Estimated Start Date
A33: PPM - Wind Ridge | E33: Jason Buffkin | F33: Get pricing together to complete panel replacement. *SJH - 10/19/22
A34: PPM - Regal Oaks | E34: Jason Buffkin | F34: Need to send Jason pricing for structural repairs ASAP. *SJH - 10/19/22
A35: PPM-Kings Crossing | B35: Not KW | E35: Jason Bufkin | F35: Stair replacement, site steps, sidewalk plates
A36: PPM - Plantation Village | B36: Not KW | E36: Jason Bufkin | F36: Roofing, Windows, Dumpster Fence, Mailbox Posts, 8x8
A37: PPM - Silver Trace Apts | B37: Not KW | E37: Jason Bufkin | F37: Stair Tread replacement, mailbox posts (8x8)
A38: PPM - Little Pee Dee Manor | B38: Not KW | E38: Jason Bufkin | F38: Gazebo Enclosure, Fountain pricing
A39: PPM - Churchwood Apts | B39: Not KW | E39: Jason Bufkin | F39: 2 story bay window replacement , accent siding, aluminum columns per PM
A40: PPM - Greenfield | B40: Not KW | E40: Jason Bufkin | F40: Storage room doors, roof replacement, siding pricing per building
A41: Mountain Glen - Brevard | B41: Not KW | D41: 44795 | E41: KMW | F41: Put off until 2023 | G41: Go measure week of 8/29-9/2/22
A42: KMW - Hartwood Village | B42: Not KW | F42: Roofing, windows, interior doors, hardware, dumpster fence | G42: Waiting on pricing back on interior doors/windows from GCL, ABC
A43: PPM - Westridge Apts. | B43: Not KW | E43: Jason Bufkin
A44: KMW - Wesleyan Homes | B44: Not KW | E44: Kyle McDowell | F44: Initial pricing estimate sent to KMac on Thursday, 5/19/22. *SJH 5/20/22 | G44: Potential start of February/Q1 of 2023
A45: HRP Murrayville | F45: Potentially starting on first week of June - waiting on contract approval. *SJH 5/20/22
A46: HRP Brightwood Farms | F46: Bid Submitted on 5/25/22. *SJH 5/27/22
A47: KMW - Fairway PH2 | F47: Bid sent to C. Binkowski on 11-10-22 *OCN 11/10/22
A48: KMW - Maynard Rd. | F48: Sent pricing revision to C. Binkowski on 7/28/22.
A49: HKJ Magnolia Hills
A50: HKJ Broadstone | F50: Bid has been sent
A51: HKJ Wynslow | F51: Bid has been sent
A52: WC - Pegram Landing Ph2 | F52: Updated quote sent 11/1/22 *OCN
A53: Park @ Aventino | C53: SAVALA | G53: WA WORKING ON BID
A54: Windsor 4th&Elm | F54: Estimate sent *OCN 10/18/22
A55: Ariston Place - Windsor | F55: Awaiting Subcontract *OCN 10/26/22
A56: Ginkgo - Glendare | E56: Paul Sidam | F56: Received return correspondence from Ginkgo that they are reviewing our price, but said that on first glance it is significantly higher. *SJH 8/24/22
A57: Ashley Oaks - Living Well Homes | F57: All currently awarded work has been completed. Property is working through budgets to approve outstanding quotes.
A58: SC Hail Job

Sheet 11.10.22
A2: Team Meeting
A3: 11.10.22
A4: Present: Wes, Sam, Oscar, Stephanie (who looks very nice today) and The Prince(the fab 5 All HERE)
A5: Topics
A6: 1.) | B6: File Naming Strategies - use descriptive words like "Plans" as this makes it easier to locate later on
A7: 2.) | B7: Siding/roofing/gutter/door/window pricing template (Do we have this? Timeline of initiative?) Nov 15 target date **Uplouded to SharePoint 10/28/22 *OCN**
A8: 3.) | B8: Sub calendar
A9: 4.) | B9: Daily JOB sheets must be filled out. They will cover our ass eventually due to the sorry ass superintendents we are dealing with on 90% of our jobs. Follow up with emails and/or text messages.
A10: 5.) | B10: Prelim Job Checklist - PO - enter prior to job start - Contract (new log - in this workbook)
A11: 6.) | B11: Vehicle Inspections 1998 GMC, 2007 Chevy, Service Truck
A12: 7.) | B12: Time to tidy up office - Trash days Tuesday and Friday - if trash hasn't been taken out to curb when you are leaving the night before or arriving , please take it out.
A13: 8.) | B13: Hotels - ask your subs to send you receipts so you can check to be sure we aren't over charged. Put receipts in their CC folder with your initials and date on it so we know it's been reviewed.
A14: PROJECTS
A15: Current Projects (Start Date) | B15: Project Manager | C15: Subcontractor & Schedule THIS WEEK | D15: Subcontractor & Schedule NEXT WEEK/FUTURE | E15: Date Inventory Recorded | F15: Weekly Job Summary (Materials Ordered/Arrival Date/Work Performed/Action Taken) | G15: Action Items Next Week (Change Order Submission Needed/Unsafe Conditions/Materials/Opportuities) | H15: Estimated Job Completion Date | I15: CONTRACTS
A16: HRP Haywood II | B16: Wes | C16: Cipriano | D16: Cipriano mid-April-June | F16: Manuel installed handrails on bldg 2 breezeways on 10/17. Waiting on bldgs 1 & 3 to be ready to install breezeway siding and soffit. *SJH - 10/19/22 | H16: 44798 | I16: Zavala contract executed - Villeda need to see if in service truck
A17: HRP Holly Springs | B17: Wes | C17: Abel Gamboa | D17: Abel through June (Crew 1) | F17: Building 1300 concrete poured 8-23. Was supposed to be poured first week of august. Was told on 8-19 by CSM and TC that 1300 was ready. Sent crew on Monday and it was not ready. See 8-23 job report for more info. 1500 concrete to be poured 9-8? | H17: 44795
A18: HRP Pine Forest II (4/16/22) | B18: Wes | D18: Abel Start Beg Aug. | E18: estimated start mid-May | F18: Remaining metal roofing order delivered on Tuesday, 8/30/22. Roofers began installing shingles on bldg 4 and metal on all bldgs. Zavala's measurements and quantities were incorrect - please see action items to the right. *SJH 9/6/22 | G18: Supplementary metal to be picked up between 9/8-9/9. Wes/CJ to take it if it arrives on 9/8, SJH to take it if it arrives on 9/9. *SJH 9/8/22
A19: KMW Church St Lofts (4/2022) | B19: SJH | F19: TKG working on installing corridor base and handrails backing, exterior and storage doors throughout the rest of the building, and hardware kits for units that are ready. *SJH - 10/19/22 | G19: Stay up to date on drywall progress.
A20: KMW Leo Loso/Gateway @ CLT Park $$$ | B20: Wes | C20: Rogelio 4/13 | D20: Cipriano June-August | F20: Cipriano working on courtyard of #2 until the weekend of 10/21, then he's moving to the outside of the building while grading and pool are installed. Hardie truck #11 scheduled for delivery on 10/20/22. Caulk delivered by SJH on 10/14. EZ.21 truck delivery is still en route, no tracking is available and they can't give us any more information on the driver's progress. *SJH - 10/19/22 | G20: Tiger wood planks sourced through Beeson Hardware, per Scott Boswell. Order not yet placed, but distributor has confirmed availability. *SJH 8/15/22
A21: KMW Retreat $$$ | B21: Wes | C21: Abel Gamboa | D21: Through 6-30(Crew 2) | E21: estimated 5/25/22 | F21: Guys not onsite this week due to wtf? 2 weeks to finish columns. waiting on abel for confirmation. | G21: Will need (4) pallets of 4x10 to finish columns. CJ to "make it happen" with other material *WA 8/4/22 | H21: 44788
A22: KMW Springfield | B22: SJH | F22: All preordered materials have arrived and are either on-site or in Wesco warehouse $80K profit - why? missing/miscoded invoices? Extra profit is from bathroom hardware order (not yet placed to save space in shop - pricing held on quote from HD Supply) *SJH - 10/19/22 | G22: Jason B. & Kyle M. Say that the job is likely to CLOSE in October, with work beginning in November. Still no confirmation on start date from KMW - *SJH - 10/19/22
A23: St. Marks | B23: SJH | F23: CO for storage fees approved and charged. Still no definite date on completion of breezeway gypcrete, but Caleb says the building should be ready for us "in two weeks". They have asked us to install gutters on #5 & Pool house ASAP - Rigo might be able to go as early as 10/20/22. *SJH - 10/19/22 | G23: Potential future job - vinyl ceilings in breezeways. Nothing new as of 9/2/22. No decision has been made here yet. *Caleb still doesn't have answer on this - it is not likely that this will be awarded at this point since the property is selling in a few weeks. *SJH - 10/19/22
A24: HRP Waterway | C24: Samir | F24: First 5 Truckloads have been delivered, Next 9 Trucks should arrive on or before 11/29. Also Ordered Breezeway Solid Soffit from Alside. *OCN 10/19/22. Need subcontract agreements - Samir - Hardie picking up 320 of 5/4x12 *OCN 11/10/22 | G24: Need subcontract for Samir*
A25: Carlisle Reno | F25: Job is completed and invoice was sent a month ago. Waiting on payment to be made. *SJH - 10/19/22
A26: PPM - Larchmont (Asheville, NC) | B26: SJH | C26: Rigo | E26: Jason Buffkin | F26: Manuel making corrections to framing repairs, reinstalling jack posts as permanent fixtures with (3) 2x8 beam, installing drywall and getting ready for final inspections. At current pace, Manuel should finish with work on 10/20 or 10/21. Final inspections to be performed at beginning of following week based on inspectors availability. *SJH - 10/19/22 | G26: Sam working with engineer to get pricing together for recently damaged exterior wall. Engineer is to submit repair plan for review on 10/19/22. *SJH - 10/19/22
A27: Springbranch - Becon (Wilmington, NC) | B27: Wes | C27: Rogelio/Rigo | F27: Replace 60 sashes | G27: Waiting for confirmation for materials to arrive.
A28: Upcoming Projects (Start Date) | B28: Project Manager | C28: Subcontractor | F28: Weekly Planning Summary (Materials Ordered/Arrival Date/Change Order Submission Needed/Unsafe Conditions/Opportuities) | G28: Action Items This Week | H28: Estimated Start Date
A29: HRP Brightwood (4/2023)
A30: Wakefield (4/2023) | F30: Sent Pricing hold list to C. Little on 7/11/22. Working on final ordering takeoff in preparation of job ordering. Job is delayed due to extensive blasting that is not yet complete. *SJH 7/11/22 | G30: SJH to follow up with Lansing on duration of pricing hold, as well as with KMW for job progress. Materials need to be ordered before contract pricing increases, but need to hold out as long as possible due to delayed job-start date. *SJH 8/24/22
A31: Melanie Combs house
A32: Pipeline/Bids | B32: Project Manager | C32: Anticipated Subcontractor | D32: Estimated Start Date | E32: Customer Contact | F32: Bid Status | G32: Action Needed/Comments | H32: Estimated Start Date
A33: PPM - Wind Ridge | E33: Jason Buffkin | F33: Get pricing together to complete panel replacement. *SJH - 10/19/22
A34: PPM - Regal Oaks | E34: Jason Buffkin | F34: Need to send Jason pricing for structural repairs ASAP. *SJH - 10/19/22
A35: PPM-Kings Crossing | B35: Not KW | E35: Jason Bufkin | F35: Stair replacement, site steps, sidewalk plates
A36: PPM - Plantation Village | B36: Not KW | E36: Jason Bufkin | F36: Roofing, Windows, Dumpster Fence, Mailbox Posts, 8x8
A37: PPM - Silver Trace Apts | B37: Not KW | E37: Jason Bufkin | F37: Stair Tread replacement, mailbox posts (8x8)
A38: PPM - Little Pee Dee Manor | B38: Not KW | E38: Jason Bufkin | F38: Gazebo Enclosure, Fountain pricing
A39: PPM - Churchwood Apts | B39: Not KW | E39: Jason Bufkin | F39: 2 story bay window replacement , accent siding, aluminum columns per PM
A40: PPM - Greenfield | B40: Not KW | E40: Jason Bufkin | F40: Storage room doors, roof replacement, siding pricing per building
A41: Mountain Glen - Brevard | B41: Not KW | D41: 44795 | E41: KMW | F41: Put off until 2023 | G41: Go measure week of 8/29-9/2/22
A42: KMW - Hartwood Village | B42: Not KW | F42: Roofing, windows, interior doors, hardware, dumpster fence | G42: Waiting on pricing back on interior doors/windows from GCL, ABC
A43: PPM - Westridge Apts. | B43: Not KW | E43: Jason Bufkin
A44: KMW - Wesleyan Homes | B44: Not KW | E44: Kyle McDowell | F44: Initial pricing estimate sent to KMac on Thursday, 5/19/22. *SJH 5/20/22 | G44: Potential start of February/Q1 of 2023
A45: HRP Murrayville | F45: Potentially starting on first week of June - waiting on contract approval. *SJH 5/20/22
A46: HRP Brightwood Farms | F46: Bid Submitted on 5/25/22. *SJH 5/27/22
A47: KMW - Fairway PH2 | F47: Bid sent to C. Binkowski on 11-10-22 *OCN 11/10/22
A48: KMW - Maynard Rd. | F48: Sent pricing revision to C. Binkowski on 7/28/22.
A49: HKJ Magnolia Hills
A50: HKJ Broadstone | F50: Bid has been sent
A51: HKJ Wynslow | F51: Bid has been sent
A52: WC - Pegram Landing Ph2 | F52: Updated quote sent 11/1/22 *OCN
A53: Park @ Aventino | C53: SAVALA | G53: WA WORKING ON BID
A54: Windsor 4th&Elm | F54: Estimate sent *OCN 10/18/22
A55: Ariston Place - Windsor | F55: Awaiting Subcontract *OCN 10/26/22
A56: Ginkgo - Glendare | E56: Paul Sidam | F56: Received return correspondence from Ginkgo that they are reviewing our price, but said that on first glance it is significantly higher. *SJH 8/24/22
A57: Ashley Oaks - Living Well Homes | F57: All currently awarded work has been completed. Property is working through budgets to approve outstanding quotes.
A58: SC Hail Job

Sheet 10.27.22 
A2: Team Meeting
A3: 44861
A4: Present: Wes, Sam, Oscar, Stephanie (who looks very nice today) and The Prince(the fab 5 All HERE)
A5: Topics
A6: 1.) | B6: File Naming Strategies - use descriptive words like "Plans" as this makes it easier to locate later on
A7: 2.) | B7: Siding/roofing/gutter/door/window pricing template (Do we have this? Timeline of initiative?) Nov 15 target date **Uplouded to SharePoint 10/28/22 *OCN**
A8: 3.) | B8: Sub calendar
A9: 4.) | B9: Daily JOB sheets must be filled out. They will cover our ass eventually due to the sorry ass superintendents we are dealing with on 90% of our jobs. Follow up with emails and/or text messages.
A10: 5.) | B10: Prelim Job Checklist - PO - enter prior to job start - Contract (new log - in this workbook)
A11: 6.) | B11: Vehicle Inspections 1998 GMC, 2007 Chevy, Service Truck
A12: 7.) | B12: Time to tidy up office - Trash days Tuesday and Friday - if trash hasn't been taken out to curb when you are leaving the night before or arriving , please take it out.
A13: 8.) | B13: Hotels - ask your subs to send you receipts so you can check to be sure we aren't over charged. Put receipts in their CC folder with your initials and date on it so we know it's been reviewed.
A14: PROJECTS
A15: Current Projects (Start Date) | B15: Project Manager | C15: Subcontractor & Schedule THIS WEEK | D15: Subcontractor & Schedule NEXT WEEK/FUTURE | E15: Date Inventory Recorded | F15: Weekly Job Summary (Materials Ordered/Arrival Date/Work Performed/Action Taken) | G15: Action Items Next Week (Change Order Submission Needed/Unsafe Conditions/Materials/Opportuities) | H15: Estimated Job Completion Date | I15: CONTRACTS
A16: HRP Haywood II | B16: Wes | C16: Cipriano | D16: Cipriano mid-April-June | F16: Manuel installed handrails on bldg 2 breezeways on 10/17. Waiting on bldgs 1 & 3 to be ready to install breezeway siding and soffit. *SJH - 10/19/22 | H16: 44798 | I16: Zavala contract executed - Villeda need to see if in service truck
A17: HRP Holly Springs | B17: Wes | C17: Abel Gamboa | D17: Abel through June (Crew 1) | F17: Building 1300 concrete poured 8-23. Was supposed to be poured first week of august. Was told on 8-19 by CSM and TC that 1300 was ready. Sent crew on Monday and it was not ready. See 8-23 job report for more info. 1500 concrete to be poured 9-8? | H17: 44795
A18: HRP Pine Forest II (4/16/22) | B18: Wes | D18: Abel Start Beg Aug. | E18: estimated start mid-May | F18: Remaining metal roofing order delivered on Tuesday, 8/30/22. Roofers began installing shingles on bldg 4 and metal on all bldgs. Zavala's measurements and quantities were incorrect - please see action items to the right. *SJH 9/6/22 | G18: Supplementary metal to be picked up between 9/8-9/9. Wes/CJ to take it if it arrives on 9/8, SJH to take it if it arrives on 9/9. *SJH 9/8/22
A19: KMW Church St Lofts (4/2022) | B19: SJH | F19: TKG working on installing corridor base and handrails backing, exterior and storage doors throughout the rest of the building, and hardware kits for units that are ready. *SJH - 10/19/22 | G19: Stay up to date on drywall progress.
A20: KMW Leo Loso/Gateway @ CLT Park $$$ | B20: Wes | C20: Rogelio 4/13 | D20: Cipriano June-August | F20: Cipriano working on courtyard of #2 until the weekend of 10/21, then he's moving to the outside of the building while grading and pool are installed. Hardie truck #11 scheduled for delivery on 10/20/22. Caulk delivered by SJH on 10/14. EZ.21 truck delivery is still en route, no tracking is available and they can't give us any more information on the driver's progress. *SJH - 10/19/22 | G20: Tiger wood planks sourced through Beeson Hardware, per Scott Boswell. Order not yet placed, but distributor has confirmed availability. *SJH 8/15/22
A21: KMW Retreat $$$ | B21: Wes | C21: Abel Gamboa | D21: Through 6-30(Crew 2) | E21: estimated 5/25/22 | F21: Guys not onsite this week due to wtf? 2 weeks to finish columns. waiting on abel for confirmation. | G21: Will need (4) pallets of 4x10 to finish columns. CJ to "make it happen" with other material *WA 8/4/22 | H21: 44788
A22: KMW Springfield | B22: SJH | F22: All preordered materials have arrived and are either on-site or in Wesco warehouse $80K profit - why? missing/miscoded invoices? Extra profit is from bathroom hardware order (not yet placed to save space in shop - pricing held on quote from HD Supply) *SJH - 10/19/22 | G22: Jason B. & Kyle M. Say that the job is likely to CLOSE in October, with work beginning in November. Still no confirmation on start date from KMW - *SJH - 10/19/22
A23: St. Marks | B23: SJH | F23: CO for storage fees approved and charged. Still no definite date on completion of breezeway gypcrete, but Caleb says the building should be ready for us "in two weeks". They have asked us to install gutters on #5 & Pool house ASAP - Rigo might be able to go as early as 10/20/22. *SJH - 10/19/22 | G23: Potential future job - vinyl ceilings in breezeways. Nothing new as of 9/2/22. No decision has been made here yet. *Caleb still doesn't have answer on this - it is not likely that this will be awarded at this point since the property is selling in a few weeks. *SJH - 10/19/22
A24: HRP Waterway | F24: First 5 Truckloads have been delivered, Next 9 Trucks should arrive on or before 11/29. Also Ordered Breezeway Solid Soffit from Alside. *OCN 10/19/22. Need subcontract agreements - Samir
A25: Carlisle Reno | F25: Job is completed and invoice was sent a month ago. Waiting on payment to be made. *SJH - 10/19/22
A26: PPM - Larchmont (Asheville, NC) | B26: SJH | C26: Rigo | E26: Jason Buffkin | F26: Manuel making corrections to framing repairs, reinstalling jack posts as permanent fixtures with (3) 2x8 beam, installing drywall and getting ready for final inspections. At current pace, Manuel should finish with work on 10/20 or 10/21. Final inspections to be performed at beginning of following week based on inspectors availability. *SJH - 10/19/22 | G26: Sam working with engineer to get pricing together for recently damaged exterior wall. Engineer is to submit repair plan for review on 10/19/22. *SJH - 10/19/22
A27: Springbranch - Becon (Wilmington, NC) | B27: Wes | C27: Rogelio/Rigo | F27: Replace 60 sashes | G27: Waiting for confirmation for materials to arrive.
A28: Upcoming Projects (Start Date) | B28: Project Manager | C28: Subcontractor | F28: Weekly Planning Summary (Materials Ordered/Arrival Date/Change Order Submission Needed/Unsafe Conditions/Opportuities) | G28: Action Items This Week | H28: Estimated Start Date
A29: HRP Brightwood (4/2023)
A30: Wakefield (4/2023) | F30: Sent Pricing hold list to C. Little on 7/11/22. Working on final ordering takeoff in preparation of job ordering. Job is delayed due to extensive blasting that is not yet complete. *SJH 7/11/22 | G30: SJH to follow up with Lansing on duration of pricing hold, as well as with KMW for job progress. Materials need to be ordered before contract pricing increases, but need to hold out as long as possible due to delayed job-start date. *SJH 8/24/22
A31: Melanie Combs house
A32: Pipeline/Bids | B32: Project Manager | C32: Anticipated Subcontractor | D32: Estimated Start Date | E32: Customer Contact | F32: Bid Status | G32: Action Needed/Comments | H32: Estimated Start Date
A33: PPM - Wind Ridge | E33: Jason Buffkin | F33: Get pricing together to complete panel replacement. *SJH - 10/19/22
A34: PPM - Regal Oaks | E34: Jason Buffkin | F34: Need to send Jason pricing for structural repairs ASAP. *SJH - 10/19/22
A35: PPM-Kings Crossing | B35: Not KW | E35: Jason Bufkin | F35: Stair replacement, site steps, sidewalk plates
A36: PPM - Plantation Village | B36: Not KW | E36: Jason Bufkin | F36: Roofing, Windows, Dumpster Fence, Mailbox Posts, 8x8
A37: PPM - Silver Trace Apts | B37: Not KW | E37: Jason Bufkin | F37: Stair Tread replacement, mailbox posts (8x8)
A38: PPM - Little Pee Dee Manor | B38: Not KW | E38: Jason Bufkin | F38: Gazebo Enclosure, Fountain pricing
A39: PPM - Churchwood Apts | B39: Not KW | E39: Jason Bufkin | F39: 2 story bay window replacement , accent siding, aluminum columns per PM
A40: PPM - Greenfield | B40: Not KW | E40: Jason Bufkin | F40: Storage room doors, roof replacement, siding pricing per building
A41: Mountain Glen - Brevard | B41: Not KW | D41: 44795 | E41: KMW | F41: Put off until 2023 | G41: Go measure week of 8/29-9/2/22
A42: KMW - Hartwood Village | B42: Not KW | F42: Roofing, windows, interior doors, hardware, dumpster fence | G42: Waiting on pricing back on interior doors/windows from GCL, ABC
A43: PPM - Westridge Apts. | B43: Not KW | E43: Jason Bufkin
A44: KMW - Wesleyan Homes | B44: Not KW | E44: Kyle McDowell | F44: Initial pricing estimate sent to KMac on Thursday, 5/19/22. *SJH 5/20/22 | G44: Potential start of February/Q1 of 2023
A45: HRP Murrayville | F45: Potentially starting on first week of June - waiting on contract approval. *SJH 5/20/22
A46: HRP Brightwood Farms | F46: Bid Submitted on 5/25/22. *SJH 5/27/22
A47: KMW - Maynard Rd. | F47: Sent pricing revision to C. Binkowski on 7/28/22.
A48: HKJ Magnolia Hills
A49: HKJ Broadstone | F49: Bid has been sent
A50: HKJ Wynslow | F50: Bid has been sent
A51: WC - Pegram Landing Ph2 | F51: Updated quote sent 11/1/22 *OCN
A52: Park @ Aventino | C52: SAVALA | G52: WA WORKING ON BID
A53: Windsor 4th&Elm | F53: Estimate sent *OCN 10/18/22
A54: Ariston Place - Windsor | F54: Awaiting Subcontract *OCN 10/26/22
A55: Ginkgo - Glendare | E55: Paul Sidam | F55: Received return correspondence from Ginkgo that they are reviewing our price, but said that on first glance it is significantly higher. *SJH 8/24/22
A56: Ashley Oaks - Living Well Homes | F56: All currently awarded work has been completed. Property is working through budgets to approve outstanding quotes.
A57: SC Hail Job

Sheet 10.19.22
A2: Team Meeting
A3: 44853
A4: Present: Wes, Sam, Oscar, Stephanie (who looks very nice today) and The Prince(the fab 5 All HERE)
A5: Topics
A6: 1.) | B6: Contract Review - Subcontractor Contracts - Due 6/1/22 Haywood II Zavala/Cipriano/Manuel; Holly Springs - Abel; Retreat @ Carteret Abel; Charlotte Park - Villeda; Crest Villeda & Yohan; Pine Forest II Abel & Zavala; Hillstone; WindRidge - Manuel (Bolded if prepared; green if executed)
A7: 2.) | B7: Siding/roofing/gutter/door/window pricing template
A8: 3.) | B8: Sub calendar
A9: 4.) | B9: Daily JOB sheets must be filled out. They will cover our ass eventually due to the sorry ass superintendents we are dealing with on 90% of our jobs. Follow up with emails and/or text messages.
A10: 5.) | B10: Job names on invoices - need your help - text job names to subs and ask them to reference them on their invoices rather than "Asheboro or Myrtle Beach"
A11: 6.) | B11: Vehicle Inspections 1998 GMC, 2007 Chevy, Service Truck
A12: 7.) | B12: Time to tidy up office - Trash days Tuesday and Friday - if trash hasn't been taken out to curb when you are leaving the night before or arriving , please take it out.
A13: 8.) | B13: Hotels - ask your subs to send you receipts so you can check to be sure we aren't over charged. Put receipts in their CC folder with your initials and date on it so we know it's been reviewed.
A14: PROJECTS
A15: Current Projects (Start Date) | B15: Project Manager | C15: Subcontractor & Schedule THIS WEEK | D15: Subcontractor & Schedule NEXT WEEK/FUTURE | E15: Date Inventory Recorded | F15: Weekly Job Summary (Materials Ordered/Arrival Date/Work Performed/Action Taken) | G15: Action Items Next Week (Change Order Submission Needed/Unsafe Conditions/Materials/Opportuities) | H15: Estimated Job Completion Date | I15: CONTRACTS
A16: HRP Haywood II | B16: Wes | C16: Cipriano | D16: Cipriano mid-April-June | F16: Manuel installed handrails on bldg 2 breezeways on 10/17. Waiting on bldgs 1 & 3 to be ready to install breezeway siding and soffit. *SJH - 10/19/22 | H16: 44798
A17: HRP Holly Springs | B17: Wes | C17: Abel Gamboa | D17: Abel through June (Crew 1) | F17: Building 1300 concrete poured 8-23. Was supposed to be poured first week of august. Was told on 8-19 by CSM and TC that 1300 was ready. Sent crew on Monday and it was not ready. See 8-23 job report for more info. 1500 concrete to be poured 9-8? | H17: 44795
A18: HRP Pine Forest II (4/16/22) | B18: Wes | D18: Abel Start Beg Aug. | E18: estimated start mid-May | F18: Remaining metal roofing order delivered on Tuesday, 8/30/22. Roofers began installing shingles on bldg 4 and metal on all bldgs. Zavala's measurements and quantities were incorrect - please see action items to the right. *SJH 9/6/22 | G18: Supplementary metal to be picked up between 9/8-9/9. Wes/CJ to take it if it arrives on 9/8, SJH to take it if it arrives on 9/9. *SJH 9/8/22
A19: KMW Church St Lofts (4/2022) | B19: SJH | F19: TKG working on installing corridor base and handrails backing, exterior and storage doors throughout the rest of the building, and hardware kits for units that are ready. *SJH - 10/19/22 | G19: Stay up to date on drywall progress.
A20: KMW Leo Loso/Gateway @ CLT Park $$$ | B20: Wes | C20: Rogelio 4/13 | D20: Cipriano June-August | F20: Cipriano working on courtyard of #2 until the weekend of 10/21, then he's moving to the outside of the building while grading and pool are installed. Hardie truck #11 scheduled for delivery on 10/20/22. Caulk delivered by SJH on 10/14. EZ.21 truck delivery is still en route, no tracking is available and they can't give us any more information on the driver's progress. *SJH - 10/19/22 | G20: Tiger wood planks sourced through Beeson Hardware, per Scott Boswell. Order not yet placed, but distributor has confirmed availability. *SJH 8/15/22
A21: KMW Retreat $$$ | B21: Wes | C21: Abel Gamboa | D21: Through 6-30(Crew 2) | E21: estimated 5/25/22 | F21: Guys not onsite this week due to wtf? 2 weeks to finish columns. waiting on abel for confirmation. | G21: Will need (4) pallets of 4x10 to finish columns. CJ to "make it happen" with other material *WA 8/4/22 | H21: 44788
A22: KMW Springfield | B22: SJH | F22: All preordered materials have arrived and are either on-site or in Wesco warehouse $80K profit - why? missing/miscoded invoices? Extra profit is from bathroom hardware order (not yet placed to save space in shop - pricing held on quote from HD Supply) *SJH - 10/19/22 | G22: Jason B. & Kyle M. Say that the job is likely to CLOSE in October, with work beginning in November. Still no confirmation on start date from KMW - *SJH - 10/19/22
A23: St. Marks | B23: SJH | F23: CO for storage fees approved and charged. Still no definite date on completion of breezeway gypcrete, but Caleb says the building should be ready for us "in two weeks". They have asked us to install gutters on #5 & Pool house ASAP - Rigo might be able to go as early as 10/20/22. *SJH - 10/19/22 | G23: Potential future job - vinyl ceilings in breezeways. Nothing new as of 9/2/22. No decision has been made here yet. *Caleb still doesn't have answer on this - it is not likely that this will be awarded at this point since the property is selling in a few weeks. *SJH - 10/19/22
A24: HRP Waterway | F24: First Truck delivery 10/13/22, All Siding Trucks have been ordered. Also Ordered Breezeway Solid Soffit from Alside. *OCN 10/19/22. Need subcontract agreements - Abel
A25: Carlisle Reno | F25: Job is completed and invoice was sent a month ago. Waiting on payment to be made. *SJH - 10/19/22
A26: PPM - Larchmont (Asheville, NC) | B26: SJH | C26: Rigo | E26: Jason Buffkin | F26: Manuel making corrections to framing repairs, reinstalling jack posts as permanent fixtures with (3) 2x8 beam, installing drywall and getting ready for final inspections. At current pace, Manuel should finish with work on 10/20 or 10/21. Final inspections to be performed at beginning of following week based on inspectors availability. *SJH - 10/19/22 | G26: Sam working with engineer to get pricing together for recently damaged exterior wall. Engineer is to submit repair plan for review on 10/19/22. *SJH - 10/19/22
A27: Springbranch - Becon (Wilmington, NC) | B27: Wes | C27: Rogelio/Rigo | F27: Replace 60 sashes | G27: Waiting for confirmation for materials to arrive.
A28: Upcoming Projects (Start Date) | B28: Project Manager | C28: Subcontractor | F28: Weekly Planning Summary (Materials Ordered/Arrival Date/Change Order Submission Needed/Unsafe Conditions/Opportuities) | G28: Action Items This Week | H28: Estimated Start Date
A29: HRP Brightwood (4/2023)
A30: Wakefield (4/2023) | F30: Sent Pricing hold list to C. Little on 7/11/22. Working on final ordering takeoff in preparation of job ordering. Job is delayed due to extensive blasting that is not yet complete. *SJH 7/11/22 | G30: SJH to follow up with Lansing on duration of pricing hold, as well as with KMW for job progress. Materials need to be ordered before contract pricing increases, but need to hold out as long as possible due to delayed job-start date. *SJH 8/24/22
A31: Melanie Combs house
A32: Pipeline/Bids | B32: Project Manager | C32: Anticipated Subcontractor | D32: Estimated Start Date | E32: Customer Contact | F32: Bid Status | G32: Action Needed/Comments | H32: Estimated Start Date
A33: PPM - Wind Ridge | E33: Jason Buffkin | F33: Get pricing together to complete panel replacement. *SJH - 10/19/22
A34: PPM - Regal Oaks | E34: Jason Buffkin | F34: Need to send Jason pricing for structural repairs ASAP. *SJH - 10/19/22
A35: PPM-Kings Crossing | B35: Not KW | E35: Jason Bufkin | F35: Stair replacement, site steps, sidewalk plates
A36: PPM - Plantation Village | B36: Not KW | E36: Jason Bufkin | F36: Roofing, Windows, Dumpster Fence, Mailbox Posts, 8x8
A37: PPM - Silver Trace Apts | B37: Not KW | E37: Jason Bufkin | F37: Stair Tread replacement, mailbox posts (8x8)
A38: PPM - Little Pee Dee Manor | B38: Not KW | E38: Jason Bufkin | F38: Gazebo Enclosure, Fountain pricing
A39: PPM - Churchwood Apts | B39: Not KW | E39: Jason Bufkin | F39: 2 story bay window replacement , accent siding, aluminum columns per PM
A40: PPM - Greenfield | B40: Not KW | E40: Jason Bufkin | F40: Storage room doors, roof replacement, siding pricing per building
A41: Mountain Glen - Brevard | B41: Not KW | D41: 44795 | E41: KMW | F41: Put off until 2023 | G41: Go measure week of 8/29-9/2/22
A42: KMW - Hartwood Village | B42: Not KW | F42: Roofing, windows, interior doors, hardware, dumpster fence | G42: Waiting on pricing back on interior doors/windows from GCL, ABC
A43: PPM - Westridge Apts. | B43: Not KW | E43: Jason Bufkin
A44: KMW - Wesleyan Homes | B44: Not KW | E44: Kyle McDowell | F44: Initial pricing estimate sent to KMac on Thursday, 5/19/22. *SJH 5/20/22 | G44: Potential start of February/Q1 of 2023
A45: HRP Murrayville | F45: Potentially starting on first week of June - waiting on contract approval. *SJH 5/20/22
A46: HRP Brightwood Farms | F46: Bid Submitted on 5/25/22. *SJH 5/27/22
A47: KMW - Maynard Rd. | F47: Sent pricing revision to C. Binkowski on 7/28/22.
A48: HKJ Magnolia Hills
A49: HKJ Broadstone | F49: Bid has been sent
A50: HKJ Wynslow | F50: Bid has been sent
A51: Park @ Aventino | C51: SAVALA | G51: WA WORKING ON BID
A52: Windsor 4th&Elm | F52: EZ Trim Quote from Southern Carlson recieved 9-7-22 Need to send revised Estimate *OCN 9/8/22
A53: Ariston Place - Windsor | F53: Bid was sent
A54: Ginkgo - Glendare | E54: Paul Sidam | F54: Received return correspondence from Ginkgo that they are reviewing our price, but said that on first glance it is significantly higher. *SJH 8/24/22
A55: Ashley Oaks - Living Well Homes | F55: All currently awarded work has been completed. Property is working through budgets to approve outstanding quotes.
A56: SC Hail Job

Sheet 9.12.22
A2: Team Meeting
A3: 44812
A4: Present: Wes, Sam, Oscar, Stephanie (who looks very nice today) and The Prince(the fab 5 All HERE)
A5: Topics
A6: 1.) | B6: Contract Review - Subcontractor Contracts - Due 6/1/22 Haywood II Zavala/Cipriano/Manuel; Holly Springs - Abel; Retreat @ Carteret Abel; Charlotte Park - Villeda; Crest Villeda & Yohan; Pine Forest II Abel & Zavala; Hillstone; WindRidge - Manuel (Bolded if prepared; green if executed)
A7: 2.) | B7: Siding/roofing/gutter/door/window pricing template
A8: 3.) | B8: Sub calendar
A9: 4.) | B9: Daily JOB sheets must be filled out. They will cover our ass eventually due to the sorry ass superintendents we are dealing with on 90% of our jobs. Follow up with emails and/or text messages.
A10: 5.) | B10: Job names on invoices - need your help - text job names to subs and ask them to reference them on their invoices rather than "Asheboro or Myrtle Beach"
A11: 6.) | B11: Vehicle Inspections 1998 GMC, 2007 Chevy, Service Truck
A12: 7.) | B12: Time to tidy up office - Trash days Tuesday and Friday - if trash hasn't been taken out to curb when you are leaving the night before or arriving , please take it out.
A13: 8.) | B13: Hotels - ask your subs to send you receipts so you can check to be sure we aren't over charged. Put receipts in their CC folder with your initials and date on it so we know it's been reviewed.
A14: PROJECTS
A15: Current Projects (Start Date) | B15: Project Manager | C15: Subcontractor & Schedule THIS WEEK | D15: Subcontractor & Schedule NEXT WEEK/FUTURE | E15: Date Inventory Recorded | F15: Weekly Job Summary (Materials Ordered/Arrival Date/Work Performed/Action Taken) | G15: Action Items Next Week (Change Order Submission Needed/Unsafe Conditions/Materials/Opportuities) | H15: Estimated Job Completion Date | I15: CONTRACTS
A16: HRP Haywood II | B16: Wes | C16: Cipriano | D16: Cipriano mid-April-June | F16: Rigo working on bldg 2 & 3 gutters. Manuel beginning breezeway siding and soffit installation. *SJH 9/6/22 Manuel to finish first 2 floors of bldg 2 by CoB Friday, 9/9/22. *SJH 9/8/22 | G16: Sam Delivered Heather J Channel (10 boxes) & trim coil (15 rolls) on Wednesday, 9/7/22. | H16: 44798
A17: HRP Holly Springs | B17: Wes | C17: Abel Gamboa | D17: Abel through June (Crew 1) | F17: Building 1300 concrete poured 8-23. Was supposed to be poured first week of august. Was told on 8-19 by CSM and TC that 1300 was ready. Sent crew on Monday and it was not ready. See 8-23 job report for more info. 1500 concrete to be poured 9-8? | H17: 44795
A18: HRP Pine Forest II (4/16/22) | B18: Wes | D18: Abel Start Beg Aug. | E18: estimated start mid-May | F18: Remaining metal roofing order delivered on Tuesday, 8/30/22. Roofers began installing shingles on bldg 4 and metal on all bldgs. Zavala's measurements and quantities were incorrect - please see action items to the right. *SJH 9/6/22 | G18: Supplementary metal to be picked up between 9/8-9/9. Wes/CJ to take it if it arrives on 9/8, SJH to take it if it arrives on 9/9. *SJH 9/8/22
A19: KMW Church St Lofts (4/2022) | B19: SJH | F19: TKG is on-site installing hardware and remaining trim for first sets of units (after painting). 1st floor area B & C to begin doors and trim on Wednesday, 9/7/22. Manuel completed temporary window framing and new trim CO on Friday, 9/2/22. Drywall and paint crews SUCK! Drywall is way behind and paint is coming in while we're working in units. No Bueno!! *SJH 9/6/22 | G19: Stay up to date on drywall progress.
A20: KMW Leo Loso/Gateway @ CLT Park $$$ | B20: Wes | C20: Rogelio 4/13 | D20: Cipriano June-August | F20: First deliveries still show 9/9, but Hardie says it will not likely ship on this date due to not yet having a carrier in place. C. Little to update once material has been picked up by carrier *SJH 9/8/22 | G20: Tiger wood planks sourced through Beeson Hardware, per Scott Boswell. Order not yet placed, but distributor has confirmed availability. *SJH 8/15/22
A21: KMW Retreat $$$ | B21: Wes | C21: Abel Gamboa | D21: Through 6-30(Crew 2) | E21: estimated 5/25/22 | F21: Guys not onsite this week due to wtf? 2 weeks to finish columns. waiting on abel for confirmation. | G21: Will need (4) pallets of 4x10 to finish columns. CJ to "make it happen" with other material *WA 8/4/22 | H21: 44788
A22: KMW Springfield | B22: SJH | F22: All preordered materials have arrived and are either on-site or in Wesco warehouse $80K profit - why? missing/miscoded invoices? Sam to review job cost. | G22: Jason B. & Kyle M. Say that the job is likely to CLOSE in September, with work beginning in October *SJH 7/19/22
